Workbook
Name _DLX1.USE: #REF!
Name _DLX10.USE: #REF!
Name _DLX2.USE: #REF!
Name _DLX3.USE: #REF!
Name _DLX4.USE: #REF!
Name _DLX5.USE: #REF!
Name _DLX6.USE: #REF!
Name _DLX8.USE: #REF!
Name aaddr: #REF!
Name AdjustedBCA: [14]Prog!$R$25
Name AdjustedBCAIssuer: [14]Prog!$R$14
Name AdjustedBCAParent: [14]Prog!$R$18
Name annual: #REF!
Name ASheet: #REF!
Name AUS_BANK_AUSTRIA: #REF!
Name AUS_ERSTE: #REF!
Name AUS_RAIFF: #REF!
Name CBRatingOutlook: [14]Prog!$R$22
Name ChartData: [19]Rate_expectations_data_old!$A$9:$AP$5000
Name Chartdata_new: [19]Rate_expectations_data!$A$9:$GD$5000
Name CollateralScoreBlendedState: [14]Prog!$T$30
Name CollateralScoreBlendedValue: [14]Prog!$R$30
Name CollateralScoreExcludingSystemicRiskState: [14]Prog!$T$31
Name CollateralScoreExcludingSystemicRiskValue: [14]Prog!$R$31
Name CollateralTypeMain: [14]Prog!$R$19
Name CommercialRelative: [14]Prog!$AC$4
Name COMMODITIES: #REF!
Name Consensus: Priv [20]Con!$A$12
Name Consensus: Priv [20]Con!$A$12
Name Consensus: Priv [20]Con!$A$12
Name Consensus: Priv [20]Con!$A$12
Name Contact: [14]Prog!$R$4
Name CoveredBondAnchor: [14]Prog!$R$26
Name CurrentOCState: [14]Prog!$T$41
Name CurrentOCValue: [14]Prog!$R$41
Name Cutoff_date: [21]Evaluation!$O$3
Name CutoffDate: [14]Prog!$R$6
Name data1: [19]CDS_data!$AJ$6:$AO$1120
Name Data2: #REF!
Name data3: [22]data!$S$6:$X$1120
Name data4: #REF!
Name DebtCushion: [14]Prog!$R$27
Name DefaultCurrency: [14]Prog!$R$8
Name ESP_BBVA: #REF!
Name ESP_POPULAR: #REF!
Name ESP_SANTANDER: #REF!
Name EurLiborCurve: '[19]Euro LIBOR Curve Data'!$A$7:$J$2000
Name Eurliborcurve_new: #REF!
Name FixedRateAssetsInCoverPoolValue: [14]Prog!$R$55
Name FixedRateCoveredBondsOutstandingValue: [14]Prog!$R$56
Name FRA_BNP: #REF!
Name FRA_CA: #REF!
Name FRA_NATIXIS: #REF!
Name FRA_SG: #REF!
Name GVal: #REF!
Name High: Priv [20]Con!$A$112
Name High: Priv [20]Con!$A$112
Name High: Priv [20]Con!$A$112
Name High: Priv [20]Con!$A$112
Name InterestRateSwapProvider: [14]Prog!$R$60

Sheet ICS_A-IRB
B3: Capital Charge - Credit Risk (ICS - based on Basel III, Internal Ratings-Based Approach) | N3: 0 | O3: Moody's Aaa | S3: 1 | T3: Moody's Aa | X3: 2 | Y3: Moody's A | AC3: 3 | AD3: Moody's Baa | AH3: 4 | AI3: Moody's Ba | AM3: 5 | AN3: Moody's B | AT3: Unrated | AU3: Moody's project loan database (total sample)
B4: (In percent) | N4: PD | O4: Correlation (R) [depends on PD] | P4: Maturity adj. (M) [depends on PD] | Q4: Cap. Requirement (K) | S4: PD | T4: Correlation (R) [depends on PD] | U4: Maturity adj. (M) [depends on PD] | V4: Cap. Requirement (K) | X4: PD | Y4: Correlation (R) [depends on PD] | Z4: Maturity adj. (M) [depends on PD] | AA4: Cap. Requirement (K) | AC4: PD | AD4: Correlation (R) [depends on PD] | AE4: Maturity adj. (M) [depends on PD] | AF4: Cap. Requirement (K) | AH4: PD | AI4: Correlation (R) [depends on PD] | AJ4: Maturity adj. (M) [depends on PD] | AK4: Cap. Requirement (K) | AM4: PD | AN4: Correlation (R) [depends on PD] | AO4: Maturity adj. (M) [depends on PD] | AP4: Cap. Requirement (K) | AT4: PD | AU4: Correlation (R) [depends on PD] | AV4: Maturity adj. (M) [depends on PD] | AW4: Cap. Requirement (K)
D5: Credit Quality Step (CQS)
B6: Maturity (Years) | D6: ='[2]EIOPA - Nongreen'!D22 -> 0 | E6: ='[2]EIOPA - Nongreen'!F22 -> 1 | F6: ='[2]EIOPA - Nongreen'!H22 -> 2 | G6: ='[2]EIOPA - Nongreen'!J22 -> 3 | H6: ='[2]EIOPA - Nongreen'!L22 -> 4 | I6: 5 | K6: ='[2]EIOPA - Nongreen'!R22 -> Unrated | N6: LGD | S6: LGD | X6: LGD | AC6: LGD | AH6: LGD | AM6: LGD | AT6: LGD
D8: Corporate Exposures - Non-financial Corporate Debt Securities - Global | N8: =1-'[2]Moody''s Global Infra and Corp D'!P103 -> 0.62 | S8: =N8 -> 0.62 | X8: =N8 -> 0.62 | AC8: =X8 -> 0.62 | AH8: =X8 -> 0.62 | AM8: =AC8 -> 0.62 | AN8: stdev(rec.) | AO8: ='[2]Moody''s Global Infra and Corp D'!K138 -> 0.337 | AP8: =AO8*(AM8/(1-AM8)) -> 0.54984211
B9: 1 | D9: =Q9*100 -> 0.049015661 | E9: =V9*100 -> 0.049015661 | F9: =AA9*100 -> 0.60703136 | G9: =AF9*100 -> 2.4747913 | H9: =AK9*100 -> 8.0059045 | I9: =AP9*100 -> 17.537063 | K9: =H9 -> 8.0059045 | N9: ='[2]Moody''s Global Infra and Corp D'!$AN$61 -> 1e-05 | O9: =0.12*(1-EXP(-50*$N9))/(1-EXP(-50))+0.24*(1-(1-EXP(-50*$N9))/(1-EXP(-50))) -> 0.23994001 | P9: =(0.11852-0.05478*LN($N9))^2 -> 0.56129773 | Q9: =(N$8*NORMSDIST((1-O9)^(-0.5)*NORMSINV($N9)+(O9/(1-O9))^(0.5)*NORMSINV(0.999))-$N9*N$8)*((1+($B9-2.5)*P9)/(1-1.5*P9)) -> 0.00049015661 | S9: ='[2]Moody''s Global Infra and Corp D'!$AN$62 -> 1e-05 | T9: =0.12*(1-EXP(-50*$S9))/(1-EXP(-50))+0.24*(1-(1-EXP(-50*$S9))/(1-EXP(-50))) -> 0.23994001 | U9: =(0.11852-0.05478*LN($S9))^2 -> 0.56129773 | V9: =(S$8*NORMSDIST((1-T9)^(-0.5)*NORMSINV($S9)+(T9/(1-T9))^(0.5)*NORMSINV(0.999))-$S9*S$8)*((1+($B9-2.5)*U9)/(1-1.5*U9)) -> 0.00049015661 | X9: ='[2]Moody''s Global Infra and Corp D'!$AN$63 -> 0.0002 | Y9: =0.12*(1-EXP(-50*$X9))/(1-EXP(-50))+0.24*(1-(1-EXP(-50*$X9))/(1-EXP(-50))) -> 0.23880598 | Z9: =(0.11852-0.05478*LN($X9))^2 -> 0.34233246 | AA9: =(X$8*NORMSDIST((1-Y9)^(-0.5)*NORMSINV($X9)+(Y9/(1-Y9))^(0.5)*NORMSINV(0.999))-$X9*X$8)*((1+($B9-2.5)*Z9)/(1-1.5*Z9)) -> 0.0060703136 | AB9: =AC9 -> 0.0013 | AC9: ='[2]Moody''s Global Infra and Corp D'!$AN$64 -> 0.0013 | AD9: =0.12*(1-EXP(-50*$AC9))/(1-EXP(-50))+0.24*(1-(1-EXP(-50*$AC9))/(1-EXP(-50))) -> 0.2324481 | AE9: =(0.11852-0.05478*LN($AC9))^2 -> 0.23285886 | AF9: =(AC$8*NORMSDIST((1-AD9)^(-0.5)*NORMSINV($AC9)+(AD9/(1-AD9))^(0.5)*NORMSINV(0.999))-$AC9*AC$8)*((1+($B9-2.5)*AE9)/(1-1.5*AE9)) -> 0.024747913 | AG9: =AH9 -> 0.0098 | AH9: ='[2]Moody''s Global Infra and Corp D'!$AN$65 -> 0.0098 | AI9: =0.12*(1-EXP(-50*$AH9))/(1-EXP(-50))+0.24*(1-(1-EXP(-50*$AH9))/(1-EXP(-50))) -> 0.19351517 | AJ9: =(0.11852-0.05478*LN($AH9))^2 -> 0.13830807 | AK9: =(AH$8*NORMSDIST((1-AI9)^(-0.5)*NORMSINV($AH9)+(AI9/(1-AI9))^(0.5)*NORMSINV(0.999))-$AH9*AH$8)*((1+($B9-2.5)*AJ9)/(1-1.5*AJ9)) -> 0.080059045 | AL9: =MAX(AM9,0.005) -> 0.0377 | AM9: ='[2]Moody''s Global Infra and Corp D'!$AN$66 -> 0.0377 | AN9: =0.12*(1-EXP(-50*$AH9))/(1-EXP(-50))+0.24*(1-(1-EXP(-50*$AH9))/(1-EXP(-50))) -> 0.19351517 | AO9: =(0.11852-0.05478*LN($AM9))^2 -> 0.088860065 | AP9: =(AM$8*NORMSDIST((1-AN9)^(-0.5)*NORMSINV($AM9)+(AN9/(1-AN9))^(0.5)*NORMSINV(0.999))-$AM9*AM$8)*((1+($B9-2.5)*AO9)/(1-1.5*AO9)) -> 0.17537063
B10: 2 | D10: =Q10*100 -> 0.22308581 | E10: =V10*100 -> 0.66907318 | F10: =AA10*100 -> 2.8649698 | G10: =AF10*100 -> 5.9695899 | H10: =AK10*100 -> 13.188898 | I10: =AP10*100 -> 23.109241 | K10: =H10 -> 13.188898 | N10: ='[2]Moody''s Global Infra and Corp D'!$AO$61 -> 1e-05 | O10: =0.12*(1-EXP(-50*$N10))/(1-EXP(-50))+0.24*(1-(1-EXP(-50*$N10))/(1-EXP(-50))) -> 0.23994001 | P10: =(0.11852-0.05478*LN($N10))^2 -> 0.56129773 | Q10: =(N$8*NORMSDIST((1-O10)^(-0.5)*NORMSINV($N10)+(O10/(1-O10))^(0.5)*NORMSINV(0.999))-$N10*N$8)*((1+($B10-2.5)*P10)/(1-1.5*P10)) -> 0.0022308581 | S10: ='[2]Moody''s Global Infra and Corp D'!$AO$62 -> 0.0001 | T10: =0.12*(1-EXP(-50*$S10))/(1-EXP(-50))+0.24*(1-(1-EXP(-50*$S10))/(1-EXP(-50))) -> 0.2394015 | U10: =(0.11852-0.05478*LN($S10))^2 -> 0.38820681 | V10: =(S$8*NORMSDIST((1-T10)^(-0.5)*NORMSINV($S10)+(T10/(1-T10))^(0.5)*NORMSINV(0.999))-$S10*S$8)*((1+($B10-2.5)*U10)/(1-1.5*U10)) -> 0.0066907318 | X10: ='[2]Moody''s Global Infra and Corp D'!$AO$63 -> 0.001 | Y10: =0.12*(1-EXP(-50*$X10))/(1-EXP(-50))+0.24*(1-(1-EXP(-50*$X10))/(1-EXP(-50))) -> 0.23414753 | Z10: =(0.11852-0.05478*LN($X10))^2 -> 0.24693628 | AA10: =(X$8*NORMSDIST((1-Y10)^(-0.5)*NORMSINV($X10)+(Y10/(1-Y10))^(0.5)*NORMSINV(0.999))-$X10*X$8)*((1+($B10-2.5)*Z10)/(1-1.5*Z10)) -> 0.028649698 | AB10: =MAX(AC10-AC9,0) -> 0.0023 | AC10: ='[2]Moody''s Global Infra and Corp D'!$AO$64 -> 0.0036 | AD10: =0.12*(1-EXP(-50*$AC10))/(1-EXP(-50))+0.24*(1-(1-EXP(-50*$AC10))/(1-EXP(-50))) -> 0.22023243 | AE10: =(0.11852-0.05478*LN($AC10))^2 -> 0.18212177 | AF10: =(AC$8*NORMSDIST((1-AD10)^(-0.5)*NORMSINV($AC10)+(AD10/(1-AD10))^(0.5)*NORMSINV(0.999))-$AC10*AC$8)*((1+($B10-2.5)*AE10)/(1-1.5*AE10)) -> 0.059695899 | AG10: =MAX(AH10-AH9,0) -> 0.0181 | AH10: ='[2]Moody''s Global Infra and Corp D'!$AO$65 -> 0.0279 | AI10: =0.12*(1-EXP(-50*$AH10))/(1-EXP(-50))+0.24*(1-(1-EXP(-50*$AH10))/(1-EXP(-50))) -> 0.14973996 | AJ10: =(0.11852-0.05478*LN($AH10))^2 -> 0.098963511 | AK10: =(AH$8*NORMSDIST((1-AI10)^(-0.5)*NORMSINV($AH10)+(AI10/(1-AI10))^(0.5)*NORMSINV(0.999))-$AH10*AH$8)*((1+($B10-2.5)*AJ10)/(1-1.5*AJ10)) -> 0.13188898 | AL10: =MAX(AM10-AM9,0.005) -> 0.053 | AM10: ='[2]Moody''s Global Infra and Corp D'!$AO$66 -> 0.0907 | AN10: =0.12*(1-EXP(-50*$AH10))/(1-EXP(-50))+0.24*(1-(1-EXP(-50*$AH10))/(1-EXP(-50))) -> 0.14973996 | AO10: =(0.11852-0.05478*LN($AM10))^2 -> 0.062501421 | AP10: =(AM$8*NORMSDIST((1-AN10)^(-0.5)*NORMSINV($AM10)+(AN10/(1-AN10))^(0.5)*NORMSINV(0.999))-$AM10*AM$8)*((1+($B10-2.5)*AO10)/(1-1.5*AO10)) -> 0.23109241
B11: 3 | D11: =Q11*100 -> 0.39715595 | E11: =V11*100 -> 1.8442026 | F11: =AA11*100 -> 5.7482172 | G11: =AF11*100 -> 9.2164456 | H11: =AK11*100 -> 17.209803 | I11: =AP11*100 -> 26.036047 | K11: =H11 -> 17.209803 | N11: ='[2]Moody''s Global Infra and Corp D'!$AP$61 -> 1e-05 | O11: =0.12*(1-EXP(-50*$N11))/(1-EXP(-50))+0.24*(1-(1-EXP(-50*$N11))/(1-EXP(-50))) -> 0.23994001 | P11: =(0.11852-0.05478*LN($N11))^2 -> 0.56129773 | Q11: =(N$8*NORMSDIST((1-O11)^(-0.5)*NORMSINV($N11)+(O11/(1-O11))^(0.5)*NORMSINV(0.999))-$N11*N$8)*((1+($B11-2.5)*P11)/(1-1.5*P11)) -> 0.0039715595 | S11: ='[2]Moody''s Global Infra and Corp D'!$AP$62 -> 0.0003 | T11: =0.12*(1-EXP(-50*$S11))/(1-EXP(-50))+0.24*(1-(1-EXP(-50*$S11))/(1-EXP(-50))) -> 0.23821343 | U11: =(0.11852-0.05478*LN($S11))^2 -> 0.31683442 | V11: =(S$8*NORMSDIST((1-T11)^(-0.5)*NORMSINV($S11)+(T11/(1-T11))^(0.5)*NORMSINV(0.999))-$S11*S$8)*((1+($B11-2.5)*U11)/(1-1.5*U11)) -> 0.018442026 | X11: ='[2]Moody''s Global Infra and Corp D'!$AP$63 -> 0.0023 | Y11: =0.12*(1-EXP(-50*$X11))/(1-EXP(-50))+0.24*(1-(1-EXP(-50*$X11))/(1-EXP(-50))) -> 0.22696394 | Z11: =(0.11852-0.05478*LN($X11))^2 -> 0.20367176 | AA11: =(X$8*NORMSDIST((1-Y11)^(-0.5)*NORMSINV($X11)+(Y11/(1-Y11))^(0.5)*NORMSINV(0.999))-$X11*X$8)*((1+($B11-2.5)*Z11)/(1-1.5*Z11)) -> 0.057482172 | AB11: =MAX(AC11-AC10,0) -> 0.0028 | AC11: ='[2]Moody''s Global Infra and Corp D'!$AP$64 -> 0.0064 | AD11: =0.12*(1-EXP(-50*$AC11))/(1-EXP(-50))+0.24*(1-(1-EXP(-50*$AC11))/(1-EXP(-50))) -> 0.20713788 | AE11: =(0.11852-0.05478*LN($AC11))^2 -> 0.15621373 | AF11: =(AC$8*NORMSDIST((1-AD11)^(-0.5)*NORMSINV($AC11)+(AD11/(1-AD11))^(0.5)*NORMSINV(0.999))-$AC11*AC$8)*((1+($B11-2.5)*AE11)/(1-1.5*AE11)) -> 0.092164456 | AG11: =MAX(AH11-AH10,0) -> 0.0224 | AH11: ='[2]Moody''s Global Infra and Corp D'!$AP$65 -> 0.0503 | AI11: =0.12*(1-EXP(-50*$AH11))/(1-EXP(-50))+0.24*(1-(1-EXP(-50*$AH11))/(1-EXP(-50))) -> 0.12970355 | AJ11: =(0.11852-0.05478*LN($AH11))^2 -> 0.079692452 | AK11: =(AH$8*NORMSDIST((1-AI11)^(-0.5)*NORMSINV($AH11)+(AI11/(1-AI11))^(0.5)*NORMSINV(0.999))-$AH11*AH$8)*((1+($B11-2.5)*AJ11)/(1-1.5*AJ11)) -> 0.17209803 | AL11: =MAX(AM11-AM10,0.005) -> 0.0547 | AM11: ='[2]Moody''s Global Infra and Corp D'!$AP$66 -> 0.1454 | AN11: =0.12*(1-EXP(-50*$AH11))/(1-EXP(-50))+0.24*(1-(1-EXP(-50*$AH11))/(1-EXP(-50))) -> 0.12970355 | AO11: =(0.11852-0.05478*LN($AM11))^2 -> 0.050243424 | AP11: =(AM$8*NORMSDIST((1-AN11)^(-0.5)*NORMSINV($AM11)+(AN11/(1-AN11))^(0.5)*NORMSINV(0.999))-$AM11*AM$8)*((1+($B11-2.5)*AO11)/(1-1.5*AO11)) -> 0.26036047
B12: 4 | D12: =Q12*100 -> 3.70874 | E12: =V12*100 -> 4.7075801 | F12: =AA12*100 -> 8.2591944 | G12: =AF12*100 -> 12.31143 | H12: =AK12*100 -> 20.966721 | I12: =AP12*100 -> 28.187145 | K12: =H12 -> 20.966721 | N12: ='[2]Moody''s Global Infra and Corp D'!$AQ$61 -> 0.0007 | O12: =0.12*(1-EXP(-50*$N12))/(1-EXP(-50))+0.24*(1-(1-EXP(-50*$N12))/(1-EXP(-50))) -> 0.23587265 | P12: =(0.11852-0.05478*LN($N12))^2 -> 0.2667366 | Q12: =(N$8*NORMSDIST((1-O12)^(-0.5)*NORMSINV($N12)+(O12/(1-O12))^(0.5)*NORMSINV(0.999))-$N12*N$8)*((1+($B12-2.5)*P12)/(1-1.5*P12)) -> 0.0370874 | S12: ='[2]Moody''s Global Infra and Corp D'!$AQ$62 -> 0.0011 | T12: =0.12*(1-EXP(-50*$S12))/(1-EXP(-50))+0.24*(1-(1-EXP(-50*$S12))/(1-EXP(-50))) -> 0.23357822 | U12: =(0.11852-0.05478*LN($S12))^2 -> 0.24177454 | V12: =(S$8*NORMSDIST((1-T12)^(-0.5)*NORMSINV($S12)+(T12/(1-T12))^(0.5)*NORMSINV(0.999))-$S12*S$8)*((1+($B12-2.5)*U12)/(1-1.5*U12)) -> 0.047075801 | X12: ='[2]Moody''s Global Infra and Corp D'!$AQ$63 -> 0.0035 | Y12: =0.12*(1-EXP(-50*$X12))/(1-EXP(-50))+0.24*(1-(1-EXP(-50*$X12))/(1-EXP(-50))) -> 0.22073484 | Z12: =(0.11852-0.05478*LN($X12))^2 -> 0.1834413 | AA12: =(X$8*NORMSDIST((1-Y12)^(-0.5)*NORMSINV($X12)+(Y12/(1-Y12))^(0.5)*NORMSINV(0.999))-$X12*X$8)*((1+($B12-2.5)*Z12)/(1-1.5*Z12)) -> 0.082591944 | AB12: =MAX(AC12-AC11,0) -> 0.0037 | AC12: ='[2]Moody''s Global Infra and Corp D'!$AQ$64 -> 0.0101 | AD12: =0.12*(1-EXP(-50*$AC12))/(1-EXP(-50))+0.24*(1-(1-EXP(-50*$AC12))/(1-EXP(-50))) -> 0.19242067 | AE12: =(0.11852-0.05478*LN($AC12))^2 -> 0.13708221 | AF12: =(AC$8*NORMSDIST((1-AD12)^(-0.5)*NORMSINV($AC12)+(AD12/(1-AD12))^(0.5)*NORMSINV(0.999))-$AC12*AC$8)*((1+($B12-2.5)*AE12)/(1-1.5*AE12)) -> 0.1231143 | AG12: =MAX(AH12-AH11,0) -> 0.0239 | AH12: ='[2]Moody''s Global Infra and Corp D'!$AQ$65 -> 0.0742 | AI12: =0.12*(1-EXP(-50*$AH12))/(1-EXP(-50))+0.24*(1-(1-EXP(-50*$AH12))/(1-EXP(-50))) -> 0.1229373 | AJ12: =(0.11852-0.05478*LN($AH12))^2 -> 0.068122197 | AK12: =(AH$8*NORMSDIST((1-AI12)^(-0.5)*NORMSINV($AH12)+(AI12/(1-AI12))^(0.5)*NORMSINV(0.999))-$AH12*AH$8)*((1+($B12-2.5)*AJ12)/(1-1.5*AJ12)) -> 0.20966721 | AL12: =MAX(AM12-AM11,0.005) -> 0.0488 | AM12: ='[2]Moody''s Global Infra and Corp D'!$AQ$66 -> 0.1942 | AN12: =0.12*(1-EXP(-50*$AH12))/(1-EXP(-50))+0.24*(1-(1-EXP(-50*$AH12))/(1-EXP(-50))) -> 0.1229373 | AO12: =(0.11852-0.05478*LN($AM12))^2 -> 0.04338769 | AP12: =(AM$8*NORMSDIST((1-AN12)^(-0.5)*NORMSINV($AM12)+(AN12/(1-AN12))^(0.5)*NORMSINV(0.999))-$AM12*AM$8)*((1+($B12-2.5)*AO12)/(1-1.5*AO12)) -> 0.28187145
B13: 5 | D13: =Q13*100 -> 6.4488335 | E13: =V13*100 -> 6.8452953 | F13: =AA13*100 -> 10.711519 | G13: =AF13*100 -> 14.954042 | H13: =AK13*100 -> 24.061214 | I13: =AP13*100 -> 29.807527 | K13: =H13 -> 24.061214 | N13: ='[2]Moody''s Global Infra and Corp D'!$AR$61 -> 0.0015 | O13: =0.12*(1-EXP(-50*$N13))/(1-EXP(-50))+0.24*(1-(1-EXP(-50*$N13))/(1-EXP(-50))) -> 0.23132922 | P13: =(0.11852-0.05478*LN($N13))^2 -> 0.22535476 | Q13: =(N$8*NORMSDIST((1-O13)^(-0.5)*NORMSINV($N13)+(O13/(1-O13))^(0.5)*NORMSINV(0.999))-$N13*N$8)*((1+($B13-2.5)*P13)/(1-1.5*P13)) -> 0.064488335 | S13: ='[2]Moody''s Global Infra and Corp D'!$AR$62 -> 0.0017 | T13: =0.12*(1-EXP(-50*$S13))/(1-EXP(-50))+0.24*(1-(1-EXP(-50*$S13))/(1-EXP(-50))) -> 0.23022147 | U13: =(0.11852-0.05478*LN($S13))^2 -> 0.21889206 | V13: =(S$8*NORMSDIST((1-T13)^(-0.5)*NORMSINV($S13)+(T13/(1-T13))^(0.5)*NORMSINV(0.999))-$S13*S$8)*((1+($B13-2.5)*U13)/(1-1.5*U13)) -> 0.068452953 | X13: ='[2]Moody''s Global Infra and Corp D'!$AR$63 -> 0.0048 | Y13: =0.12*(1-EXP(-50*$X13))/(1-EXP(-50))+0.24*(1-(1-EXP(-50*$X13))/(1-EXP(-50))) -> 0.21439534 | Z13: =(0.11852-0.05478*LN($X13))^2 -> 0.1689194 | AA13: =(X$8*NORMSDIST((1-Y13)^(-0.5)*NORMSINV($X13)+(Y13/(1-Y13))^(0.5)*NORMSINV(0.999))-$X13*X$8)*((1+($B13-2.5)*Z13)/(1-1.5*Z13)) -> 0.10711519 | AB13: =MAX(AC13-AC12,0) -> 0.004 | AC13: ='[2]Moody''s Global Infra and Corp D'!$AR$64 -> 0.0141 | AD13: =0.12*(1-EXP(-50*$AC13))/(1-EXP(-50))+0.24*(1-(1-EXP(-50*$AC13))/(1-EXP(-50))) -> 0.17929303 | AE13: =(0.11852-0.05478*LN($AC13))^2 -> 0.12388244 | AF13: =(AC$8*NORMSDIST((1-AD13)^(-0.5)*NORMSINV($AC13)+(AD13/(1-AD13))^(0.5)*NORMSINV(0.999))-$AC13*AC$8)*((1+($B13-2.5)*AE13)/(1-1.5*AE13)) -> 0.14954042 | AG13: =MAX(AH13-AH12,0) -> 0.0206 | AH13: ='[2]Moody''s Global Infra and Corp D'!$AR$65 -> 0.0948 | AI13: =0.12*(1-EXP(-50*$AH13))/(1-EXP(-50))+0.24*(1-(1-EXP(-50*$AH13))/(1-EXP(-50))) -> 0.12104864 | AJ13: =(0.11852-0.05478*LN($AH13))^2 -> 0.061296305 | AK13: =(AH$8*NORMSDIST((1-AI13)^(-0.5)*NORMSINV($AH13)+(AI13/(1-AI13))^(0.5)*NORMSINV(0.999))-$AH13*AH$8)*((1+($B13-2.5)*AJ13)/(1-1.5*AJ13)) -> 0.24061214 | AL13: =MAX(AM13-AM12,0.005) -> 0.0452 | AM13: ='[2]Moody''s Global Infra and Corp D'!$AR$66 -> 0.2394 | AN13: =0.12*(1-EXP(-50*$AH13))/(1-EXP(-50))+0.24*(1-(1-EXP(-50*$AH13))/(1-EXP(-50))) -> 0.12104864 | AO13: =(0.11852-0.05478*LN($AM13))^2 -> 0.038743842 | AP13: =(AM$8*NORMSDIST((1-AN13)^(-0.5)*NORMSINV($AM13)+(AN13/(1-AN13))^(0.5)*NORMSINV(0.999))-$AM13*AM$8)*((1+($B13-2.5)*AO13)/(1-1.5*AO13)) -> 0.29807527
B14: 6 | D14: =Q14*100 -> 9.1013403 | E14: =V14*100 -> 8.5880787 | F14: =AA14*100 -> 13.222733 | G14: =AF14*100 -> 17.234189 | H14: =AK14*100 -> 26.761608 | I14: =AP14*100 -> 30.846321 | K14: =H14 -> 26.761608 | N14: ='[2]Moody''s Global Infra and Corp D'!$AS$61 -> 0.0024 | O14: =0.12*(1-EXP(-50*$N14))/(1-EXP(-50))+0.24*(1-(1-EXP(-50*$N14))/(1-EXP(-50))) -> 0.22643045 | P14: =(0.11852-0.05478*LN($N14))^2 -> 0.20157285 | Q14: =(N$8*NORMSDIST((1-O14)^(-0.5)*NORMSINV($N14)+(O14/(1-O14))^(0.5)*NORMSINV(0.999))-$N14*N$8)*((1+($B14-2.5)*P14)/(1-1.5*P14)) -> 0.091013403 | S14: ='[2]Moody''s Global Infra and Corp D'!$AS$62 -> 0.0021 | T14: =0.12*(1-EXP(-50*$S14))/(1-EXP(-50))+0.24*(1-(1-EXP(-50*$S14))/(1-EXP(-50))) -> 0.22803894 | U14: =(0.11852-0.05478*LN($S14))^2 -> 0.20819464 | V14: =(S$8*NORMSDIST((1-T14)^(-0.5)*NORMSINV($S14)+(T14/(1-T14))^(0.5)*NORMSINV(0.999))-$S14*S$8)*((1+($B14-2.5)*U14)/(1-1.5*U14)) -> 0.085880787 | X14: ='[2]Moody''s Global Infra and Corp D'!$AS$63 -> 0.0064 | Y14: =0.12*(1-EXP(-50*$X14))/(1-EXP(-50))+0.24*(1-(1-EXP(-50*$X14))/(1-EXP(-50))) -> 0.20713788 | Z14: =(0.11852-0.05478*LN($X14))^2 -> 0.15621373 | AA14: =(X$8*NORMSDIST((1-Y14)^(-0.5)*NORMSINV($X14)+(Y14/(1-Y14))^(0.5)*NORMSINV(0.999))-$X14*X$8)*((1+($B14-2.5)*Z14)/(1-1.5*Z14)) -> 0.13222733 | AB14: =MAX(AC14-AC13,0) -> 0.004 | AC14: ='[2]Moody''s Global Infra and Corp D'!$AS$64 -> 0.0181 | AD14: =0.12*(1-EXP(-50*$AC14))/(1-EXP(-50))+0.24*(1-(1-EXP(-50*$AC14))/(1-EXP(-50))) -> 0.16854503 | AE14: =(0.11852-0.05478*LN($AC14))^2 -> 0.1144393 | AF14: =(AC$8*NORMSDIST((1-AD14)^(-0.5)*NORMSINV($AC14)+(AD14/(1-AD14))^(0.5)*NORMSINV(0.999))-$AC14*AC$8)*((1+($B14-2.5)*AE14)/(1-1.5*AE14)) -> 0.17234189 | AG14: =MAX(AH14-AH13,0) -> 0.0198 | AH14: ='[2]Moody''s Global Infra and Corp D'!$AS$65 -> 0.1146 | AI14: =0.12*(1-EXP(-50*$AH14))/(1-EXP(-50))+0.24*(1-(1-EXP(-50*$AH14))/(1-EXP(-50))) -> 0.12038965 | AJ14: =(0.11852-0.05478*LN($AH14))^2 -> 0.05625925 | AK14: =(AH$8*NORMSDIST((1-AI14)^(-0.5)*NORMSINV($AH14)+(AI14/(1-AI14))^(0.5)*NORMSINV(0.999))-$AH14*AH$8)*((1+($B14-2.5)*AJ14)/(1-1.5*AJ14)) -> 0.26761608 | AL14: =MAX(AM14-AM13,0.005) -> 0.0407 | AM14: ='[2]Moody''s Global Infra and Corp D'!$AS$66 -> 0.2801 | AN14: =0.12*(1-EXP(-50*$AH14))/(1-EXP(-50))+0.24*(1-(1-EXP(-50*$AH14))/(1-EXP(-50))) -> 0.12038965 | AO14: =(0.11852-0.05478*LN($AM14))^2 -> 0.03543185 | AP14: =(AM$8*NORMSDIST((1-AN14)^(-0.5)*NORMSINV($AM14)+(AN14/(1-AN14))^(0.5)*NORMSINV(0.999))-$AM14*AM$8)*((1+($B14-2.5)*AO14)/(1-1.5*AO14)) -> 0.30846321
B15: 7 | D15: =Q15*100 -> 11.69384 | E15: =V15*100 -> 10.177024 | F15: =AA15*100 -> 15.591596 | G15: =AF15*100 -> 19.292689 | H15: =AK15*100 -> 29.061929 | I15: =AP15*100 -> 31.454937 | K15: =H15 -> 29.061929 | N15: ='[2]Moody''s Global Infra and Corp D'!$AT$61 -> 0.0034 | O15: =0.12*(1-EXP(-50*$N15))/(1-EXP(-50))+0.24*(1-(1-EXP(-50*$N15))/(1-EXP(-50))) -> 0.22123978 | P15: =(0.11852-0.05478*LN($N15))^2 -> 0.18480405 | Q15: =(N$8*NORMSDIST((1-O15)^(-0.5)*NORMSINV($N15)+(O15/(1-O15))^(0.5)*NORMSINV(0.999))-$N15*N$8)*((1+($B15-2.5)*P15)/(1-1.5*P15)) -> 0.1169384 | S15: ='[2]Moody''s Global Infra and Corp D'!$AT$62 -> 0.0024 | T15: =0.12*(1-EXP(-50*$S15))/(1-EXP(-50))+0.24*(1-(1-EXP(-50*$S15))/(1-EXP(-50))) -> 0.22643045 | U15: =(0.11852-0.05478*LN($S15))^2 -> 0.20157285 | V15: =(S$8*NORMSDIST((1-T15)^(-0.5)*NORMSINV($S15)+(T15/(1-T15))^(0.5)*NORMSINV(0.999))-$S15*S$8)*((1+($B15-2.5)*U15)/(1-1.5*U15)) -> 0.10177024 | X15: ='[2]Moody''s Global Infra and Corp D'!$AT$63 -> 0.0081 | Y15: =0.12*(1-EXP(-50*$X15))/(1-EXP(-50))+0.24*(1-(1-EXP(-50*$X15))/(1-EXP(-50))) -> 0.20003722 | Z15: =(0.11852-0.05478*LN($X15))^2 -> 0.14617969 | AA15: =(X$8*NORMSDIST((1-Y15)^(-0.5)*NORMSINV($X15)+(Y15/(1-Y15))^(0.5)*NORMSINV(0.999))-$X15*X$8)*((1+($B15-2.5)*Z15)/(1-1.5*Z15)) -> 0.15591596 | AB15: =MAX(AC15-AC14,0) -> 0.004 | AC15: ='[2]Moody''s Global Infra and Corp D'!$AT$64 -> 0.0221 | AD15: =0.12*(1-EXP(-50*$AC15))/(1-EXP(-50))+0.24*(1-(1-EXP(-50*$AC15))/(1-EXP(-50))) -> 0.15974531 | AE15: =(0.11852-0.05478*LN($AC15))^2 -> 0.10715874 | AF15: =(AC$8*NORMSDIST((1-AD15)^(-0.5)*NORMSINV($AC15)+(AD15/(1-AD15))^(0.5)*NORMSINV(0.999))-$AC15*AC$8)*((1+($B15-2.5)*AE15)/(1-1.5*AE15)) -> 0.19292689 | AG15: =MAX(AH15-AH14,0) -> 0.0182 | AH15: ='[2]Moody''s Global Infra and Corp D'!$AT$65 -> 0.1328 | AI15: =0.12*(1-EXP(-50*$AH15))/(1-EXP(-50))+0.24*(1-(1-EXP(-50*$AH15))/(1-EXP(-50))) -> 0.12015684 | AJ15: =(0.11852-0.05478*LN($AH15))^2 -> 0.052494117 | AK15: =(AH$8*NORMSDIST((1-AI15)^(-0.5)*NORMSINV($AH15)+(AI15/(1-AI15))^(0.5)*NORMSINV(0.999))-$AH15*AH$8)*((1+($B15-2.5)*AJ15)/(1-1.5*AJ15)) -> 0.29061929 | AL15: =MAX(AM15-AM14,0.005) -> 0.0372 | AM15: ='[2]Moody''s Global Infra and Corp D'!$AT$66 -> 0.3173 | AN15: =0.12*(1-EXP(-50*$AH15))/(1-EXP(-50))+0.24*(1-(1-EXP(-50*$AH15))/(1-EXP(-50))) -> 0.12015684 | AO15: =(0.11852-0.05478*LN($AM15))^2 -> 0.032906822 | AP15: =(AM$8*NORMSDIST((1-AN15)^(-0.5)*NORMSINV($AM15)+(AN15/(1-AN15))^(0.5)*NORMSINV(0.999))-$AM15*AM$8)*((1+($B15-2.5)*AO15)/(1-1.5*AO15)) -> 0.31454937
B16: 8 | D16: =Q16*100 -> 12.873709 | E16: =V16*100 -> 11.791437 | F16: =AA16*100 -> 17.910785 | G16: =AF16*100 -> 21.200313 | H16: =AK16*100 -> 31.067133 | I16: =AP16*100 -> 31.81546 | K16: =H16 -> 31.067133 | N16: ='[2]Moody''s Global Infra and Corp D'!$AU$61 -> 0.0034 | O16: =0.12*(1-EXP(-50*$N16))/(1-EXP(-50))+0.24*(1-(1-EXP(-50*$N16))/(1-EXP(-50))) -> 0.22123978 | P16: =(0.11852-0.05478*LN($N16))^2 -> 0.18480405 | Q16: =(N$8*NORMSDIST((1-O16)^(-0.5)*NORMSINV($N16)+(O16/(1-O16))^(0.5)*NORMSINV(0.999))-$N16*N$8)*((1+($B16-2.5)*P16)/(1-1.5*P16)) -> 0.12873709 | S16: ='[2]Moody''s Global Infra and Corp D'!$AU$62 -> 0.0027 | T16: =0.12*(1-EXP(-50*$S16))/(1-EXP(-50))+0.24*(1-(1-EXP(-50*$S16))/(1-EXP(-50))) -> 0.22484591 | U16: =(0.11852-0.05478*LN($S16))^2 -> 0.19582085 | V16: =(S$8*NORMSDIST((1-T16)^(-0.5)*NORMSINV($S16)+(T16/(1-T16))^(0.5)*NORMSINV(0.999))-$S16*S$8)*((1+($B16-2.5)*U16)/(1-1.5*U16)) -> 0.11791437 | X16: ='[2]Moody''s Global Infra and Corp D'!$AU$63 -> 0.0101 | Y16: =0.12*(1-EXP(-50*$X16))/(1-EXP(-50))+0.24*(1-(1-EXP(-50*$X16))/(1-EXP(-50))) -> 0.19242067 | Z16: =(0.11852-0.05478*LN($X16))^2 -> 0.13708221 | AA16: =(X$8*NORMSDIST((1-Y16)^(-0.5)*NORMSINV($X16)+(Y16/(1-Y16))^(0.5)*NORMSINV(0.999))-$X16*X$8)*((1+($B16-2.5)*Z16)/(1-1.5*Z16)) -> 0.17910785 | AB16: =MAX(AC16-AC15,0) -> 0.0039 | AC16: ='[2]Moody''s Global Infra and Corp D'!$AU$64 -> 0.026 | AD16: =0.12*(1-EXP(-50*$AC16))/(1-EXP(-50))+0.24*(1-(1-EXP(-50*$AC16))/(1-EXP(-50))) -> 0.15270382 | AE16: =(0.11852-0.05478*LN($AC16))^2 -> 0.10140932 | AF16: =(AC$8*NORMSDIST((1-AD16)^(-0.5)*NORMSINV($AC16)+(AD16/(1-AD16))^(0.5)*NORMSINV(0.999))-$AC16*AC$8)*((1+($B16-2.5)*AE16)/(1-1.5*AE16)) -> 0.21200313 | AG16: =MAX(AH16-AH15,0) -> 0.0173 | AH16: ='[2]Moody''s Global Infra and Corp D'!$AU$65 -> 0.1501 | AI16: =0.12*(1-EXP(-50*$AH16))/(1-EXP(-50))+0.24*(1-(1-EXP(-50*$AH16))/(1-EXP(-50))) -> 0.12006604 | AJ16: =(0.11852-0.05478*LN($AH16))^2 -> 0.049465196 | AK16: =(AH$8*NORMSDIST((1-AI16)^(-0.5)*NORMSINV($AH16)+(AI16/(1-AI16))^(0.5)*NORMSINV(0.999))-$AH16*AH$8)*((1+($B16-2.5)*AJ16)/(1-1.5*AJ16)) -> 0.31067133 | AL16: =MAX(AM16-AM15,0.005) -> 0.0307 | AM16: ='[2]Moody''s Global Infra and Corp D'!$AU$66 -> 0.348 | AN16: =0.12*(1-EXP(-50*$AH16))/(1-EXP(-50))+0.24*(1-(1-EXP(-50*$AH16))/(1-EXP(-50))) -> 0.12006604 | AO16: =(0.11852-0.05478*LN($AM16))^2 -> 0.031096918 | AP16: =(AM$8*NORMSDIST((1-AN16)^(-0.5)*NORMSINV($AM16)+(AN16/(1-AN16))^(0.5)*NORMSINV(0.999))-$AM16*AM$8)*((1+($B16-2.5)*AO16)/(1-1.5*AO16)) -> 0.3181546
B17: 9 | D17: =Q17*100 -> 14.053577 | E17: =V17*100 -> 13.748477 | F17: =AA17*100 -> 19.943034 | G17: =AF17*100 -> 23.012607 | H17: =AK17*100 -> 32.836013 | I17: =AP17*100 -> 32.037589 | K17: =H17 -> 32.836013 | N17: ='[2]Moody''s Global Infra and Corp D'!$AV$61 -> 0.0034 | O17: =0.12*(1-EXP(-50*$N17))/(1-EXP(-50))+0.24*(1-(1-EXP(-50*$N17))/(1-EXP(-50))) -> 0.22123978 | P17: =(0.11852-0.05478*LN($N17))^2 -> 0.18480405 | Q17: =(N$8*NORMSDIST((1-O17)^(-0.5)*NORMSINV($N17)+(O17/(1-O17))^(0.5)*NORMSINV(0.999))-$N17*N$8)*((1+($B17-2.5)*P17)/(1-1.5*P17)) -> 0.14053577 | S17: ='[2]Moody''s Global Infra and Corp D'!$AV$62 -> 0.0032 | T17: =0.12*(1-EXP(-50*$S17))/(1-EXP(-50))+0.24*(1-(1-EXP(-50*$S17))/(1-EXP(-50))) -> 0.22225725 | U17: =(0.11852-0.05478*LN($S17))^2 -> 0.18767041 | V17: =(S$8*NORMSDIST((1-T17)^(-0.5)*NORMSINV($S17)+(T17/(1-T17))^(0.5)*NORMSINV(0.999))-$S17*S$8)*((1+($B17-2.5)*U17)/(1-1.5*U17)) -> 0.13748477 | X17: ='[2]Moody''s Global Infra and Corp D'!$AV$63 -> 0.0118 | Y17: =0.12*(1-EXP(-50*$X17))/(1-EXP(-50))+0.24*(1-(1-EXP(-50*$X17))/(1-EXP(-50))) -> 0.18651927 | Z17: =(0.11852-0.05478*LN($X17))^2 -> 0.1308445 | AA17: =(X$8*NORMSDIST((1-Y17)^(-0.5)*NORMSINV($X17)+(Y17/(1-Y17))^(0.5)*NORMSINV(0.999))-$X17*X$8)*((1+($B17-2.5)*Z17)/(1-1.5*Z17)) -> 0.19943034 | AB17: =MAX(AC17-AC16,0) -> 0.0038 | AC17: ='[2]Moody''s Global Infra and Corp D'!$AV$64 -> 0.0298 | AD17: =0.12*(1-EXP(-50*$AC17))/(1-EXP(-50))+0.24*(1-(1-EXP(-50*$AC17))/(1-EXP(-50))) -> 0.14704472 | AE17: =(0.11852-0.05478*LN($AC17))^2 -> 0.096705864 | AF17: =(AC$8*NORMSDIST((1-AD17)^(-0.5)*NORMSINV($AC17)+(AD17/(1-AD17))^(0.5)*NORMSINV(0.999))-$AC17*AC$8)*((1+($B17-2.5)*AE17)/(1-1.5*AE17)) -> 0.23012607 | AG17: =MAX(AH17-AH16,0) -> 0.0168 | AH17: ='[2]Moody''s Global Infra and Corp D'!$AV$65 -> 0.1669 | AI17: =0.12*(1-EXP(-50*$AH17))/(1-EXP(-50))+0.24*(1-(1-EXP(-50*$AH17))/(1-EXP(-50))) -> 0.12002851 | AJ17: =(0.11852-0.05478*LN($AH17))^2 -> 0.046913804 | AK17: =(AH$8*NORMSDIST((1-AI17)^(-0.5)*NORMSINV($AH17)+(AI17/(1-AI17))^(0.5)*NORMSINV(0.999))-$AH17*AH$8)*((1+($B17-2.5)*AJ17)/(1-1.5*AJ17)) -> 0.32836013 | AL17: =MAX(AM17-AM16,0.005) -> 0.0261 | AM17: ='[2]Moody''s Global Infra and Corp D'!$AV$66 -> 0.3741 | AN17: =0.12*(1-EXP(-50*$AH17))/(1-EXP(-50))+0.24*(1-(1-EXP(-50*$AH17))/(1-EXP(-50))) -> 0.12002851 | AO17: =(0.11852-0.05478*LN($AM17))^2 -> 0.029715367 | AP17: =(AM$8*NORMSDIST((1-AN17)^(-0.5)*NORMSINV($AM17)+(AN17/(1-AN17))^(0.5)*NORMSINV(0.999))-$AM17*AM$8)*((1+($B17-2.5)*AO17)/(1-1.5*AO17)) -> 0.32037589
B18: 10 | D18: =Q18*100 -> 15.233446 | E18: =V18*100 -> 15.966283 | F18: =AA18*100 -> 21.756314 | G18: =AF18*100 -> 24.803343 | H18: =AK18*100 -> 34.410529 | I18: =AP18*100 -> 32.218729 | K18: =H18 -> 34.410529 | N18: ='[2]Moody''s Global Infra and Corp D'!$AW$61 -> 0.0034 | O18: =0.12*(1-EXP(-50*$N18))/(1-EXP(-50))+0.24*(1-(1-EXP(-50*$N18))/(1-EXP(-50))) -> 0.22123978 | P18: =(0.11852-0.05478*LN($N18))^2 -> 0.18480405 | Q18: =(N$8*NORMSDIST((1-O18)^(-0.5)*NORMSINV($N18)+(O18/(1-O18))^(0.5)*NORMSINV(0.999))-$N18*N$8)*((1+($B18-2.5)*P18)/(1-1.5*P18)) -> 0.15233446 | S18: ='[2]Moody''s Global Infra and Corp D'!$AW$62 -> 0.0039 | T18: =0.12*(1-EXP(-50*$S18))/(1-EXP(-50))+0.24*(1-(1-EXP(-50*$S18))/(1-EXP(-50))) -> 0.21874016 | U18: =(0.11852-0.05478*LN($S18))^2 -> 0.17839856 | V18: =(S$8*NORMSDIST((1-T18)^(-0.5)*NORMSINV($S18)+(T18/(1-T18))^(0.5)*NORMSINV(0.999))-$S18*S$8)*((1+($B18-2.5)*U18)/(1-1.5*U18)) -> 0.15966283 | X18: ='[2]Moody''s Global Infra and Corp D'!$AW$63 -> 0.0131 | Y18: =0.12*(1-EXP(-50*$X18))/(1-EXP(-50))+0.24*(1-(1-EXP(-50*$X18))/(1-EXP(-50))) -> 0.18233305 | Z18: =(0.11852-0.05478*LN($X18))^2 -> 0.12673538 | AA18: =(X$8*NORMSDIST((1-Y18)^(-0.5)*NORMSINV($X18)+(Y18/(1-Y18))^(0.5)*NORMSINV(0.999))-$X18*X$8)*((1+($B18-2.5)*Z18)/(1-1.5*Z18)) -> 0.21756314 | AB18: =MAX(AC18-AC17,0) -> 0.0041 | AC18: ='[2]Moody''s Global Infra and Corp D'!$AW$64 -> 0.0339 | AD18: =0.12*(1-EXP(-50*$AC18))/(1-EXP(-50))+0.24*(1-(1-EXP(-50*$AC18))/(1-EXP(-50))) -> 0.14203191 | AE18: =(0.11852-0.05478*LN($AC18))^2 -> 0.092363816 | AF18: =(AC$8*NORMSDIST((1-AD18)^(-0.5)*NORMSINV($AC18)+(AD18/(1-AD18))^(0.5)*NORMSINV(0.999))-$AC18*AC$8)*((1+($B18-2.5)*AE18)/(1-1.5*AE18)) -> 0.24803343 | AG18: =MAX(AH18-AH17,0) -> 0.0169 | AH18: ='[2]Moody''s Global Infra and Corp D'!$AW$65 -> 0.1838 | AI18: =0.12*(1-EXP(-50*$AH18))/(1-EXP(-50))+0.24*(1-(1-EXP(-50*$AH18))/(1-EXP(-50))) -> 0.12001225 | AJ18: =(0.11852-0.05478*LN($AH18))^2 -> 0.044652858 | AK18: =(AH$8*NORMSDIST((1-AI18)^(-0.5)*NORMSINV($AH18)+(AI18/(1-AI18))^(0.5)*NORMSINV(0.999))-$AH18*AH$8)*((1+($B18-2.5)*AJ18)/(1-1.5*AJ18)) -> 0.34410529 | AL18: =MAX(AM18-AM17,0.005) -> 0.0213 | AM18: ='[2]Moody''s Global Infra and Corp D'!$AW$66 -> 0.3954 | AN18: =0.12*(1-EXP(-50*$AH18))/(1-EXP(-50))+0.24*(1-(1-EXP(-50*$AH18))/(1-EXP(-50))) -> 0.12001225 | AO18: =(0.11852-0.05478*LN($AM18))^2 -> 0.028678754 | AP18: =(AM$8*NORMSDIST((1-AN18)^(-0.5)*NORMSINV($AM18)+(AN18/(1-AN18))^(0.5)*NORMSINV(0.999))-$AM18*AM$8)*((1+($B18-2.5)*AO18)/(1-1.5*AO18)) -> 0.32218729
D20: Corporate Exposures - Corporate Bank Loans (based on Moody's) - Global | N20: =1-'[2]Moody''s Global Infra and Corp D'!P101 -> 0.196 | S20: =N20 -> 0.196 | X20: =N20 -> 0.196 | AC20: =X20 -> 0.196 | AH20: =X20 -> 0.196 | AM20: =AC20 -> 0.196 | AN20: stdev(rec.) | AO20: 0.305 | AP20: =AO20*(AM20/(1-AM20)) -> 0.074353234
B21: =$B$9 -> 1 | D21: =Q21*100 -> 0.015071274 | E21: =V21*100 -> 0.19190024 | F21: =AA21*100 -> 0.44814729 | G21: =AF21*100 -> 1.0462229 | H21: =AK21*100 -> 2.5080263 | I21: =AP21*100 -> 5.447553 | K21: =H21 -> 2.5080263 | M21: =N21 -> 1e-05 | N21: ='[2]Moody''s Global Infra and Corp D'!AQ89 -> 1e-05 | O21: =0.12*(1-EXP(-50*$N21))/(1-EXP(-50))+0.24*(1-(1-EXP(-50*$N21))/(1-EXP(-50))) -> 0.23994001 | P21: =(0.11852-0.05478*LN($N21))^2 -> 0.56129773 | Q21: =(N$20*NORMSDIST((1-O21)^(-0.5)*NORMSINV($N21)+(O21/(1-O21))^(0.5)*NORMSINV(0.999))-$N21*N$8)*((1+($B21-2.5)*P21)/(1-1.5*P21)) -> 0.00015071274 | R21: =S21 -> 0.0002 | S21: ='[2]Moody''s Global Infra and Corp D'!$AF$91 -> 0.0002 | T21: =0.12*(1-EXP(-50*$S21))/(1-EXP(-50))+0.24*(1-(1-EXP(-50*$S21))/(1-EXP(-50))) -> 0.23880598 | U21: =(0.11852-0.05478*LN($S21))^2 -> 0.34233246 | V21: =(S$20*NORMSDIST((1-T21)^(-0.5)*NORMSINV($S21)+(T21/(1-T21))^(0.5)*NORMSINV(0.999))-$S21*S$20)*((1+($B21-2.5)*U21)/(1-1.5*U21)) -> 0.0019190024 | X21: ='[2]Moody''s Global Infra and Corp D'!$AF$93 -> 0.0006 | Y21: =0.12*(1-EXP(-50*$X21))/(1-EXP(-50))+0.24*(1-(1-EXP(-50*$X21))/(1-EXP(-50))) -> 0.23645346 | Z21: =(0.11852-0.05478*LN($X21))^2 -> 0.27553036 | AA21: =(X$20*NORMSDIST((1-Y21)^(-0.5)*NORMSINV($X21)+(Y21/(1-Y21))^(0.5)*NORMSINV(0.999))-$X21*X$20)*((1+($B21-2.5)*Z21)/(1-1.5*Z21)) -> 0.0044814729 | AB21: =AC21 -> 0.002 | AC21: ='[2]Moody''s Global Infra and Corp D'!$AF$95 -> 0.002 | AD21: =0.12*(1-EXP(-50*$AC21))/(1-EXP(-50))+0.24*(1-(1-EXP(-50*$AC21))/(1-EXP(-50))) -> 0.22858049 | AE21: =(0.11852-0.05478*LN($AC21))^2 -> 0.21064082 | AF21: =(AC$20*NORMSDIST((1-AD21)^(-0.5)*NORMSINV($AC21)+(AD21/(1-AD21))^(0.5)*NORMSINV(0.999))-$AC21*AC$20)*((1+($B21-2.5)*AE21)/(1-1.5*AE21)) -> 0.010462229 | AG21: =AH21 -> 0.0096 | AH21: ='[2]Moody''s Global Infra and Corp D'!$AF$97 -> 0.0096 | AI21: =0.12*(1-EXP(-50*$AH21))/(1-EXP(-50))+0.24*(1-(1-EXP(-50*$AH21))/(1-EXP(-50))) -> 0.19425401 | AJ21: =(0.11852-0.05478*LN($AH21))^2 -> 0.13914948 | AK21: =(AH$20*NORMSDIST((1-AI21)^(-0.5)*NORMSINV($AH21)+(AI21/(1-AI21))^(0.5)*NORMSINV(0.999))-$AH21*AH$20)*((1+($B21-2.5)*AJ21)/(1-1.5*AJ21)) -> 0.025080263 | AL21: =AM21 -> 0.0362 | AM21: ='[2]Moody''s Global Infra and Corp D'!$AF$99 -> 0.0362 | AN21: =0.12*(1-EXP(-50*$AH21))/(1-EXP(-50))+0.24*(1-(1-EXP(-50*$AH21))/(1-EXP(-50))) -> 0.19425401 | AO21: =(0.11852-0.05478*LN($AM21))^2 -> 0.090191007 | AP21: =(AM$20*NORMSDIST((1-AN21)^(-0.5)*NORMSINV($AM21)+(AN21/(1-AN21))^(0.5)*NORMSINV(0.999))-$AM21*AM$20)*((1+($B21-2.5)*AO21)/(1-1.5*AO21)) -> 0.05447553
B22: =$B$10 -> 2 | D22: =Q22*100 -> 0.20333274 | E22: =V22*100 -> 0.72571276 | F22: =AA22*100 -> 1.328646 | G22: =AF22*100 -> 2.2440391 | H22: =AK22*100 -> 4.1115519 | I22: =AP22*100 -> 7.2095748 | K22: =H22 -> 4.1115519 | M22: =N22-N21 -> 9e-05 | N22: ='[2]Moody''s Global Infra and Corp D'!$AG$89 -> 0.0001 | O22: =0.12*(1-EXP(-50*$N22))/(1-EXP(-50))+0.24*(1-(1-EXP(-50*$N22))/(1-EXP(-50))) -> 0.2394015 | P22: =(0.11852-0.05478*LN($N22))^2 -> 0.38820681 | Q22: =(N$20*NORMSDIST((1-O22)^(-0.5)*NORMSINV($N22)+(O22/(1-O22))^(0.5)*NORMSINV(0.999))-$N22*N$8)*((1+($B22-2.5)*P22)/(1-1.5*P22)) -> 0.0020333274 | R22: =S22-S21 -> 0.0005 | S22: ='[2]Moody''s Global Infra and Corp D'!$AG$91 -> 0.0007 | T22: =0.12*(1-EXP(-50*$S22))/(1-EXP(-50))+0.24*(1-(1-EXP(-50*$S22))/(1-EXP(-50))) -> 0.23587265 | U22: =(0.11852-0.05478*LN($S22))^2 -> 0.2667366 | V22: =(S$20*NORMSDIST((1-T22)^(-0.5)*NORMSINV($S22)+(T22/(1-T22))^(0.5)*NORMSINV(0.999))-$S22*S$20)*((1+($B22-2.5)*U22)/(1-1.5*U22)) -> 0.0072571276 | X22: ='[2]Moody''s Global Infra and Corp D'!$AG$93 -> 0.0019 | Y22: =0.12*(1-EXP(-50*$X22))/(1-EXP(-50))+0.24*(1-(1-EXP(-50*$X22))/(1-EXP(-50))) -> 0.22912475 | Z22: =(0.11852-0.05478*LN($X22))^2 -> 0.21322791 | AA22: =(X$20*NORMSDIST((1-Y22)^(-0.5)*NORMSINV($X22)+(Y22/(1-Y22))^(0.5)*NORMSINV(0.999))-$X22*X$20)*((1+($B22-2.5)*Z22)/(1-1.5*Z22)) -> 0.01328646 | AB22: =MAX(AC22-AC21,0) -> 0.0031 | AC22: ='[2]Moody''s Global Infra and Corp D'!$AG$95 -> 0.0051 | AD22: =0.12*(1-EXP(-50*$AC22))/(1-EXP(-50))+0.24*(1-(1-EXP(-50*$AC22))/(1-EXP(-50))) -> 0.21298998 | AE22: =(0.11852-0.05478*LN($AC22))^2 -> 0.16620057 | AF22: =(AC$20*NORMSDIST((1-AD22)^(-0.5)*NORMSINV($AC22)+(AD22/(1-AD22))^(0.5)*NORMSINV(0.999))-$AC22*AC$20)*((1+($B22-2.5)*AE22)/(1-1.5*AE22)) -> 0.022440391 | AG22: =MAX(AH22-AH21,0) -> 0.017 | AH22: ='[2]Moody''s Global Infra and Corp D'!$AG$97 -> 0.0266 | AI22: =0.12*(1-EXP(-50*$AH22))/(1-EXP(-50))+0.24*(1-(1-EXP(-50*$AH22))/(1-EXP(-50))) -> 0.15173727 | AJ22: =(0.11852-0.05478*LN($AH22))^2 -> 0.1006149 | AK22: =(AH$20*NORMSDIST((1-AI22)^(-0.5)*NORMSINV($AH22)+(AI22/(1-AI22))^(0.5)*NORMSINV(0.999))-$AH22*AH$20)*((1+($B22-2.5)*AJ22)/(1-1.5*AJ22)) -> 0.041115519 | AL22: =MAX(AM22-AM21,0) -> 0.0494 | AM22: ='[2]Moody''s Global Infra and Corp D'!$AG$99 -> 0.0856 | AN22: =0.12*(1-EXP(-50*$AH22))/(1-EXP(-50))+0.24*(1-(1-EXP(-50*$AH22))/(1-EXP(-50))) -> 0.15173727 | AO22: =(0.11852-0.05478*LN($AM22))^2 -> 0.064096606 | AP22: =(AM$20*NORMSDIST((1-AN22)^(-0.5)*NORMSINV($AM22)+(AN22/(1-AN22))^(0.5)*NORMSINV(0.999))-$AM22*AM$20)*((1+($B22-2.5)*AO22)/(1-1.5*AO22)) -> 0.072095748
B23: =$B$11 -> 3 | D23: =Q23*100 -> 0.30127974 | E23: =V23*100 -> 1.2845289 | F23: =AA23*100 -> 2.3514354 | G23: =AF23*100 -> 3.2472315 | H23: =AK23*100 -> 5.3360452 | I23: =AP23*100 -> 8.1332935 | K23: =H23 -> 5.3360452 | M23: =N23-N22 -> 0 | N23: ='[2]Moody''s Global Infra and Corp D'!$AH$89 -> 0.0001 | O23: =0.12*(1-EXP(-50*$N23))/(1-EXP(-50))+0.24*(1-(1-EXP(-50*$N23))/(1-EXP(-50))) -> 0.2394015 | P23: =(0.11852-0.05478*LN($N23))^2 -> 0.38820681 | Q23: =(N$20*NORMSDIST((1-O23)^(-0.5)*NORMSINV($N23)+(O23/(1-O23))^(0.5)*NORMSINV(0.999))-$N23*N$8)*((1+($B23-2.5)*P23)/(1-1.5*P23)) -> 0.0030127974 | R23: =S23-S22 -> 0.0005 | S23: ='[2]Moody''s Global Infra and Corp D'!$AH$91 -> 0.0012 | T23: =0.12*(1-EXP(-50*$S23))/(1-EXP(-50))+0.24*(1-(1-EXP(-50*$S23))/(1-EXP(-50))) -> 0.23301174 | U23: =(0.11852-0.05478*LN($S23))^2 -> 0.23710984 | V23: =(S$20*NORMSDIST((1-T23)^(-0.5)*NORMSINV($S23)+(T23/(1-T23))^(0.5)*NORMSINV(0.999))-$S23*S$20)*((1+($B23-2.5)*U23)/(1-1.5*U23)) -> 0.012845289 | X23: ='[2]Moody''s Global Infra and Corp D'!$AH$93 -> 0.0039 | Y23: =0.12*(1-EXP(-50*$X23))/(1-EXP(-50))+0.24*(1-(1-EXP(-50*$X23))/(1-EXP(-50))) -> 0.21874016 | Z23: =(0.11852-0.05478*LN($X23))^2 -> 0.17839856 | AA23: =(X$20*NORMSDIST((1-Y23)^(-0.5)*NORMSINV($X23)+(Y23/(1-Y23))^(0.5)*NORMSINV(0.999))-$X23*X$20)*((1+($B23-2.5)*Z23)/(1-1.5*Z23)) -> 0.023514354 | AB23: =MAX(AC23-AC22,0) -> 0.0034 | AC23: ='[2]Moody''s Global Infra and Corp D'!$AH$95 -> 0.0085 | AD23: =0.12*(1-EXP(-50*$AC23))/(1-EXP(-50))+0.24*(1-(1-EXP(-50*$AC23))/(1-EXP(-50))) -> 0.19845237 | AE23: =(0.11852-0.05478*LN($AC23))^2 -> 0.14416754 | AF23: =(AC$20*NORMSDIST((1-AD23)^(-0.5)*NORMSINV($AC23)+(AD23/(1-AD23))^(0.5)*NORMSINV(0.999))-$AC23*AC$20)*((1+($B23-2.5)*AE23)/(1-1.5*AE23)) -> 0.032472315 | AG23: =MAX(AH23-AH22,0) -> 0.0207 | AH23: ='[2]Moody''s Global Infra and Corp D'!$AH$97 -> 0.0473 | AI23: =0.12*(1-EXP(-50*$AH23))/(1-EXP(-50))+0.24*(1-(1-EXP(-50*$AH23))/(1-EXP(-50))) -> 0.13127392 | AJ23: =(0.11852-0.05478*LN($AH23))^2 -> 0.081605749 | AK23: =(AH$20*NORMSDIST((1-AI23)^(-0.5)*NORMSINV($AH23)+(AI23/(1-AI23))^(0.5)*NORMSINV(0.999))-$AH23*AH$20)*((1+($B23-2.5)*AJ23)/(1-1.5*AJ23)) -> 0.053360452 | AL23: =MAX(AM23-AM22,0) -> 0.0503 | AM23: ='[2]Moody''s Global Infra and Corp D'!$AH$99 -> 0.1359 | AN23: =0.12*(1-EXP(-50*$AH23))/(1-EXP(-50))+0.24*(1-(1-EXP(-50*$AH23))/(1-EXP(-50))) -> 0.13127392 | AO23: =(0.11852-0.05478*LN($AM23))^2 -> 0.051916485 | AP23: =(AM$20*NORMSDIST((1-AN23)^(-0.5)*NORMSINV($AM23)+(AN23/(1-AN23))^(0.5)*NORMSINV(0.999))-$AM23*AM$20)*((1+($B23-2.5)*AO23)/(1-1.5*AO23)) -> 0.081332935
B24: =$B$12 -> 4 | D24: =Q24*100 -> 0.82284292 | E24: =V24*100 -> 2.0609903 | F24: =AA24*100 -> 3.2766987 | G24: =AF24*100 -> 4.1608492 | H24: =AK24*100 -> 6.469057 | I24: =AP24*100 -> 8.8280096 | K24: =H24 -> 6.469057 | M24: =N24-N23 -> 0.0003 | N24: ='[2]Moody''s Global Infra and Corp D'!$AI$89 -> 0.0004 | O24: =0.12*(1-EXP(-50*$N24))/(1-EXP(-50))+0.24*(1-(1-EXP(-50*$N24))/(1-EXP(-50))) -> 0.23762384 | P24: =(0.11852-0.05478*LN($N24))^2 -> 0.29934165 | Q24: =(N$20*NORMSDIST((1-O24)^(-0.5)*NORMSINV($N24)+(O24/(1-O24))^(0.5)*NORMSINV(0.999))-$N24*N$8)*((1+($B24-2.5)*P24)/(1-1.5*P24)) -> 0.0082284292 | R24: =S24-S23 -> 0.0009 | S24: ='[2]Moody''s Global Infra and Corp D'!$AI$91 -> 0.0021 | T24: =0.12*(1-EXP(-50*$S24))/(1-EXP(-50))+0.24*(1-(1-EXP(-50*$S24))/(1-EXP(-50))) -> 0.22803894 | U24: =(0.11852-0.05478*LN($S24))^2 -> 0.20819464 | V24: =(S$20*NORMSDIST((1-T24)^(-0.5)*NORMSINV($S24)+(T24/(1-T24))^(0.5)*NORMSINV(0.999))-$S24*S$20)*((1+($B24-2.5)*U24)/(1-1.5*U24)) -> 0.020609903 | X24: ='[2]Moody''s Global Infra and Corp D'!$AI$93 -> 0.0061 | Y24: =0.12*(1-EXP(-50*$X24))/(1-EXP(-50))+0.24*(1-(1-EXP(-50*$X24))/(1-EXP(-50))) -> 0.2084548 | Z24: =(0.11852-0.05478*LN($X24))^2 -> 0.15829956 | AA24: =(X$20*NORMSDIST((1-Y24)^(-0.5)*NORMSINV($X24)+(Y24/(1-Y24))^(0.5)*NORMSINV(0.999))-$X24*X$20)*((1+($B24-2.5)*Z24)/(1-1.5*Z24)) -> 0.032766987 | AB24: =MAX(AC24-AC23,0) -> 0.0042 | AC24: ='[2]Moody''s Global Infra and Corp D'!$AI$95 -> 0.0127 | AD24: =0.12*(1-EXP(-50*$AC24))/(1-EXP(-50))+0.24*(1-(1-EXP(-50*$AC24))/(1-EXP(-50))) -> 0.18359226 | AE24: =(0.11852-0.05478*LN($AC24))^2 -> 0.12794777 | AF24: =(AC$20*NORMSDIST((1-AD24)^(-0.5)*NORMSINV($AC24)+(AD24/(1-AD24))^(0.5)*NORMSINV(0.999))-$AC24*AC$20)*((1+($B24-2.5)*AE24)/(1-1.5*AE24)) -> 0.041608492 | AG24: =MAX(AH24-AH23,0) -> 0.0217 | AH24: ='[2]Moody''s Global Infra and Corp D'!$AI$97 -> 0.069 | AI24: =0.12*(1-EXP(-50*$AH24))/(1-EXP(-50))+0.24*(1-(1-EXP(-50*$AH24))/(1-EXP(-50))) -> 0.12380948 | AJ24: =(0.11852-0.05478*LN($AH24))^2 -> 0.070215715 | AK24: =(AH$20*NORMSDIST((1-AI24)^(-0.5)*NORMSINV($AH24)+(AI24/(1-AI24))^(0.5)*NORMSINV(0.999))-$AH24*AH$20)*((1+($B24-2.5)*AJ24)/(1-1.5*AJ24)) -> 0.06469057 | AL24: =MAX(AM24-AM23,0) -> 0.045 | AM24: ='[2]Moody''s Global Infra and Corp D'!$AI$99 -> 0.1809 | AN24: =0.12*(1-EXP(-50*$AH24))/(1-EXP(-50))+0.24*(1-(1-EXP(-50*$AH24))/(1-EXP(-50))) -> 0.12380948 | AO24: =(0.11852-0.05478*LN($AM24))^2 -> 0.045021812 | AP24: =(AM$20*NORMSDIST((1-AN24)^(-0.5)*NORMSINV($AM24)+(AN24/(1-AN24))^(0.5)*NORMSINV(0.999))-$AM24*AM$20)*((1+($B24-2.5)*AO24)/(1-1.5*AO24)) -> 0.088280096
B25: =$B$13 -> 5 | D25: =Q25*100 -> 1.3133367 | E25: =V25*100 -> 2.8765219 | F25: =AA25*100 -> 4.1497793 | G25: =AF25*100 -> 4.9221279 | H25: =AK25*100 -> 7.4319462 | I25: =AP25*100 -> 9.3757764 | K25: =H25 -> 7.4319462 | M25: =N25-N24 -> 0.0003 | N25: ='[2]Moody''s Global Infra and Corp D'!$AJ$89 -> 0.0007 | O25: =0.12*(1-EXP(-50*$N25))/(1-EXP(-50))+0.24*(1-(1-EXP(-50*$N25))/(1-EXP(-50))) -> 0.23587265 | P25: =(0.11852-0.05478*LN($N25))^2 -> 0.2667366 | Q25: =(N$20*NORMSDIST((1-O25)^(-0.5)*NORMSINV($N25)+(O25/(1-O25))^(0.5)*NORMSINV(0.999))-$N25*N$8)*((1+($B25-2.5)*P25)/(1-1.5*P25)) -> 0.013133367 | R25: =S25-S24 -> 0.0011 | S25: ='[2]Moody''s Global Infra and Corp D'!$AJ$91 -> 0.0032 | T25: =0.12*(1-EXP(-50*$S25))/(1-EXP(-50))+0.24*(1-(1-EXP(-50*$S25))/(1-EXP(-50))) -> 0.22225725 | U25: =(0.11852-0.05478*LN($S25))^2 -> 0.18767041 | V25: =(S$20*NORMSDIST((1-T25)^(-0.5)*NORMSINV($S25)+(T25/(1-T25))^(0.5)*NORMSINV(0.999))-$S25*S$20)*((1+($B25-2.5)*U25)/(1-1.5*U25)) -> 0.028765219 | X25: ='[2]Moody''s Global Infra and Corp D'!$AJ$93 -> 0.0087 | Y25: =0.12*(1-EXP(-50*$X25))/(1-EXP(-50))+0.24*(1-(1-EXP(-50*$X25))/(1-EXP(-50))) -> 0.19767176 | Z25: =(0.11852-0.05478*LN($X25))^2 -> 0.1432017 | AA25: =(X$20*NORMSDIST((1-Y25)^(-0.5)*NORMSINV($X25)+(Y25/(1-Y25))^(0.5)*NORMSINV(0.999))-$X25*X$20)*((1+($B25-2.5)*Z25)/(1-1.5*Z25)) -> 0.041497793 | AB25: =MAX(AC25-AC24,0) -> 0.0041 | AC25: ='[2]Moody''s Global Infra and Corp D'!$AJ$95 -> 0.0168 | AD25: =0.12*(1-EXP(-50*$AC25))/(1-EXP(-50))+0.24*(1-(1-EXP(-50*$AC25))/(1-EXP(-50))) -> 0.17180526 | AE25: =(0.11852-0.05478*LN($AC25))^2 -> 0.11721838 | AF25: =(AC$20*NORMSDIST((1-AD25)^(-0.5)*NORMSINV($AC25)+(AD25/(1-AD25))^(0.5)*NORMSINV(0.999))-$AC25*AC$20)*((1+($B25-2.5)*AE25)/(1-1.5*AE25)) -> 0.049221279 | AG25: =MAX(AH25-AH24,0) -> 0.0191 | AH25: ='[2]Moody''s Global Infra and Corp D'!$AJ$97 -> 0.0881 | AI25: =0.12*(1-EXP(-50*$AH25))/(1-EXP(-50))+0.24*(1-(1-EXP(-50*$AH25))/(1-EXP(-50))) -> 0.12146593 | AJ25: =(0.11852-0.05478*LN($AH25))^2 -> 0.063300602 | AK25: =(AH$20*NORMSDIST((1-AI25)^(-0.5)*NORMSINV($AH25)+(AI25/(1-AI25))^(0.5)*NORMSINV(0.999))-$AH25*AH$20)*((1+($B25-2.5)*AJ25)/(1-1.5*AJ25)) -> 0.074319462 | AL25: =MAX(AM25-AM24,0) -> 0.0409 | AM25: ='[2]Moody''s Global Infra and Corp D'!$AJ$99 -> 0.2218 | AN25: =0.12*(1-EXP(-50*$AH25))/(1-EXP(-50))+0.24*(1-(1-EXP(-50*$AH25))/(1-EXP(-50))) -> 0.12146593 | AO25: =(0.11852-0.05478*LN($AM25))^2 -> 0.040408052 | AP25: =(AM$20*NORMSDIST((1-AN25)^(-0.5)*NORMSINV($AM25)+(AN25/(1-AN25))^(0.5)*NORMSINV(0.999))-$AM25*AM$20)*((1+($B25-2.5)*AO25)/(1-1.5*AO25)) -> 0.093757764
B26: =$B$14 -> 6 | D26: =Q26*100 -> 1.800765 | E26: =V26*100 -> 3.6068728 | F26: =AA26*100 -> 4.9467305 | G26: =AF26*100 -> 5.6046796 | H26: =AK26*100 -> 8.2692404 | I26: =AP26*100 -> 9.7645973 | K26: =H26 -> 8.2692404 | M26: =N26-N25 -> 0.0003 | N26: ='[2]Moody''s Global Infra and Corp D'!$AK$89 -> 0.001 | O26: =0.12*(1-EXP(-50*$N26))/(1-EXP(-50))+0.24*(1-(1-EXP(-50*$N26))/(1-EXP(-50))) -> 0.23414753 | P26: =(0.11852-0.05478*LN($N26))^2 -> 0.24693628 | Q26: =(N$20*NORMSDIST((1-O26)^(-0.5)*NORMSINV($N26)+(O26/(1-O26))^(0.5)*NORMSINV(0.999))-$N26*N$8)*((1+($B26-2.5)*P26)/(1-1.5*P26)) -> 0.01800765 | R26: =S26-S25 -> 0.001 | S26: ='[2]Moody''s Global Infra and Corp D'!$AK$91 -> 0.0042 | T26: =0.12*(1-EXP(-50*$S26))/(1-EXP(-50))+0.24*(1-(1-EXP(-50*$S26))/(1-EXP(-50))) -> 0.21727011 | U26: =(0.11852-0.05478*LN($S26))^2 -> 0.17498569 | V26: =(S$20*NORMSDIST((1-T26)^(-0.5)*NORMSINV($S26)+(T26/(1-T26))^(0.5)*NORMSINV(0.999))-$S26*S$20)*((1+($B26-2.5)*U26)/(1-1.5*U26)) -> 0.036068728 | X26: ='[2]Moody''s Global Infra and Corp D'!$AK$93 -> 0.0116 | Y26: =0.12*(1-EXP(-50*$X26))/(1-EXP(-50))+0.24*(1-(1-EXP(-50*$X26))/(1-EXP(-50))) -> 0.1871878 | Z26: =(0.11852-0.05478*LN($X26))^2 -> 0.13152284 | AA26: =(X$20*NORMSDIST((1-Y26)^(-0.5)*NORMSINV($X26)+(Y26/(1-Y26))^(0.5)*NORMSINV(0.999))-$X26*X$20)*((1+($B26-2.5)*Z26)/(1-1.5*Z26)) -> 0.049467305 | AB26: =MAX(AC26-AC25,0) -> 0.0042 | AC26: ='[2]Moody''s Global Infra and Corp D'!$AK$95 -> 0.021 | AD26: =0.12*(1-EXP(-50*$AC26))/(1-EXP(-50))+0.24*(1-(1-EXP(-50*$AC26))/(1-EXP(-50))) -> 0.16199253 | AE26: =(0.11852-0.05478*LN($AC26))^2 -> 0.10899763 | AF26: =(AC$20*NORMSDIST((1-AD26)^(-0.5)*NORMSINV($AC26)+(AD26/(1-AD26))^(0.5)*NORMSINV(0.999))-$AC26*AC$20)*((1+($B26-2.5)*AE26)/(1-1.5*AE26)) -> 0.056046796 | AG26: =MAX(AH26-AH25,0) -> 0.0176 | AH26: ='[2]Moody''s Global Infra and Corp D'!$AK$97 -> 0.1057 | AI26: =0.12*(1-EXP(-50*$AH26))/(1-EXP(-50))+0.24*(1-(1-EXP(-50*$AH26))/(1-EXP(-50))) -> 0.12060804 | AJ26: =(0.11852-0.05478*LN($AH26))^2 -> 0.058379692 | AK26: =(AH$20*NORMSDIST((1-AI26)^(-0.5)*NORMSINV($AH26)+(AI26/(1-AI26))^(0.5)*NORMSINV(0.999))-$AH26*AH$20)*((1+($B26-2.5)*AJ26)/(1-1.5*AJ26)) -> 0.082692404 | AL26: =MAX(AM26-AM25,0) -> 0.0368 | AM26: ='[2]Moody''s Global Infra and Corp D'!$AK$99 -> 0.2586 | AN26: =0.12*(1-EXP(-50*$AH26))/(1-EXP(-50))+0.24*(1-(1-EXP(-50*$AH26))/(1-EXP(-50))) -> 0.12060804 | AO26: =(0.11852-0.05478*LN($AM26))^2 -> 0.037098019 | AP26: =(AM$20*NORMSDIST((1-AN26)^(-0.5)*NORMSINV($AM26)+(AN26/(1-AN26))^(0.5)*NORMSINV(0.999))-$AM26*AM$20)*((1+($B26-2.5)*AO26)/(1-1.5*AO26)) -> 0.097645973
B27: =$B$15 -> 7 | D27: =Q27*100 -> 2.3626814 | E27: =V27*100 -> 4.3057852 | F27: =AA27*100 -> 5.6610021 | G27: =AF27*100 -> 6.2251289 | H27: =AK27*100 -> 8.9873118 | I27: =AP27*100 -> 10.030088 | K27: =H27 -> 8.9873118 | M27: =N27-N26 -> 0.0004 | N27: ='[2]Moody''s Global Infra and Corp D'!$AL$89 -> 0.0014 | O27: =0.12*(1-EXP(-50*$N27))/(1-EXP(-50))+0.24*(1-(1-EXP(-50*$N27))/(1-EXP(-50))) -> 0.23188726 | P27: =(0.11852-0.05478*LN($N27))^2 -> 0.22895736 | Q27: =(N$20*NORMSDIST((1-O27)^(-0.5)*NORMSINV($N27)+(O27/(1-O27))^(0.5)*NORMSINV(0.999))-$N27*N$8)*((1+($B27-2.5)*P27)/(1-1.5*P27)) -> 0.023626814 | R27: =S27-S26 -> 0.001 | S27: ='[2]Moody''s Global Infra and Corp D'!$AL$91 -> 0.0052 | T27: =0.12*(1-EXP(-50*$S27))/(1-EXP(-50))+0.24*(1-(1-EXP(-50*$S27))/(1-EXP(-50))) -> 0.21252619 | U27: =(0.11852-0.05478*LN($S27))^2 -> 0.16533439 | V27: =(S$20*NORMSDIST((1-T27)^(-0.5)*NORMSINV($S27)+(T27/(1-T27))^(0.5)*NORMSINV(0.999))-$S27*S$20)*((1+($B27-2.5)*U27)/(1-1.5*U27)) -> 0.043057852 | X27: ='[2]Moody''s Global Infra and Corp D'!$AL$93 -> 0.0146 | Y27: =0.12*(1-EXP(-50*$X27))/(1-EXP(-50))+0.24*(1-(1-EXP(-50*$X27))/(1-EXP(-50))) -> 0.17782908 | Z27: =(0.11852-0.05478*LN($X27))^2 -> 0.12254234 | AA27: =(X$20*NORMSDIST((1-Y27)^(-0.5)*NORMSINV($X27)+(Y27/(1-Y27))^(0.5)*NORMSINV(0.999))-$X27*X$20)*((1+($B27-2.5)*Z27)/(1-1.5*Z27)) -> 0.056610021 | AB27: =MAX(AC27-AC26,0) -> 0.004 | AC27: ='[2]Moody''s Global Infra and Corp D'!$AL$95 -> 0.025 | AD27: =0.12*(1-EXP(-50*$AC27))/(1-EXP(-50))+0.24*(1-(1-EXP(-50*$AC27))/(1-EXP(-50))) -> 0.15438058 | AE27: =(0.11852-0.05478*LN($AC27))^2 -> 0.10278232 | AF27: =(AC$20*NORMSDIST((1-AD27)^(-0.5)*NORMSINV($AC27)+(AD27/(1-AD27))^(0.5)*NORMSINV(0.999))-$AC27*AC$20)*((1+($B27-2.5)*AE27)/(1-1.5*AE27)) -> 0.062251289 | AG27: =MAX(AH27-AH26,0) -> 0.0156 | AH27: ='[2]Moody''s Global Infra and Corp D'!$AL$97 -> 0.1213 | AI27: =0.12*(1-EXP(-50*$AH27))/(1-EXP(-50))+0.24*(1-(1-EXP(-50*$AH27))/(1-EXP(-50))) -> 0.12027873 | AJ27: =(0.11852-0.05478*LN($AH27))^2 -> 0.054792406 | AK27: =(AH$20*NORMSDIST((1-AI27)^(-0.5)*NORMSINV($AH27)+(AI27/(1-AI27))^(0.5)*NORMSINV(0.999))-$AH27*AH$20)*((1+($B27-2.5)*AJ27)/(1-1.5*AJ27)) -> 0.089873118 | AL27: =MAX(AM27-AM26,0) -> 0.0335 | AM27: ='[2]Moody''s Global Infra and Corp D'!$AL$99 -> 0.2921 | AN27: =0.12*(1-EXP(-50*$AH27))/(1-EXP(-50))+0.24*(1-(1-EXP(-50*$AH27))/(1-EXP(-50))) -> 0.12027873 | AO27: =(0.11852-0.05478*LN($AM27))^2 -> 0.034572012 | AP27: =(AM$20*NORMSDIST((1-AN27)^(-0.5)*NORMSINV($AM27)+(AN27/(1-AN27))^(0.5)*NORMSINV(0.999))-$AM27*AM$20)*((1+($B27-2.5)*AO27)/(1-1.5*AO27)) -> 0.10030088
B28: =$B$16 -> 8 | D28: =Q28*100 -> 2.6291204 | E28: =V28*100 -> 4.9287927 | F28: =AA28*100 -> 6.3154495 | G28: =AF28*100 -> 6.8142206 | H28: =AK28*100 -> 9.6268699 | I28: =AP28*100 -> 10.214806 | K28: =H28 -> 9.6268699 | M28: =N28-N27 -> 0 | N28: ='[2]Moody''s Global Infra and Corp D'!$AM$89 -> 0.0014 | O28: =0.12*(1-EXP(-50*$N28))/(1-EXP(-50))+0.24*(1-(1-EXP(-50*$N28))/(1-EXP(-50))) -> 0.23188726 | P28: =(0.11852-0.05478*LN($N28))^2 -> 0.22895736 | Q28: =(N$20*NORMSDIST((1-O28)^(-0.5)*NORMSINV($N28)+(O28/(1-O28))^(0.5)*NORMSINV(0.999))-$N28*N$8)*((1+($B28-2.5)*P28)/(1-1.5*P28)) -> 0.026291204 | R28: =S28-S27 -> 0.0008 | S28: ='[2]Moody''s Global Infra and Corp D'!$AM$91 -> 0.006 | T28: =0.12*(1-EXP(-50*$S28))/(1-EXP(-50))+0.24*(1-(1-EXP(-50*$S28))/(1-EXP(-50))) -> 0.20889819 | U28: =(0.11852-0.05478*LN($S28))^2 -> 0.1590209 | V28: =(S$20*NORMSDIST((1-T28)^(-0.5)*NORMSINV($S28)+(T28/(1-T28))^(0.5)*NORMSINV(0.999))-$S28*S$20)*((1+($B28-2.5)*U28)/(1-1.5*U28)) -> 0.049287927 | X28: ='[2]Moody''s Global Infra and Corp D'!$AM$93 -> 0.0177 | Y28: =0.12*(1-EXP(-50*$X28))/(1-EXP(-50))+0.24*(1-(1-EXP(-50*$X28))/(1-EXP(-50))) -> 0.1695257 | Z28: =(0.11852-0.05478*LN($X28))^2 -> 0.11526905 | AA28: =(X$20*NORMSDIST((1-Y28)^(-0.5)*NORMSINV($X28)+(Y28/(1-Y28))^(0.5)*NORMSINV(0.999))-$X28*X$20)*((1+($B28-2.5)*Z28)/(1-1.5*Z28)) -> 0.063154495 | AB28: =MAX(AC28-AC27,0) -> 0.004 | AC28: ='[2]Moody''s Global Infra and Corp D'!$AM$95 -> 0.029 | AD28: =0.12*(1-EXP(-50*$AC28))/(1-EXP(-50))+0.24*(1-(1-EXP(-50*$AC28))/(1-EXP(-50))) -> 0.14814843 | AE28: =(0.11852-0.05478*LN($AC28))^2 -> 0.097635232 | AF28: =(AC$20*NORMSDIST((1-AD28)^(-0.5)*NORMSINV($AC28)+(AD28/(1-AD28))^(0.5)*NORMSINV(0.999))-$AC28*AC$20)*((1+($B28-2.5)*AE28)/(1-1.5*AE28)) -> 0.068142206 | AG28: =MAX(AH28-AH27,0) -> 0.0147 | AH28: ='[2]Moody''s Global Infra and Corp D'!$AM$97 -> 0.136 | AI28: =0.12*(1-EXP(-50*$AH28))/(1-EXP(-50))+0.24*(1-(1-EXP(-50*$AH28))/(1-EXP(-50))) -> 0.12013365 | AJ28: =(0.11852-0.05478*LN($AH28))^2 -> 0.051898125 | AK28: =(AH$20*NORMSDIST((1-AI28)^(-0.5)*NORMSINV($AH28)+(AI28/(1-AI28))^(0.5)*NORMSINV(0.999))-$AH28*AH$20)*((1+($B28-2.5)*AJ28)/(1-1.5*AJ28)) -> 0.096268699 | AL28: =MAX(AM28-AM27,0) -> 0.028 | AM28: ='[2]Moody''s Global Infra and Corp D'!$AM$99 -> 0.3201 | AN28: =0.12*(1-EXP(-50*$AH28))/(1-EXP(-50))+0.24*(1-(1-EXP(-50*$AH28))/(1-EXP(-50))) -> 0.12013365 | AO28: =(0.11852-0.05478*LN($AM28))^2 -> 0.032732442 | AP28: =(AM$20*NORMSDIST((1-AN28)^(-0.5)*NORMSINV($AM28)+(AN28/(1-AN28))^(0.5)*NORMSINV(0.999))-$AM28*AM$20)*((1+($B28-2.5)*AO28)/(1-1.5*AO28)) -> 0.10214806
B29: =$B$17 -> 9 | D29: =Q29*100 -> 2.8955595 | E29: =V29*100 -> 5.5165878 | F29: =AA29*100 -> 6.9312821 | G29: =AF29*100 -> 7.3900124 | H29: =AK29*100 -> 10.20193 | I29: =AP29*100 -> 10.350553 | K29: =H29 -> 10.20193 | M29: =N29-N28 -> 0 | N29: ='[2]Moody''s Global Infra and Corp D'!$AN$89 -> 0.0014 | O29: =0.12*(1-EXP(-50*$N29))/(1-EXP(-50))+0.24*(1-(1-EXP(-50*$N29))/(1-EXP(-50))) -> 0.23188726 | P29: =(0.11852-0.05478*LN($N29))^2 -> 0.22895736 | Q29: =(N$20*NORMSDIST((1-O29)^(-0.5)*NORMSINV($N29)+(O29/(1-O29))^(0.5)*NORMSINV(0.999))-$N29*N$8)*((1+($B29-2.5)*P29)/(1-1.5*P29)) -> 0.028955595 | R29: =S29-S28 -> 0.0007 | S29: ='[2]Moody''s Global Infra and Corp D'!$AN$91 -> 0.0067 | T29: =0.12*(1-EXP(-50*$S29))/(1-EXP(-50))+0.24*(1-(1-EXP(-50*$S29))/(1-EXP(-50))) -> 0.20584057 | U29: =(0.11852-0.05478*LN($S29))^2 -> 0.15423637 | V29: =(S$20*NORMSDIST((1-T29)^(-0.5)*NORMSINV($S29)+(T29/(1-T29))^(0.5)*NORMSINV(0.999))-$S29*S$20)*((1+($B29-2.5)*U29)/(1-1.5*U29)) -> 0.055165878 | X29: ='[2]Moody''s Global Infra and Corp D'!$AN$93 -> 0.021 | Y29: =0.12*(1-EXP(-50*$X29))/(1-EXP(-50))+0.24*(1-(1-EXP(-50*$X29))/(1-EXP(-50))) -> 0.16199253 | Z29: =(0.11852-0.05478*LN($X29))^2 -> 0.10899763 | AA29: =(X$20*NORMSDIST((1-Y29)^(-0.5)*NORMSINV($X29)+(Y29/(1-Y29))^(0.5)*NORMSINV(0.999))-$X29*X$20)*((1+($B29-2.5)*Z29)/(1-1.5*Z29)) -> 0.069312821 | AB29: =MAX(AC29-AC28,0) -> 0.0042 | AC29: ='[2]Moody''s Global Infra and Corp D'!$AN$95 -> 0.0332 | AD29: =0.12*(1-EXP(-50*$AC29))/(1-EXP(-50))+0.24*(1-(1-EXP(-50*$AC29))/(1-EXP(-50))) -> 0.14281668 | AE29: =(0.11852-0.05478*LN($AC29))^2 -> 0.093059866 | AF29: =(AC$20*NORMSDIST((1-AD29)^(-0.5)*NORMSINV($AC29)+(AD29/(1-AD29))^(0.5)*NORMSINV(0.999))-$AC29*AC$20)*((1+($B29-2.5)*AE29)/(1-1.5*AE29)) -> 0.073900124 | AG29: =MAX(AH29-AH28,0) -> 0.014 | AH29: ='[2]Moody''s Global Infra and Corp D'!$AN$97 -> 0.15 | AI29: =0.12*(1-EXP(-50*$AH29))/(1-EXP(-50))+0.24*(1-(1-EXP(-50*$AH29))/(1-EXP(-50))) -> 0.12006637 | AJ29: =(0.11852-0.05478*LN($AH29))^2 -> 0.049481437 | AK29: =(AH$20*NORMSDIST((1-AI29)^(-0.5)*NORMSINV($AH29)+(AI29/(1-AI29))^(0.5)*NORMSINV(0.999))-$AH29*AH$20)*((1+($B29-2.5)*AJ29)/(1-1.5*AJ29)) -> 0.1020193 | AL29: =MAX(AM29-AM28,0) -> 0.0241 | AM29: ='[2]Moody''s Global Infra and Corp D'!$AN$99 -> 0.3442 | AN29: =0.12*(1-EXP(-50*$AH29))/(1-EXP(-50))+0.24*(1-(1-EXP(-50*$AH29))/(1-EXP(-50))) -> 0.12006637 | AO29: =(0.11852-0.05478*LN($AM29))^2 -> 0.031309407 | AP29: =(AM$20*NORMSDIST((1-AN29)^(-0.5)*NORMSINV($AM29)+(AN29/(1-AN29))^(0.5)*NORMSINV(0.999))-$AM29*AM$20)*((1+($B29-2.5)*AO29)/(1-1.5*AO29)) -> 0.10350553
B30: =$B$18 -> 10 | D30: =Q30*100 -> 3.1619985 | E30: =V30*100 -> 6.1369224 | F30: =AA30*100 -> 7.5031323 | G30: =AF30*100 -> 7.9651789 | H30: =AK30*100 -> 10.728777 | I30: =AP30*100 -> 10.472943 | K30: =H30 -> 10.728777 | M30: =N30-N29 -> 0 | N30: ='[2]Moody''s Global Infra and Corp D'!$AO$89 -> 0.0014 | O30: =0.12*(1-EXP(-50*$N30))/(1-EXP(-50))+0.24*(1-(1-EXP(-50*$N30))/(1-EXP(-50))) -> 0.23188726 | P30: =(0.11852-0.05478*LN($N30))^2 -> 0.22895736 | Q30: =(N$20*NORMSDIST((1-O30)^(-0.5)*NORMSINV($N30)+(O30/(1-O30))^(0.5)*NORMSINV(0.999))-$N30*N$8)*((1+($B30-2.5)*P30)/(1-1.5*P30)) -> 0.031619985 | R30: =S30-S29 -> 0.0009 | S30: ='[2]Moody''s Global Infra and Corp D'!$AO$91 -> 0.0076 | T30: =0.12*(1-EXP(-50*$S30))/(1-EXP(-50))+0.24*(1-(1-EXP(-50*$S30))/(1-EXP(-50))) -> 0.20206337 | U30: =(0.11852-0.05478*LN($S30))^2 -> 0.14886083 | V30: =(S$20*NORMSDIST((1-T30)^(-0.5)*NORMSINV($S30)+(T30/(1-T30))^(0.5)*NORMSINV(0.999))-$S30*S$20)*((1+($B30-2.5)*U30)/(1-1.5*U30)) -> 0.061369224 | X30: ='[2]Moody''s Global Infra and Corp D'!$AO$93 -> 0.0241 | Y30: =0.12*(1-EXP(-50*$X30))/(1-EXP(-50))+0.24*(1-(1-EXP(-50*$X30))/(1-EXP(-50))) -> 0.15596304 | Z30: =(0.11852-0.05478*LN($X30))^2 -> 0.10407416 | AA30: =(X$20*NORMSDIST((1-Y30)^(-0.5)*NORMSINV($X30)+(Y30/(1-Y30))^(0.5)*NORMSINV(0.999))-$X30*X$20)*((1+($B30-2.5)*Z30)/(1-1.5*Z30)) -> 0.075031323 | AB30: =MAX(AC30-AC29,0) -> 0.0046 | AC30: ='[2]Moody''s Global Infra and Corp D'!$AO$95 -> 0.0378 | AD30: =0.12*(1-EXP(-50*$AC30))/(1-EXP(-50))+0.24*(1-(1-EXP(-50*$AC30))/(1-EXP(-50))) -> 0.13812862 | AE30: =(0.11852-0.05478*LN($AC30))^2 -> 0.088773572 | AF30: =(AC$20*NORMSDIST((1-AD30)^(-0.5)*NORMSINV($AC30)+(AD30/(1-AD30))^(0.5)*NORMSINV(0.999))-$AC30*AC$20)*((1+($B30-2.5)*AE30)/(1-1.5*AE30)) -> 0.079651789 | AG30: =MAX(AH30-AH29,0) -> 0.0141 | AH30: ='[2]Moody''s Global Infra and Corp D'!$AO$97 -> 0.1641 | AI30: =0.12*(1-EXP(-50*$AH30))/(1-EXP(-50))+0.24*(1-(1-EXP(-50*$AH30))/(1-EXP(-50))) -> 0.12003279 | AJ30: =(0.11852-0.05478*LN($AH30))^2 -> 0.047316151 | AK30: =(AH$20*NORMSDIST((1-AI30)^(-0.5)*NORMSINV($AH30)+(AI30/(1-AI30))^(0.5)*NORMSINV(0.999))-$AH30*AH$20)*((1+($B30-2.5)*AJ30)/(1-1.5*AJ30)) -> 0.10728777 | AL30: =MAX(AM30-AM29,0) -> 0.0189 | AM30: ='[2]Moody''s Global Infra and Corp D'!$AO$99 -> 0.3631 | AN30: =0.12*(1-EXP(-50*$AH30))/(1-EXP(-50))+0.24*(1-(1-EXP(-50*$AH30))/(1-EXP(-50))) -> 0.12003279 | AO30: =(0.11852-0.05478*LN($AM30))^2 -> 0.030281693 | AP30: =(AM$20*NORMSDIST((1-AN30)^(-0.5)*NORMSINV($AM30)+(AN30/(1-AN30))^(0.5)*NORMSINV(0.999))-$AM30*AM$20)*((1+($B30-2.5)*AO30)/(1-1.5*AO30)) -> 0.10472943 | AY30: PPP only | BE30: F-IRB (LGD=45%) | BK30: PPP only
D32: ='[2]Table - SII - Interim'!D27:R27 -> Infrastructure Investment (Global) 3/ | N32: =1-'[2]Moody''s Global Infra and Corp D'!P98 -> 0.44 | S32: =N32 -> 0.44 | X32: =N32 -> 0.44 | AC32: =X32 -> 0.44 | AH32: =X32 -> 0.44 | AM32: =AC32 -> 0.44 | AN32: stdev(rec.) | AO32: =AO8*AM32/AM8 -> 0.23916129 | AP32: =AO32*(AM32/(1-AM32)) -> 0.18791244 | AS32: Marginal PD ↓/Recovery → | AT32: =1-'[2]default rates (3)'!CR13/100 -> 0.20519401 | AU32: stdev(rec.) | AV32: ='[2]default rates (3)'!CS13 -> 0.3371022 | AW32: =AV32*(AT32/(1-AT32)) -> 0.087029228 | AY32: Marginal PD ↓/Recovery → | AZ32: =1-'[3]default rates'!$CR$66/100 -> 0.14192385 | BA32: stdev(rec.) | BB32: ='[3]default rates'!$CS$66 -> 0.29046617 | BC32: =BB32*(AZ32/(1-AZ32)) -> 0.048042445 | BE32: Marginal PD ↓/Recovery → | BF32: 0.45 | BG32: stdev(rec.) | BH32: =BF32/AT32*AV32 -> 0.73928079 | BI32: =BH32*(BF32/(1-BF32)) -> 0.6048661 | BK32: Marginal PD ↓/Recovery → | BL32: =BF32 -> 0.45 | BM32: stdev(rec.) | BN32: ='[3]default rates'!$CS$66 -> 0.29046617 | BO32: =BN32*(BL32/(1-BL32)) -> 0.23765414
B33: =$B$9 -> 1 | D33: =Q33*100 -> 0.034785308 | E33: =V33*100 -> 0.034785308 | F33: =AA33*100 -> 0.034785308 | G33: =AF33*100 -> 1.4604107 | H33: =AK33*100 -> 3.6017124 | I33: =AP33*100 -> 5.8287812 | K33: =AW33*100 -> 3.1244816 | N33: ='[2]Moody''s Global Infra and Corp D'!$P$61 -> 1e-05 | O33: =0.12*(1-EXP(-50*$N33))/(1-EXP(-50))+0.24*(1-(1-EXP(-50*$N33))/(1-EXP(-50))) -> 0.23994001 | P33: =(0.11852-0.05478*LN($N33))^2 -> 0.56129773 | Q33: =(N$32*NORMSDIST((1-O33)^(-0.5)*NORMSINV($N33)+(O33/(1-O33))^(0.5)*NORMSINV(0.999))-$N33*N$32)*((1+($B33-2.5)*P33)/(1-1.5*P33)) -> 0.00034785308 | S33: ='[2]Moody''s Global Infra and Corp D'!$P$62 -> 1e-05 | T33: =0.12*(1-EXP(-50*$S33))/(1-EXP(-50))+0.24*(1-(1-EXP(-50*$S33))/(1-EXP(-50))) -> 0.23994001 | U33: =(0.11852-0.05478*LN($S33))^2 -> 0.56129773 | V33: =(S$32*NORMSDIST((1-T33)^(-0.5)*NORMSINV($S33)+(T33/(1-T33))^(0.5)*NORMSINV(0.999))-$S33*S$32)*((1+($B33-2.5)*U33)/(1-1.5*U33)) -> 0.00034785308 | W33: =X33 -> 1e-05 | X33: ='[2]Moody''s Global Infra and Corp D'!$P$63 -> 1e-05 | Y33: =0.12*(1-EXP(-50*$X33))/(1-EXP(-50))+0.24*(1-(1-EXP(-50*$X33))/(1-EXP(-50))) -> 0.23994001 | Z33: =(0.11852-0.05478*LN($X33))^2 -> 0.56129773 | AA33: =(X$32*NORMSDIST((1-Y33)^(-0.5)*NORMSINV($X33)+(Y33/(1-Y33))^(0.5)*NORMSINV(0.999))-$X33*X$32)*((1+($B33-2.5)*Z33)/(1-1.5*Z33)) -> 0.00034785308 | AB33: =AC33 -> 0.001 | AC33: ='[2]Moody''s Global Infra and Corp D'!$P$64 -> 0.001 | AD33: =0.12*(1-EXP(-50*$AC33))/(1-EXP(-50))+0.24*(1-(1-EXP(-50*$AC33))/(1-EXP(-50))) -> 0.23414753 | AE33: =(0.11852-0.05478*LN($AC33))^2 -> 0.24693628 | AF33: =(AC$32*NORMSDIST((1-AD33)^(-0.5)*NORMSINV($AC33)+(AD33/(1-AD33))^(0.5)*NORMSINV(0.999))-$AC33*AC$32)*((1+($B33-2.5)*AE33)/(1-1.5*AE33)) -> 0.014604107 | AG33: =AH33 -> 0.004 | AH33: ='[2]Moody''s Global Infra and Corp D'!$P$65 -> 0.004 | AI33: =0.12*(1-EXP(-50*$AH33))/(1-EXP(-50))+0.24*(1-(1-EXP(-50*$AH33))/(1-EXP(-50))) -> 0.21824769 | AJ33: =(0.11852-0.05478*LN($AH33))^2 -> 0.1772289 | AK33: =(AH$32*NORMSDIST((1-AI33)^(-0.5)*NORMSINV($AH33)+(AI33/(1-AI33))^(0.5)*NORMSINV(0.999))-$AH33*AH$32)*((1+($B33-2.5)*AJ33)/(1-1.5*AJ33)) -> 0.036017124 | AL33: ='[9]default rates'!$BI$114 -> 0.014681935 | AM33: ='[2]Moody''s Global Infra and Corp D'!$P$66 -> 0.025 | AN33: =0.12*(1-EXP(-50*$AM33))/(1-EXP(-50))+0.24*(1-(1-EXP(-50*$AM33))/(1-EXP(-50))) -> 0.15438058 | AO33: =(0.11852-0.05478*LN($AM33))^2 -> 0.10278232 | AP33: =(AM$32*NORMSDIST((1-AN33)^(-0.5)*NORMSINV($AL33)+(AN33/(1-AN33))^(0.5)*NORMSINV(0.999))-$AL33*AM$32)*((1+($B33-2.5)*AO33)/(1-1.5*AO33)) -> 0.058287812 | AS33: ='[3]default rates'!$AR$146 -> 0.014681935 | AT33: =AS33 -> 0.014681935 | AU33: =0.12*(1-EXP(-50*$AT33))/(1-EXP(-50))+0.24*(1-(1-EXP(-50*$AT33))/(1-EXP(-50))) -> 0.17759265 | AV33: =(0.11852-0.05478*LN($AT33))^2 -> 0.1223278 | AW33: =(AT$32*NORMSDIST((1-AU33)^(-0.5)*NORMSINV($AT33)+(AU33/(1-AU33))^(0.5)*NORMSINV(0.999))-$AT33*AT$32)*((1+($B33-2.5)*AV33)/(1-1.5*AV33)) -> 0.031244816 | AY33: ='[3]default rates'!$BG$333 -> 0.0077661225 | AZ33: =AY33 -> 0.0077661225 | BA33: =0.12*(1-EXP(-50*$AT33))/(1-EXP(-50))+0.24*(1-(1-EXP(-50*$AT33))/(1-EXP(-50))) -> 0.17759265 | BB33: =(0.11852-0.05478*LN($AT33))^2 -> 0.1223278 | BC33: =(AZ$32*NORMSDIST((1-BA33)^(-0.5)*NORMSINV($AZ33)+(BA33/(1-BA33))^(0.5)*NORMSINV(0.999))-$AZ33*AZ$32)*((1+($B33-2.5)*BB33)/(1-1.5*BB33)) -> 0.01435841 | BE33: ='[3]default rates'!$AR$146 -> 0.014681935 | BF33: =BE33 -> 0.014681935 | BG33: =0.12*(1-EXP(-50*$AT33))/(1-EXP(-50))+0.24*(1-(1-EXP(-50*$AT33))/(1-EXP(-50))) -> 0.17759265 | BH33: =(0.11852-0.05478*LN($AT33))^2 -> 0.1223278 | BI33: =(BF$32*NORMSDIST((1-BG33)^(-0.5)*NORMSINV($BF33)+(BG33/(1-BG33))^(0.5)*NORMSINV(0.999))-$BF33*BF$32)*((1+($B33-2.5)*BH33)/(1-1.5*BH33)) -> 0.068521334 | BK33: ='[3]default rates'!$BG$333 -> 0.0077661225 | BL33: =BK33 -> 0.0077661225 | BM33: =0.12*(1-EXP(-50*$AT33))/(1-EXP(-50))+0.24*(1-(1-EXP(-50*$AT33))/(1-EXP(-50))) -> 0.17759265 | BN33: =(0.11852-0.05478*LN($AT33))^2 -> 0.1223278 | BO33: =(BL$32*NORMSDIST((1-BM33)^(-0.5)*NORMSINV($BL33)+(BM33/(1-BM33))^(0.5)*NORMSINV(0.999))-$BL33*BL$32)*((1+($B33-2.5)*BN33)/(1-1.5*BN33)) -> 0.045526418
B34: =$B$10 -> 2 | D34: =Q34*100 -> 0.15831896 | E34: =V34*100 -> 0.15831896 | F34: =AA34*100 -> 0.15831896 | G34: =AF34*100 -> 3.0719039 | H34: =AK34*100 -> 7.3947377 | I34: =AP34*100 -> 11.565537 | K34: =AW34*100 -> 4.3975694 | N34: ='[2]Moody''s Global Infra and Corp D'!$Q$61 -> 1e-05 | O34: =0.12*(1-EXP(-50*$N34))/(1-EXP(-50))+0.24*(1-(1-EXP(-50*$N34))/(1-EXP(-50))) -> 0.23994001 | P34: =(0.11852-0.05478*LN($N34))^2 -> 0.56129773 | Q34: =(N$32*NORMSDIST((1-O34)^(-0.5)*NORMSINV($N34)+(O34/(1-O34))^(0.5)*NORMSINV(0.999))-$N34*N$32)*((1+($B34-2.5)*P34)/(1-1.5*P34)) -> 0.0015831896 | S34: ='[2]Moody''s Global Infra and Corp D'!$Q$62 -> 1e-05 | T34: =0.12*(1-EXP(-50*$S34))/(1-EXP(-50))+0.24*(1-(1-EXP(-50*$S34))/(1-EXP(-50))) -> 0.23994001 | U34: =(0.11852-0.05478*LN($S34))^2 -> 0.56129773 | V34: =(S$32*NORMSDIST((1-T34)^(-0.5)*NORMSINV($S34)+(T34/(1-T34))^(0.5)*NORMSINV(0.999))-$S34*S$32)*((1+($B34-2.5)*U34)/(1-1.5*U34)) -> 0.0015831896 | W34: =MAX(X34-X33,0) -> 0 | X34: ='[2]Moody''s Global Infra and Corp D'!$Q$63 -> 1e-05 | Y34: =0.12*(1-EXP(-50*$X34))/(1-EXP(-50))+0.24*(1-(1-EXP(-50*$X34))/(1-EXP(-50))) -> 0.23994001 | Z34: =(0.11852-0.05478*LN($X34))^2 -> 0.56129773 | AA34: =(X$32*NORMSDIST((1-Y34)^(-0.5)*NORMSINV($X34)+(Y34/(1-Y34))^(0.5)*NORMSINV(0.999))-$X34*X$32)*((1+($B34-2.5)*Z34)/(1-1.5*Z34)) -> 0.0015831896 | AB34: =MAX(AC34-AC33,0) -> 0.001 | AC34: ='[2]Moody''s Global Infra and Corp D'!$Q$64 -> 0.002 | AD34: =0.12*(1-EXP(-50*$AC34))/(1-EXP(-50))+0.24*(1-(1-EXP(-50*$AC34))/(1-EXP(-50))) -> 0.22858049 | AE34: =(0.11852-0.05478*LN($AC34))^2 -> 0.21064082 | AF34: =(AC$32*NORMSDIST((1-AD34)^(-0.5)*NORMSINV($AC34)+(AD34/(1-AD34))^(0.5)*NORMSINV(0.999))-$AC34*AC$32)*((1+($B34-2.5)*AE34)/(1-1.5*AE34)) -> 0.030719039 | AG34: =MAX(AH34-AH33,0) -> 0.009 | AH34: ='[2]Moody''s Global Infra and Corp D'!$Q$65 -> 0.013 | AI34: =0.12*(1-EXP(-50*$AH34))/(1-EXP(-50))+0.24*(1-(1-EXP(-50*$AH34))/(1-EXP(-50))) -> 0.18264549 | AJ34: =(0.11852-0.05478*LN($AH34))^2 -> 0.12703444 | AK34: =(AH$32*NORMSDIST((1-AI34)^(-0.5)*NORMSINV($AH34)+(AI34/(1-AI34))^(0.5)*NORMSINV(0.999))-$AH34*AH$32)*((1+($B34-2.5)*AJ34)/(1-1.5*AJ34)) -> 0.073947377 | AL34: ='[9]default rates'!$BJ$114 -> 0.013934007 | AM34: ='[2]Moody''s Global Infra and Corp D'!$Q$66 -> 0.054 | AN34: =0.12*(1-EXP(-50*$AM34))/(1-EXP(-50))+0.24*(1-(1-EXP(-50*$AM34))/(1-EXP(-50))) -> 0.12806466 | AO34: =(0.11852-0.05478*LN($AM34))^2 -> 0.077512289 | AP34: =(AM$32*NORMSDIST((1-AN34)^(-0.5)*NORMSINV($AM34)+(AN34/(1-AN34))^(0.5)*NORMSINV(0.999))-$AM34*AM$32)*((1+($B34-2.5)*AO34)/(1-1.5*AO34)) -> 0.11565537 | AS34: ='[3]default rates'!$AS$146 -> 0.013934007 | AT34: =AT33+AS34 -> 0.028615942 | AU34: =0.12*(1-EXP(-50*$AT34))/(1-EXP(-50))+0.24*(1-(1-EXP(-50*$AT34))/(1-EXP(-50))) -> 0.14869419 | AV34: =(0.11852-0.05478*LN($AT34))^2 -> 0.098092165 | AW34: =(AT$32*NORMSDIST((1-AU34)^(-0.5)*NORMSINV($AT34)+(AU34/(1-AU34))^(0.5)*NORMSINV(0.999))-$AT34*AT$32)*((1+($B34-2.5)*AV34)/(1-1.5*AV34)) -> 0.043975694 | AY34: ='[3]default rates'!$BH$333 -> 0.0074333815 | AZ34: =AZ33+AY34 -> 0.015199504 | BA34: =0.12*(1-EXP(-50*$AT34))/(1-EXP(-50))+0.24*(1-(1-EXP(-50*$AT34))/(1-EXP(-50))) -> 0.14869419 | BB34: =(0.11852-0.05478*LN($AT34))^2 -> 0.098092165 | BC34: =(AZ$32*NORMSDIST((1-BA34)^(-0.5)*NORMSINV($AZ34)+(BA34/(1-BA34))^(0.5)*NORMSINV(0.999))-$AZ34*AZ$32)*((1+($B34-2.5)*BB34)/(1-1.5*BB34)) -> 0.020660314 | BE34: ='[3]default rates'!$AS$146 -> 0.013934007 | BF34: =BF33+BE34 -> 0.028615942 | BG34: =0.12*(1-EXP(-50*$AT34))/(1-EXP(-50))+0.24*(1-(1-EXP(-50*$AT34))/(1-EXP(-50))) -> 0.14869419 | BH34: =(0.11852-0.05478*LN($AT34))^2 -> 0.098092165 | BI34: =(BF$32*NORMSDIST((1-BG34)^(-0.5)*NORMSINV($BF34)+(BG34/(1-BG34))^(0.5)*NORMSINV(0.999))-$BF34*BF$32)*((1+($B34-2.5)*BH34)/(1-1.5*BH34)) -> 0.09644074 | BK34: ='[3]default rates'!$BH$333 -> 0.0074333815 | BL34: =BL33+BK34 -> 0.015199504 | BM34: =0.12*(1-EXP(-50*$AT34))/(1-EXP(-50))+0.24*(1-(1-EXP(-50*$AT34))/(1-EXP(-50))) -> 0.14869419 | BN34: =(0.11852-0.05478*LN($AT34))^2 -> 0.098092165 | BO34: =(BL$32*NORMSDIST((1-BM34)^(-0.5)*NORMSINV($BL34)+(BM34/(1-BM34))^(0.5)*NORMSINV(0.999))-$BL34*BL$32)*((1+($B34-2.5)*BN34)/(1-1.5*BN34)) -> 0.065507959
B35: =$B$11 -> 3 | D35: =Q35*100 -> 0.28185261 | E35: =V35*100 -> 0.28185261 | F35: =AA35*100 -> 2.6059981 | G35: =AF35*100 -> 5.3406534 | H35: =AK35*100 -> 9.8330965 | I35: =AP35*100 -> 14.792513 | K35: =AW35*100 -> 5.2839018 | N35: ='[2]Moody''s Global Infra and Corp D'!$R$61 -> 1e-05 | O35: =0.12*(1-EXP(-50*$N35))/(1-EXP(-50))+0.24*(1-(1-EXP(-50*$N35))/(1-EXP(-50))) -> 0.23994001 | P35: =(0.11852-0.05478*LN($N35))^2 -> 0.56129773 | Q35: =(N$32*NORMSDIST((1-O35)^(-0.5)*NORMSINV($N35)+(O35/(1-O35))^(0.5)*NORMSINV(0.999))-$N35*N$32)*((1+($B35-2.5)*P35)/(1-1.5*P35)) -> 0.0028185261 | S35: ='[2]Moody''s Global Infra and Corp D'!$R$62 -> 1e-05 | T35: =0.12*(1-EXP(-50*$S35))/(1-EXP(-50))+0.24*(1-(1-EXP(-50*$S35))/(1-EXP(-50))) -> 0.23994001 | U35: =(0.11852-0.05478*LN($S35))^2 -> 0.56129773 | V35: =(S$32*NORMSDIST((1-T35)^(-0.5)*NORMSINV($S35)+(T35/(1-T35))^(0.5)*NORMSINV(0.999))-$S35*S$32)*((1+($B35-2.5)*U35)/(1-1.5*U35)) -> 0.0028185261 | W35: =MAX(X35-X34,0) -> 0.00099 | X35: ='[2]Moody''s Global Infra and Corp D'!$R$63 -> 0.001 | Y35: =0.12*(1-EXP(-50*$X35))/(1-EXP(-50))+0.24*(1-(1-EXP(-50*$X35))/(1-EXP(-50))) -> 0.23414753 | Z35: =(0.11852-0.05478*LN($X35))^2 -> 0.24693628 | AA35: =(X$32*NORMSDIST((1-Y35)^(-0.5)*NORMSINV($X35)+(Y35/(1-Y35))^(0.5)*NORMSINV(0.999))-$X35*X$32)*((1+($B35-2.5)*Z35)/(1-1.5*Z35)) -> 0.026059981 | AB35: =MAX(AC35-AC34,0) -> 0.002 | AC35: ='[2]Moody''s Global Infra and Corp D'!$R$64 -> 0.004 | AD35: =0.12*(1-EXP(-50*$AC35))/(1-EXP(-50))+0.24*(1-(1-EXP(-50*$AC35))/(1-EXP(-50))) -> 0.21824769 | AE35: =(0.11852-0.05478*LN($AC35))^2 -> 0.1772289 | AF35: =(AC$32*NORMSDIST((1-AD35)^(-0.5)*NORMSINV($AC35)+(AD35/(1-AD35))^(0.5)*NORMSINV(0.999))-$AC35*AC$32)*((1+($B35-2.5)*AE35)/(1-1.5*AE35)) -> 0.053406534 | AG35: =MAX(AH35-AH34,0) -> 0.01 | AH35: ='[2]Moody''s Global Infra and Corp D'!$R$65 -> 0.023 | AI35: =0.12*(1-EXP(-50*$AH35))/(1-EXP(-50))+0.24*(1-(1-EXP(-50*$AH35))/(1-EXP(-50))) -> 0.15799641 | AJ35: =(0.11852-0.05478*LN($AH35))^2 -> 0.10573193 | AK35: =(AH$32*NORMSDIST((1-AI35)^(-0.5)*NORMSINV($AH35)+(AI35/(1-AI35))^(0.5)*NORMSINV(0.999))-$AH35*AH$32)*((1+($B35-2.5)*AJ35)/(1-1.5*AJ35)) -> 0.098330965 | AL35: ='[9]default rates'!$BK$114 -> 0.010626389 | AM35: ='[2]Moody''s Global Infra and Corp D'!$R$66 -> 0.087 | AN35: =0.12*(1-EXP(-50*$AM35))/(1-EXP(-50))+0.24*(1-(1-EXP(-50*$AM35))/(1-EXP(-50))) -> 0.12154882 | AO35: =(0.11852-0.05478*LN($AM35))^2 -> 0.063647412 | AP35: =(AM$32*NORMSDIST((1-AN35)^(-0.5)*NORMSINV($AM35)+(AN35/(1-AN35))^(0.5)*NORMSINV(0.999))-$AM35*AM$32)*((1+($B35-2.5)*AO35)/(1-1.5*AO35)) -> 0.14792513 | AS35: ='[3]default rates'!$AT$146 -> 0.010626389 | AT35: =AT34+AS35 -> 0.039242331 | AU35: =0.12*(1-EXP(-50*$AT35))/(1-EXP(-50))+0.24*(1-(1-EXP(-50*$AT35))/(1-EXP(-50))) -> 0.13686727 | AV35: =(0.11852-0.05478*LN($AT35))^2 -> 0.087555389 | AW35: =(AT$32*NORMSDIST((1-AU35)^(-0.5)*NORMSINV($AT35)+(AU35/(1-AU35))^(0.5)*NORMSINV(0.999))-$AT35*AT$32)*((1+($B35-2.5)*AV35)/(1-1.5*AV35)) -> 0.052839018 | AY35: ='[3]default rates'!$BI$333 -> 0.0071503814 | AZ35: =AZ34+AY35 -> 0.022349885 | BA35: =0.12*(1-EXP(-50*$AT35))/(1-EXP(-50))+0.24*(1-(1-EXP(-50*$AT35))/(1-EXP(-50))) -> 0.13686727 | BB35: =(0.11852-0.05478*LN($AT35))^2 -> 0.087555389 | BC35: =(AZ$32*NORMSDIST((1-BA35)^(-0.5)*NORMSINV($AZ35)+(BA35/(1-BA35))^(0.5)*NORMSINV(0.999))-$AZ35*AZ$32)*((1+($B35-2.5)*BB35)/(1-1.5*BB35)) -> 0.026224483 | BE35: ='[3]default rates'!$AT$146 -> 0.010626389 | BF35: =BF34+BE35 -> 0.039242331 | BG35: =0.12*(1-EXP(-50*$AT35))/(1-EXP(-50))+0.24*(1-(1-EXP(-50*$AT35))/(1-EXP(-50))) -> 0.13686727 | BH35: =(0.11852-0.05478*LN($AT35))^2 -> 0.087555389 | BI35: =(BF$32*NORMSDIST((1-BG35)^(-0.5)*NORMSINV($BF35)+(BG35/(1-BG35))^(0.5)*NORMSINV(0.999))-$BF35*BF$32)*((1+($B35-2.5)*BH35)/(1-1.5*BH35)) -> 0.11587842 | BK35: ='[3]default rates'!$BI$333 -> 0.0071503814 | BL35: =BL34+BK35 -> 0.022349885 | BM35: =0.12*(1-EXP(-50*$AT35))/(1-EXP(-50))+0.24*(1-(1-EXP(-50*$AT35))/(1-EXP(-50))) -> 0.13686727 | BN35: =(0.11852-0.05478*LN($AT35))^2 -> 0.087555389 | BO35: =(BL$32*NORMSDIST((1-BM35)^(-0.5)*NORMSINV($BL35)+(BM35/(1-BM35))^(0.5)*NORMSINV(0.999))-$BL35*BL$32)*((1+($B35-2.5)*BN35)/(1-1.5*BN35)) -> 0.083150349
B36: =$B$12 -> 4 | D36: =Q36*100 -> 0.40538626 | E36: =V36*100 -> 0.40538626 | F36: =AA36*100 -> 3.1787918 | G36: =AF36*100 -> 6.8099078 | H36: =AK36*100 -> 11.932135 | I36: =AP36*100 -> 17.225711 | K36: =AW36*100 -> 6.0201774 | N36: ='[2]Moody''s Global Infra and Corp D'!$S$61 -> 1e-05 | O36: =0.12*(1-EXP(-50*$N36))/(1-EXP(-50))+0.24*(1-(1-EXP(-50*$N36))/(1-EXP(-50))) -> 0.23994001 | P36: =(0.11852-0.05478*LN($N36))^2 -> 0.56129773 | Q36: =(N$32*NORMSDIST((1-O36)^(-0.5)*NORMSINV($N36)+(O36/(1-O36))^(0.5)*NORMSINV(0.999))-$N36*N$32)*((1+($B36-2.5)*P36)/(1-1.5*P36)) -> 0.0040538626 | S36: ='[2]Moody''s Global Infra and Corp D'!$S$62 -> 1e-05 | T36: =0.12*(1-EXP(-50*$S36))/(1-EXP(-50))+0.24*(1-(1-EXP(-50*$S36))/(1-EXP(-50))) -> 0.23994001 | U36: =(0.11852-0.05478*LN($S36))^2 -> 0.56129773 | V36: =(S$32*NORMSDIST((1-T36)^(-0.5)*NORMSINV($S36)+(T36/(1-T36))^(0.5)*NORMSINV(0.999))-$S36*S$32)*((1+($B36-2.5)*U36)/(1-1.5*U36)) -> 0.0040538626 | W36: =MAX(X36-X35,0) -> 0 | X36: ='[2]Moody''s Global Infra and Corp D'!$S$63 -> 0.001 | Y36: =0.12*(1-EXP(-50*$X36))/(1-EXP(-50))+0.24*(1-(1-EXP(-50*$X36))/(1-EXP(-50))) -> 0.23414753 | Z36: =(0.11852-0.05478*LN($X36))^2 -> 0.24693628 | AA36: =(X$32*NORMSDIST((1-Y36)^(-0.5)*NORMSINV($X36)+(Y36/(1-Y36))^(0.5)*NORMSINV(0.999))-$X36*X$32)*((1+($B36-2.5)*Z36)/(1-1.5*Z36)) -> 0.031787918 | AB36: =MAX(AC36-AC35,0) -> 0.001 | AC36: ='[2]Moody''s Global Infra and Corp D'!$S$64 -> 0.005 | AD36: =0.12*(1-EXP(-50*$AC36))/(1-EXP(-50))+0.24*(1-(1-EXP(-50*$AC36))/(1-EXP(-50))) -> 0.21345609 | AE36: =(0.11852-0.05478*LN($AC36))^2 -> 0.16708623 | AF36: =(AC$32*NORMSDIST((1-AD36)^(-0.5)*NORMSINV($AC36)+(AD36/(1-AD36))^(0.5)*NORMSINV(0.999))-$AC36*AC$32)*((1+($B36-2.5)*AE36)/(1-1.5*AE36)) -> 0.068099078 | AG36: =MAX(AH36-AH35,0) -> 0.012 | AH36: ='[2]Moody''s Global Infra and Corp D'!$S$65 -> 0.035 | AI36: =0.12*(1-EXP(-50*$AH36))/(1-EXP(-50))+0.24*(1-(1-EXP(-50*$AH36))/(1-EXP(-50))) -> 0.14085287 | AJ36: =(0.11852-0.05478*LN($AH36))^2 -> 0.091303607 | AK36: =(AH$32*NORMSDIST((1-AI36)^(-0.5)*NORMSINV($AH36)+(AI36/(1-AI36))^(0.5)*NORMSINV(0.999))-$AH36*AH$32)*((1+($B36-2.5)*AJ36)/(1-1.5*AJ36)) -> 0.11932135 | AL36: ='[9]default rates'!$BL$114 -> 0.0079422334 | AM36: ='[2]Moody''s Global Infra and Corp D'!$S$66 -> 0.115 | AN36: =0.12*(1-EXP(-50*$AM36))/(1-EXP(-50))+0.24*(1-(1-EXP(-50*$AM36))/(1-EXP(-50))) -> 0.12038193 | AO36: =(0.11852-0.05478*LN($AM36))^2 -> 0.05616874 | AP36: =(AM$32*NORMSDIST((1-AN36)^(-0.5)*NORMSINV($AM36)+(AN36/(1-AN36))^(0.5)*NORMSINV(0.999))-$AM36*AM$32)*((1+($B36-2.5)*AO36)/(1-1.5*AO36)) -> 0.17225711 | AS36: ='[3]default rates'!$AU$146 -> 0.0079422334 | AT36: =AT35+AS36 -> 0.047184564 | AU36: =0.12*(1-EXP(-50*$AT36))/(1-EXP(-50))+0.24*(1-(1-EXP(-50*$AT36))/(1-EXP(-50))) -> 0.13133917 | AV36: =(0.11852-0.05478*LN($AT36))^2 -> 0.081682243 | AW36: =(AT$32*NORMSDIST((1-AU36)^(-0.5)*NORMSINV($AT36)+(AU36/(1-AU36))^(0.5)*NORMSINV(0.999))-$AT36*AT$32)*((1+($B36-2.5)*AV36)/(1-1.5*AV36)) -> 0.060201774 | AY36: ='[3]default rates'!$BJ$333 -> 0.0066886779 | AZ36: =AZ35+AY36 -> 0.029038563 | BA36: =0.12*(1-EXP(-50*$AT36))/(1-EXP(-50))+0.24*(1-(1-EXP(-50*$AT36))/(1-EXP(-50))) -> 0.13133917 | BB36: =(0.11852-0.05478*LN($AT36))^2 -> 0.081682243 | BC36: =(AZ$32*NORMSDIST((1-BA36)^(-0.5)*NORMSINV($AZ36)+(BA36/(1-BA36))^(0.5)*NORMSINV(0.999))-$AZ36*AZ$32)*((1+($B36-2.5)*BB36)/(1-1.5*BB36)) -> 0.031544079 | BE36: ='[3]default rates'!$AU$146 -> 0.0079422334 | BF36: =BF35+BE36 -> 0.047184564 | BG36: =0.12*(1-EXP(-50*$AT36))/(1-EXP(-50))+0.24*(1-(1-EXP(-50*$AT36))/(1-EXP(-50))) -> 0.13133917 | BH36: =(0.11852-0.05478*LN($AT36))^2 -> 0.081682243 | BI36: =(BF$32*NORMSDIST((1-BG36)^(-0.5)*NORMSINV($BF36)+(BG36/(1-BG36))^(0.5)*NORMSINV(0.999))-$BF36*BF$32)*((1+($B36-2.5)*BH36)/(1-1.5*BH36)) -> 0.13202529 | BK36: ='[3]default rates'!$BJ$333 -> 0.0066886779 | BL36: =BL35+BK36 -> 0.029038563 | BM36: =0.12*(1-EXP(-50*$AT36))/(1-EXP(-50))+0.24*(1-(1-EXP(-50*$AT36))/(1-EXP(-50))) -> 0.13133917 | BN36: =(0.11852-0.05478*LN($AT36))^2 -> 0.081682243 | BO36: =(BL$32*NORMSDIST((1-BM36)^(-0.5)*NORMSINV($BL36)+(BM36/(1-BM36))^(0.5)*NORMSINV(0.999))-$BL36*BL$32)*((1+($B36-2.5)*BN36)/(1-1.5*BN36)) -> 0.10001727
B37: =$B$13 -> 5 | D37: =Q37*100 -> 0.52891991 | E37: =V37*100 -> 0.52891991 | F37: =AA37*100 -> 5.2416249 | G37: =AF37*100 -> 8.695387 | H37: =AK37*100 -> 13.834373 | I37: =AP37*100 -> 19.102999 | K37: =AW37*100 -> 6.670781 | N37: ='[2]Moody''s Global Infra and Corp D'!$T$61 -> 1e-05 | O37: =0.12*(1-EXP(-50*$N37))/(1-EXP(-50))+0.24*(1-(1-EXP(-50*$N37))/(1-EXP(-50))) -> 0.23994001 | P37: =(0.11852-0.05478*LN($N37))^2 -> 0.56129773 | Q37: =(N$32*NORMSDIST((1-O37)^(-0.5)*NORMSINV($N37)+(O37/(1-O37))^(0.5)*NORMSINV(0.999))-$N37*N$32)*((1+($B37-2.5)*P37)/(1-1.5*P37)) -> 0.0052891991 | S37: ='[2]Moody''s Global Infra and Corp D'!$T$62 -> 1e-05 | T37: =0.12*(1-EXP(-50*$S37))/(1-EXP(-50))+0.24*(1-(1-EXP(-50*$S37))/(1-EXP(-50))) -> 0.23994001 | U37: =(0.11852-0.05478*LN($S37))^2 -> 0.56129773 | V37: =(S$32*NORMSDIST((1-T37)^(-0.5)*NORMSINV($S37)+(T37/(1-T37))^(0.5)*NORMSINV(0.999))-$S37*S$32)*((1+($B37-2.5)*U37)/(1-1.5*U37)) -> 0.0052891991 | W37: =MAX(X37-X36,0) -> 0.001 | X37: ='[2]Moody''s Global Infra and Corp D'!$T$63 -> 0.002 | Y37: =0.12*(1-EXP(-50*$X37))/(1-EXP(-50))+0.24*(1-(1-EXP(-50*$X37))/(1-EXP(-50))) -> 0.22858049 | Z37: =(0.11852-0.05478*LN($X37))^2 -> 0.21064082 | AA37: =(X$32*NORMSDIST((1-Y37)^(-0.5)*NORMSINV($X37)+(Y37/(1-Y37))^(0.5)*NORMSINV(0.999))-$X37*X$32)*((1+($B37-2.5)*Z37)/(1-1.5*Z37)) -> 0.052416249 | AB37: =MAX(AC37-AC36,0) -> 0.002 | AC37: ='[2]Moody''s Global Infra and Corp D'!$T$64 -> 0.007 | AD37: =0.12*(1-EXP(-50*$AC37))/(1-EXP(-50))+0.24*(1-(1-EXP(-50*$AC37))/(1-EXP(-50))) -> 0.20456257 | AE37: =(0.11852-0.05478*LN($AC37))^2 -> 0.15235741 | AF37: =(AC$32*NORMSDIST((1-AD37)^(-0.5)*NORMSINV($AC37)+(AD37/(1-AD37))^(0.5)*NORMSINV(0.999))-$AC37*AC$32)*((1+($B37-2.5)*AE37)/(1-1.5*AE37)) -> 0.08695387 | AG37: =MAX(AH37-AH36,0) -> 0.012 | AH37: ='[2]Moody''s Global Infra and Corp D'!$T$65 -> 0.047 | AI37: =0.12*(1-EXP(-50*$AH37))/(1-EXP(-50))+0.24*(1-(1-EXP(-50*$AH37))/(1-EXP(-50))) -> 0.1314443 | AJ37: =(0.11852-0.05478*LN($AH37))^2 -> 0.081805008 | AK37: =(AH$32*NORMSDIST((1-AI37)^(-0.5)*NORMSINV($AH37)+(AI37/(1-AI37))^(0.5)*NORMSINV(0.999))-$AH37*AH$32)*((1+($B37-2.5)*AJ37)/(1-1.5*AJ37)) -> 0.13834373 | AL37: ='[9]default rates'!$BM$114 -> 0.0060237118 | AM37: ='[2]Moody''s Global Infra and Corp D'!$T$66 -> 0.139 | AN37: =0.12*(1-EXP(-50*$AM37))/(1-EXP(-50))+0.24*(1-(1-EXP(-50*$AM37))/(1-EXP(-50))) -> 0.12011504 | AO37: =(0.11852-0.05478*LN($AM37))^2 -> 0.051354971 | AP37: =(AM$32*NORMSDIST((1-AN37)^(-0.5)*NORMSINV($AM37)+(AN37/(1-AN37))^(0.5)*NORMSINV(0.999))-$AM37*AM$32)*((1+($B37-2.5)*AO37)/(1-1.5*AO37)) -> 0.19102999 | AS37: ='[3]default rates'!$AV$146 -> 0.0060237118 | AT37: =AT36+AS37 -> 0.053208276 | AU37: =0.12*(1-EXP(-50*$AT37))/(1-EXP(-50))+0.24*(1-(1-EXP(-50*$AT37))/(1-EXP(-50))) -> 0.12839031 | AV37: =(0.11852-0.05478*LN($AT37))^2 -> 0.07796347 | AW37: =(AT$32*NORMSDIST((1-AU37)^(-0.5)*NORMSINV($AT37)+(AU37/(1-AU37))^(0.5)*NORMSINV(0.999))-$AT37*AT$32)*((1+($B37-2.5)*AV37)/(1-1.5*AV37)) -> 0.06670781 | AY37: ='[3]default rates'!$BK$333 -> 0.0051951715 | AZ37: =AZ36+AY37 -> 0.034233735 | BA37: =0.12*(1-EXP(-50*$AT37))/(1-EXP(-50))+0.24*(1-(1-EXP(-50*$AT37))/(1-EXP(-50))) -> 0.12839031 | BB37: =(0.11852-0.05478*LN($AT37))^2 -> 0.07796347 | BC37: =(AZ$32*NORMSDIST((1-BA37)^(-0.5)*NORMSINV($AZ37)+(BA37/(1-BA37))^(0.5)*NORMSINV(0.999))-$AZ37*AZ$32)*((1+($B37-2.5)*BB37)/(1-1.5*BB37)) -> 0.036059028 | BE37: ='[3]default rates'!$AV$146 -> 0.0060237118 | BF37: =BF36+BE37 -> 0.053208276 | BG37: =0.12*(1-EXP(-50*$AT37))/(1-EXP(-50))+0.24*(1-(1-EXP(-50*$AT37))/(1-EXP(-50))) -> 0.12839031 | BH37: =(0.11852-0.05478*LN($AT37))^2 -> 0.07796347 | BI37: =(BF$32*NORMSDIST((1-BG37)^(-0.5)*NORMSINV($BF37)+(BG37/(1-BG37))^(0.5)*NORMSINV(0.999))-$BF37*BF$32)*((1+($B37-2.5)*BH37)/(1-1.5*BH37)) -> 0.14629333 | BK37: ='[3]default rates'!$BK$333 -> 0.0051951715 | BL37: =BL36+BK37 -> 0.034233735 | BM37: =0.12*(1-EXP(-50*$AT37))/(1-EXP(-50))+0.24*(1-(1-EXP(-50*$AT37))/(1-EXP(-50))) -> 0.12839031 | BN37: =(0.11852-0.05478*LN($AT37))^2 -> 0.07796347 | BO37: =(BL$32*NORMSDIST((1-BM37)^(-0.5)*NORMSINV($BL37)+(BM37/(1-BM37))^(0.5)*NORMSINV(0.999))-$BL37*BL$32)*((1+($B37-2.5)*BN37)/(1-1.5*BN37)) -> 0.11433288
B38: =$B$14 -> 6 | D38: =Q38*100 -> 0.65245356 | E38: =V38*100 -> 0.65245356 | F38: =AA38*100 -> 5.9648652 | G38: =AF38*100 -> 10.052736 | H38: =AK38*100 -> 15.369614 | I38: =AP38*100 -> 20.532903 | K38: =AW38*100 -> 7.232137 | N38: ='[2]Moody''s Global Infra and Corp D'!$U$61 -> 1e-05 | O38: =0.12*(1-EXP(-50*$N38))/(1-EXP(-50))+0.24*(1-(1-EXP(-50*$N38))/(1-EXP(-50))) -> 0.23994001 | P38: =(0.11852-0.05478*LN($N38))^2 -> 0.56129773 | Q38: =(N$32*NORMSDIST((1-O38)^(-0.5)*NORMSINV($N38)+(O38/(1-O38))^(0.5)*NORMSINV(0.999))-$N38*N$32)*((1+($B38-2.5)*P38)/(1-1.5*P38)) -> 0.0065245356 | S38: ='[2]Moody''s Global Infra and Corp D'!$U$62 -> 1e-05 | T38: =0.12*(1-EXP(-50*$S38))/(1-EXP(-50))+0.24*(1-(1-EXP(-50*$S38))/(1-EXP(-50))) -> 0.23994001 | U38: =(0.11852-0.05478*LN($S38))^2 -> 0.56129773 | V38: =(S$32*NORMSDIST((1-T38)^(-0.5)*NORMSINV($S38)+(T38/(1-T38))^(0.5)*NORMSINV(0.999))-$S38*S$32)*((1+($B38-2.5)*U38)/(1-1.5*U38)) -> 0.0065245356 | W38: =MAX(X38-X37,0) -> 0 | X38: ='[2]Moody''s Global Infra and Corp D'!$U$63 -> 0.002 | Y38: =0.12*(1-EXP(-50*$X38))/(1-EXP(-50))+0.24*(1-(1-EXP(-50*$X38))/(1-EXP(-50))) -> 0.22858049 | Z38: =(0.11852-0.05478*LN($X38))^2 -> 0.21064082 | AA38: =(X$32*NORMSDIST((1-Y38)^(-0.5)*NORMSINV($X38)+(Y38/(1-Y38))^(0.5)*NORMSINV(0.999))-$X38*X$32)*((1+($B38-2.5)*Z38)/(1-1.5*Z38)) -> 0.059648652 | AB38: =MAX(AC38-AC37,0) -> 0.001 | AC38: ='[2]Moody''s Global Infra and Corp D'!$U$64 -> 0.008 | AD38: =0.12*(1-EXP(-50*$AC38))/(1-EXP(-50))+0.24*(1-(1-EXP(-50*$AC38))/(1-EXP(-50))) -> 0.20043841 | AE38: =(0.11852-0.05478*LN($AC38))^2 -> 0.14670051 | AF38: =(AC$32*NORMSDIST((1-AD38)^(-0.5)*NORMSINV($AC38)+(AD38/(1-AD38))^(0.5)*NORMSINV(0.999))-$AC38*AC$32)*((1+($B38-2.5)*AE38)/(1-1.5*AE38)) -> 0.10052736 | AG38: =MAX(AH38-AH37,0) -> 0.008 | AH38: ='[2]Moody''s Global Infra and Corp D'!$U$65 -> 0.055 | AI38: =0.12*(1-EXP(-50*$AH38))/(1-EXP(-50))+0.24*(1-(1-EXP(-50*$AH38))/(1-EXP(-50))) -> 0.12767134 | AJ38: =(0.11852-0.05478*LN($AH38))^2 -> 0.076953602 | AK38: =(AH$32*NORMSDIST((1-AI38)^(-0.5)*NORMSINV($AH38)+(AI38/(1-AI38))^(0.5)*NORMSINV(0.999))-$AH38*AH$32)*((1+($B38-2.5)*AJ38)/(1-1.5*AJ38)) -> 0.15369614 | AL38: ='[9]default rates'!$BN$114 -> 0.0036809899 | AM38: ='[2]Moody''s Global Infra and Corp D'!$U$66 -> 0.157 | AN38: =0.12*(1-EXP(-50*$AM38))/(1-EXP(-50))+0.24*(1-(1-EXP(-50*$AM38))/(1-EXP(-50))) -> 0.12004677 | AO38: =(0.11852-0.05478*LN($AM38))^2 -> 0.048376106 | AP38: =(AM$32*NORMSDIST((1-AN38)^(-0.5)*NORMSINV($AM38)+(AN38/(1-AN38))^(0.5)*NORMSINV(0.999))-$AM38*AM$32)*((1+($B38-2.5)*AO38)/(1-1.5*AO38)) -> 0.20532903 | AS38: ='[3]default rates'!$AW$146 -> 0.0036809899 | AT38: =AT37+AS38 -> 0.056889266 | AU38: =0.12*(1-EXP(-50*$AT38))/(1-EXP(-50))+0.24*(1-(1-EXP(-50*$AT38))/(1-EXP(-50))) -> 0.12697986 | AV38: =(0.11852-0.05478*LN($AT38))^2 -> 0.075930564 | AW38: =(AT$32*NORMSDIST((1-AU38)^(-0.5)*NORMSINV($AT38)+(AU38/(1-AU38))^(0.5)*NORMSINV(0.999))-$AT38*AT$32)*((1+($B38-2.5)*AV38)/(1-1.5*AV38)) -> 0.07232137 | AY38: ='[3]default rates'!$BL$333 -> 0.0035862798 | AZ38: =AZ37+AY38 -> 0.037820015 | BA38: =0.12*(1-EXP(-50*$AT38))/(1-EXP(-50))+0.24*(1-(1-EXP(-50*$AT38))/(1-EXP(-50))) -> 0.12697986 | BB38: =(0.11852-0.05478*LN($AT38))^2 -> 0.075930564 | BC38: =(AZ$32*NORMSDIST((1-BA38)^(-0.5)*NORMSINV($AZ38)+(BA38/(1-BA38))^(0.5)*NORMSINV(0.999))-$AZ38*AZ$32)*((1+($B38-2.5)*BB38)/(1-1.5*BB38)) -> 0.039952499 | BE38: ='[3]default rates'!$AW$146 -> 0.0036809899 | BF38: =BF37+BE38 -> 0.056889266 | BG38: =0.12*(1-EXP(-50*$AT38))/(1-EXP(-50))+0.24*(1-(1-EXP(-50*$AT38))/(1-EXP(-50))) -> 0.12697986 | BH38: =(0.11852-0.05478*LN($AT38))^2 -> 0.075930564 | BI38: =(BF$32*NORMSDIST((1-BG38)^(-0.5)*NORMSINV($BF38)+(BG38/(1-BG38))^(0.5)*NORMSINV(0.999))-$BF38*BF$32)*((1+($B38-2.5)*BH38)/(1-1.5*BH38)) -> 0.15860412 | BK38: ='[3]default rates'!$BL$333 -> 0.0035862798 | BL38: =BL37+BK38 -> 0.037820015 | BM38: =0.12*(1-EXP(-50*$AT38))/(1-EXP(-50))+0.24*(1-(1-EXP(-50*$AT38))/(1-EXP(-50))) -> 0.12697986 | BN38: =(0.11852-0.05478*LN($AT38))^2 -> 0.075930564 | BO38: =(BL$32*NORMSDIST((1-BM38)^(-0.5)*NORMSINV($BL38)+(BM38/(1-BM38))^(0.5)*NORMSINV(0.999))-$BL38*BL$32)*((1+($B38-2.5)*BN38)/(1-1.5*BN38)) -> 0.12667797
B39: =$B$15 -> 7 | D39: =Q39*100 -> 0.77598721 | E39: =V39*100 -> 0.77598721 | F39: =AA39*100 -> 7.9049736 | G39: =AF39*100 -> 11.688908 | H39: =AK39*100 -> 16.661552 | I39: =AP39*100 -> 21.802925 | K39: =AW39*100 -> 7.7410386 | N39: ='[2]Moody''s Global Infra and Corp D'!$V$61 -> 1e-05 | O39: =0.12*(1-EXP(-50*$N39))/(1-EXP(-50))+0.24*(1-(1-EXP(-50*$N39))/(1-EXP(-50))) -> 0.23994001 | P39: =(0.11852-0.05478*LN($N39))^2 -> 0.56129773 | Q39: =(N$32*NORMSDIST((1-O39)^(-0.5)*NORMSINV($N39)+(O39/(1-O39))^(0.5)*NORMSINV(0.999))-$N39*N$32)*((1+($B39-2.5)*P39)/(1-1.5*P39)) -> 0.0077598721 | S39: ='[2]Moody''s Global Infra and Corp D'!$V$62 -> 1e-05 | T39: =0.12*(1-EXP(-50*$S39))/(1-EXP(-50))+0.24*(1-(1-EXP(-50*$S39))/(1-EXP(-50))) -> 0.23994001 | U39: =(0.11852-0.05478*LN($S39))^2 -> 0.56129773 | V39: =(S$32*NORMSDIST((1-T39)^(-0.5)*NORMSINV($S39)+(T39/(1-T39))^(0.5)*NORMSINV(0.999))-$S39*S$32)*((1+($B39-2.5)*U39)/(1-1.5*U39)) -> 0.0077598721 | W39: =MAX(X39-X38,0) -> 0.001 | X39: ='[2]Moody''s Global Infra and Corp D'!$V$63 -> 0.003 | Y39: =0.12*(1-EXP(-50*$X39))/(1-EXP(-50))+0.24*(1-(1-EXP(-50*$X39))/(1-EXP(-50))) -> 0.22328496 | Z39: =(0.11852-0.05478*LN($X39))^2 -> 0.19074607 | AA39: =(X$32*NORMSDIST((1-Y39)^(-0.5)*NORMSINV($X39)+(Y39/(1-Y39))^(0.5)*NORMSINV(0.999))-$X39*X$32)*((1+($B39-2.5)*Z39)/(1-1.5*Z39)) -> 0.079049736 | AB39: =MAX(AC39-AC38,0) -> 0.002 | AC39: ='[2]Moody''s Global Infra and Corp D'!$V$64 -> 0.01 | AD39: =0.12*(1-EXP(-50*$AC39))/(1-EXP(-50))+0.24*(1-(1-EXP(-50*$AC39))/(1-EXP(-50))) -> 0.19278368 | AE39: =(0.11852-0.05478*LN($AC39))^2 -> 0.13748613 | AF39: =(AC$32*NORMSDIST((1-AD39)^(-0.5)*NORMSINV($AC39)+(AD39/(1-AD39))^(0.5)*NORMSINV(0.999))-$AC39*AC$32)*((1+($B39-2.5)*AE39)/(1-1.5*AE39)) -> 0.11688908 | AG39: =MAX(AH39-AH38,0) -> 0.005 | AH39: ='[2]Moody''s Global Infra and Corp D'!$V$65 -> 0.06 | AI39: =0.12*(1-EXP(-50*$AH39))/(1-EXP(-50))+0.24*(1-(1-EXP(-50*$AH39))/(1-EXP(-50))) -> 0.12597445 | AJ39: =(0.11852-0.05478*LN($AH39))^2 -> 0.074331828 | AK39: =(AH$32*NORMSDIST((1-AI39)^(-0.5)*NORMSINV($AH39)+(AI39/(1-AI39))^(0.5)*NORMSINV(0.999))-$AH39*AH$32)*((1+($B39-2.5)*AJ39)/(1-1.5*AJ39)) -> 0.16661552 | AL39: ='[9]default rates'!$BO$114 -> 0.0022383359 | AM39: ='[2]Moody''s Global Infra and Corp D'!$V$66 -> 0.175 | AN39: =0.12*(1-EXP(-50*$AM39))/(1-EXP(-50))+0.24*(1-(1-EXP(-50*$AM39))/(1-EXP(-50))) -> 0.12001902 | AO39: =(0.11852-0.05478*LN($AM39))^2 -> 0.045795939 | AP39: =(AM$32*NORMSDIST((1-AN39)^(-0.5)*NORMSINV($AM39)+(AN39/(1-AN39))^(0.5)*NORMSINV(0.999))-$AM39*AM$32)*((1+($B39-2.5)*AO39)/(1-1.5*AO39)) -> 0.21802925 | AS39: ='[3]default rates'!$AX$146 -> 0.0022383359 | AT39: =AT38+AS39 -> 0.059127602 | AU39: =0.12*(1-EXP(-50*$AT39))/(1-EXP(-50))+0.24*(1-(1-EXP(-50*$AT39))/(1-EXP(-50))) -> 0.12624082 | AV39: =(0.11852-0.05478*LN($AT39))^2 -> 0.074769973 | AW39: =(AT$32*NORMSDIST((1-AU39)^(-0.5)*NORMSINV($AT39)+(AU39/(1-AU39))^(0.5)*NORMSINV(0.999))-$AT39*AT$32)*((1+($B39-2.5)*AV39)/(1-1.5*AV39)) -> 0.077410386 | AY39: ='[3]default rates'!$BM$333 -> 0.0028924124 | AZ39: =AZ38+AY39 -> 0.040712427 | BA39: =0.12*(1-EXP(-50*$AT39))/(1-EXP(-50))+0.24*(1-(1-EXP(-50*$AT39))/(1-EXP(-50))) -> 0.12624082 | BB39: =(0.11852-0.05478*LN($AT39))^2 -> 0.074769973 | BC39: =(AZ$32*NORMSDIST((1-BA39)^(-0.5)*NORMSINV($AZ39)+(BA39/(1-BA39))^(0.5)*NORMSINV(0.999))-$AZ39*AZ$32)*((1+($B39-2.5)*BB39)/(1-1.5*BB39)) -> 0.043697951 | BE39: ='[3]default rates'!$AX$146 -> 0.0022383359 | BF39: =BF38+BE39 -> 0.059127602 | BG39: =0.12*(1-EXP(-50*$AT39))/(1-EXP(-50))+0.24*(1-(1-EXP(-50*$AT39))/(1-EXP(-50))) -> 0.12624082 | BH39: =(0.11852-0.05478*LN($AT39))^2 -> 0.074769973 | BI39: =(BF$32*NORMSDIST((1-BG39)^(-0.5)*NORMSINV($BF39)+(BG39/(1-BG39))^(0.5)*NORMSINV(0.999))-$BF39*BF$32)*((1+($B39-2.5)*BH39)/(1-1.5*BH39)) -> 0.16976457 | BK39: ='[3]default rates'!$BM$333 -> 0.0028924124 | BL39: =BL38+BK39 -> 0.040712427 | BM39: =0.12*(1-EXP(-50*$AT39))/(1-EXP(-50))+0.24*(1-(1-EXP(-50*$AT39))/(1-EXP(-50))) -> 0.12624082 | BN39: =(0.11852-0.05478*LN($AT39))^2 -> 0.074769973 | BO39: =(BL$32*NORMSDIST((1-BM39)^(-0.5)*NORMSINV($BL39)+(BM39/(1-BM39))^(0.5)*NORMSINV(0.999))-$BL39*BL$32)*((1+($B39-2.5)*BN39)/(1-1.5*BN39)) -> 0.13855373
B40: =$B$16 -> 8 | D40: =Q40*100 -> 0.89952086 | E40: =V40*100 -> 0.89952086 | F40: =AA40*100 -> 8.7163582 | G40: =AF40*100 -> 12.956507 | H40: =AK40*100 -> 17.800262 | I40: =AP40*100 -> 22.882258 | K40: =AW40*100 -> 8.2242374 | N40: ='[2]Moody''s Global Infra and Corp D'!$W$61 -> 1e-05 | O40: =0.12*(1-EXP(-50*$N40))/(1-EXP(-50))+0.24*(1-(1-EXP(-50*$N40))/(1-EXP(-50))) -> 0.23994001 | P40: =(0.11852-0.05478*LN($N40))^2 -> 0.56129773 | Q40: =(N$32*NORMSDIST((1-O40)^(-0.5)*NORMSINV($N40)+(O40/(1-O40))^(0.5)*NORMSINV(0.999))-$N40*N$32)*((1+($B40-2.5)*P40)/(1-1.5*P40)) -> 0.0089952086 | S40: ='[2]Moody''s Global Infra and Corp D'!$W$62 -> 1e-05 | T40: =0.12*(1-EXP(-50*$S40))/(1-EXP(-50))+0.24*(1-(1-EXP(-50*$S40))/(1-EXP(-50))) -> 0.23994001 | U40: =(0.11852-0.05478*LN($S40))^2 -> 0.56129773 | V40: =(S$32*NORMSDIST((1-T40)^(-0.5)*NORMSINV($S40)+(T40/(1-T40))^(0.5)*NORMSINV(0.999))-$S40*S$32)*((1+($B40-2.5)*U40)/(1-1.5*U40)) -> 0.0089952086 | W40: =MAX(X40-X39,0) -> 0 | X40: ='[2]Moody''s Global Infra and Corp D'!$W$63 -> 0.003 | Y40: =0.12*(1-EXP(-50*$X40))/(1-EXP(-50))+0.24*(1-(1-EXP(-50*$X40))/(1-EXP(-50))) -> 0.22328496 | Z40: =(0.11852-0.05478*LN($X40))^2 -> 0.19074607 | AA40: =(X$32*NORMSDIST((1-Y40)^(-0.5)*NORMSINV($X40)+(Y40/(1-Y40))^(0.5)*NORMSINV(0.999))-$X40*X$32)*((1+($B40-2.5)*Z40)/(1-1.5*Z40)) -> 0.087163582 | AB40: =MAX(AC40-AC39,0) -> 0.001 | AC40: ='[2]Moody''s Global Infra and Corp D'!$W$64 -> 0.011 | AD40: =0.12*(1-EXP(-50*$AC40))/(1-EXP(-50))+0.24*(1-(1-EXP(-50*$AC40))/(1-EXP(-50))) -> 0.18923398 | AE40: =(0.11852-0.05478*LN($AC40))^2 -> 0.13364152 | AF40: =(AC$32*NORMSDIST((1-AD40)^(-0.5)*NORMSINV($AC40)+(AD40/(1-AD40))^(0.5)*NORMSINV(0.999))-$AC40*AC$32)*((1+($B40-2.5)*AE40)/(1-1.5*AE40)) -> 0.12956507 | AG40: =MAX(AH40-AH39,0) -> 0.003 | AH40: ='[2]Moody''s Global Infra and Corp D'!$W$65 -> 0.063 | AI40: =0.12*(1-EXP(-50*$AH40))/(1-EXP(-50))+0.24*(1-(1-EXP(-50*$AH40))/(1-EXP(-50))) -> 0.12514226 | AJ40: =(0.11852-0.05478*LN($AH40))^2 -> 0.072881595 | AK40: =(AH$32*NORMSDIST((1-AI40)^(-0.5)*NORMSINV($AH40)+(AI40/(1-AI40))^(0.5)*NORMSINV(0.999))-$AH40*AH$32)*((1+($B40-2.5)*AJ40)/(1-1.5*AJ40)) -> 0.17800262 | AL40: ='[9]default rates'!$BP$114 -> 0.0015203642 | AM40: ='[2]Moody''s Global Infra and Corp D'!$W$66 -> 0.19 | AN40: =0.12*(1-EXP(-50*$AM40))/(1-EXP(-50))+0.24*(1-(1-EXP(-50*$AM40))/(1-EXP(-50))) -> 0.12000898 | AO40: =(0.11852-0.05478*LN($AM40))^2 -> 0.043888094 | AP40: =(AM$32*NORMSDIST((1-AN40)^(-0.5)*NORMSINV($AM40)+(AN40/(1-AN40))^(0.5)*NORMSINV(0.999))-$AM40*AM$32)*((1+($B40-2.5)*AO40)/(1-1.5*AO40)) -> 0.22882258 | AS40: ='[3]default rates'!$AY$146 -> 0.0015203642 | AT40: =AT39+AS40 -> 0.060647966 | AU40: =0.12*(1-EXP(-50*$AT40))/(1-EXP(-50))+0.24*(1-(1-EXP(-50*$AT40))/(1-EXP(-50))) -> 0.12578399 | AV40: =(0.11852-0.05478*LN($AT40))^2 -> 0.074011321 | AW40: =(AT$32*NORMSDIST((1-AU40)^(-0.5)*NORMSINV($AT40)+(AU40/(1-AU40))^(0.5)*NORMSINV(0.999))-$AT40*AT$32)*((1+($B40-2.5)*AV40)/(1-1.5*AV40)) -> 0.082242374 | AY40: ='[3]default rates'!$BN$333 -> 0.0022948817 | AZ40: =AZ39+AY40 -> 0.043007309 | BA40: =0.12*(1-EXP(-50*$AT40))/(1-EXP(-50))+0.24*(1-(1-EXP(-50*$AT40))/(1-EXP(-50))) -> 0.12578399 | BB40: =(0.11852-0.05478*LN($AT40))^2 -> 0.074011321 | BC40: =(AZ$32*NORMSDIST((1-BA40)^(-0.5)*NORMSINV($AZ40)+(BA40/(1-BA40))^(0.5)*NORMSINV(0.999))-$AZ40*AZ$32)*((1+($B40-2.5)*BB40)/(1-1.5*BB40)) -> 0.04725006 | BE40: ='[3]default rates'!$AY$146 -> 0.0015203642 | BF40: =BF39+BE40 -> 0.060647966 | BG40: =0.12*(1-EXP(-50*$AT40))/(1-EXP(-50))+0.24*(1-(1-EXP(-50*$AT40))/(1-EXP(-50))) -> 0.12578399 | BH40: =(0.11852-0.05478*LN($AT40))^2 -> 0.074011321 | BI40: =(BF$32*NORMSDIST((1-BG40)^(-0.5)*NORMSINV($BF40)+(BG40/(1-BG40))^(0.5)*NORMSINV(0.999))-$BF40*BF$32)*((1+($B40-2.5)*BH40)/(1-1.5*BH40)) -> 0.18036135 | BK40: ='[3]default rates'!$BN$333 -> 0.0022948817 | BL40: =BL39+BK40 -> 0.043007309 | BM40: =0.12*(1-EXP(-50*$AT40))/(1-EXP(-50))+0.24*(1-(1-EXP(-50*$AT40))/(1-EXP(-50))) -> 0.12578399 | BN40: =(0.11852-0.05478*LN($AT40))^2 -> 0.074011321 | BO40: =(BL$32*NORMSDIST((1-BM40)^(-0.5)*NORMSINV($BL40)+(BM40/(1-BM40))^(0.5)*NORMSINV(0.999))-$BL40*BL$32)*((1+($B40-2.5)*BN40)/(1-1.5*BN40)) -> 0.14981645
B41: =$B$17 -> 9 | D41: =Q41*100 -> 1.0230545 | E41: =V41*100 -> 1.0230545 | F41: =AA41*100 -> 9.5277429 | G41: =AF41*100 -> 14.416441 | H41: =AK41*100 -> 19.000243 | I41: =AP41*100 -> 23.867248 | K41: =AW41*100 -> 8.6851847 | N41: ='[2]Moody''s Global Infra and Corp D'!$X$61 -> 1e-05 | O41: =0.12*(1-EXP(-50*$N41))/(1-EXP(-50))+0.24*(1-(1-EXP(-50*$N41))/(1-EXP(-50))) -> 0.23994001 | P41: =(0.11852-0.05478*LN($N41))^2 -> 0.56129773 | Q41: =(N$32*NORMSDIST((1-O41)^(-0.5)*NORMSINV($N41)+(O41/(1-O41))^(0.5)*NORMSINV(0.999))-$N41*N$32)*((1+($B41-2.5)*P41)/(1-1.5*P41)) -> 0.010230545 | S41: ='[2]Moody''s Global Infra and Corp D'!$X$62 -> 1e-05 | T41: =0.12*(1-EXP(-50*$S41))/(1-EXP(-50))+0.24*(1-(1-EXP(-50*$S41))/(1-EXP(-50))) -> 0.23994001 | U41: =(0.11852-0.05478*LN($S41))^2 -> 0.56129773 | V41: =(S$32*NORMSDIST((1-T41)^(-0.5)*NORMSINV($S41)+(T41/(1-T41))^(0.5)*NORMSINV(0.999))-$S41*S$32)*((1+($B41-2.5)*U41)/(1-1.5*U41)) -> 0.010230545 | W41: =MAX(X41-X40,0) -> 0 | X41: ='[2]Moody''s Global Infra and Corp D'!$X$63 -> 0.003 | Y41: =0.12*(1-EXP(-50*$X41))/(1-EXP(-50))+0.24*(1-(1-EXP(-50*$X41))/(1-EXP(-50))) -> 0.22328496 | Z41: =(0.11852-0.05478*LN($X41))^2 -> 0.19074607 | AA41: =(X$32*NORMSDIST((1-Y41)^(-0.5)*NORMSINV($X41)+(Y41/(1-Y41))^(0.5)*NORMSINV(0.999))-$X41*X$32)*((1+($B41-2.5)*Z41)/(1-1.5*Z41)) -> 0.095277429 | AB41: =MAX(AC41-AC40,0) -> 0.002 | AC41: ='[2]Moody''s Global Infra and Corp D'!$X$64 -> 0.013 | AD41: =0.12*(1-EXP(-50*$AC41))/(1-EXP(-50))+0.24*(1-(1-EXP(-50*$AC41))/(1-EXP(-50))) -> 0.18264549 | AE41: =(0.11852-0.05478*LN($AC41))^2 -> 0.12703444 | AF41: =(AC$32*NORMSDIST((1-AD41)^(-0.5)*NORMSINV($AC41)+(AD41/(1-AD41))^(0.5)*NORMSINV(0.999))-$AC41*AC$32)*((1+($B41-2.5)*AE41)/(1-1.5*AE41)) -> 0.14416441 | AG41: =MAX(AH41-AH40,0) -> 0.004 | AH41: ='[2]Moody''s Global Infra and Corp D'!$X$65 -> 0.067 | AI41: =0.12*(1-EXP(-50*$AH41))/(1-EXP(-50))+0.24*(1-(1-EXP(-50*$AH41))/(1-EXP(-50))) -> 0.12421012 | AJ41: =(0.11852-0.05478*LN($AH41))^2 -> 0.07107224 | AK41: =(AH$32*NORMSDIST((1-AI41)^(-0.5)*NORMSINV($AH41)+(AI41/(1-AI41))^(0.5)*NORMSINV(0.999))-$AH41*AH$32)*((1+($B41-2.5)*AJ41)/(1-1.5*AJ41)) -> 0.19000243 | AL41: ='[9]default rates'!$BQ$114 -> 0.00087248509 | AM41: ='[2]Moody''s Global Infra and Corp D'!$X$66 -> 0.206 | AN41: =0.12*(1-EXP(-50*$AM41))/(1-EXP(-50))+0.24*(1-(1-EXP(-50*$AM41))/(1-EXP(-50))) -> 0.12000404 | AO41: =(0.11852-0.05478*LN($AM41))^2 -> 0.042051973 | AP41: =(AM$32*NORMSDIST((1-AN41)^(-0.5)*NORMSINV($AM41)+(AN41/(1-AN41))^(0.5)*NORMSINV(0.999))-$AM41*AM$32)*((1+($B41-2.5)*AO41)/(1-1.5*AO41)) -> 0.23867248 | AS41: ='[3]default rates'!$AZ$146 -> 0.00087248509 | AT41: =AT40+AS41 -> 0.061520451 | AU41: =0.12*(1-EXP(-50*$AT41))/(1-EXP(-50))+0.24*(1-(1-EXP(-50*$AT41))/(1-EXP(-50))) -> 0.12553709 | AV41: =(0.11852-0.05478*LN($AT41))^2 -> 0.0735862 | AW41: =(AT$32*NORMSDIST((1-AU41)^(-0.5)*NORMSINV($AT41)+(AU41/(1-AU41))^(0.5)*NORMSINV(0.999))-$AT41*AT$32)*((1+($B41-2.5)*AV41)/(1-1.5*AV41)) -> 0.086851847 | AY41: ='[3]default rates'!$BO$333 -> 0.0014169671 | AZ41: =AZ40+AY41 -> 0.044424276 | BA41: =0.12*(1-EXP(-50*$AT41))/(1-EXP(-50))+0.24*(1-(1-EXP(-50*$AT41))/(1-EXP(-50))) -> 0.12553709 | BB41: =(0.11852-0.05478*LN($AT41))^2 -> 0.0735862 | BC41: =(AZ$32*NORMSDIST((1-BA41)^(-0.5)*NORMSINV($AZ41)+(BA41/(1-BA41))^(0.5)*NORMSINV(0.999))-$AZ41*AZ$32)*((1+($B41-2.5)*BB41)/(1-1.5*BB41)) -> 0.050433997 | BE41: ='[3]default rates'!$AZ$146 -> 0.00087248509 | BF41: =BF40+BE41 -> 0.061520451 | BG41: =0.12*(1-EXP(-50*$AT41))/(1-EXP(-50))+0.24*(1-(1-EXP(-50*$AT41))/(1-EXP(-50))) -> 0.12553709 | BH41: =(0.11852-0.05478*LN($AT41))^2 -> 0.0735862 | BI41: =(BF$32*NORMSDIST((1-BG41)^(-0.5)*NORMSINV($BF41)+(BG41/(1-BG41))^(0.5)*NORMSINV(0.999))-$BF41*BF$32)*((1+($B41-2.5)*BH41)/(1-1.5*BH41)) -> 0.19047014 | BK41: ='[3]default rates'!$BO$333 -> 0.0014169671 | BL41: =BL40+BK41 -> 0.044424276 | BM41: =0.12*(1-EXP(-50*$AT41))/(1-EXP(-50))+0.24*(1-(1-EXP(-50*$AT41))/(1-EXP(-50))) -> 0.12553709 | BN41: =(0.11852-0.05478*LN($AT41))^2 -> 0.0735862 | BO41: =(BL$32*NORMSDIST((1-BM41)^(-0.5)*NORMSINV($BL41)+(BM41/(1-BM41))^(0.5)*NORMSINV(0.999))-$BL41*BL$32)*((1+($B41-2.5)*BN41)/(1-1.5*BN41)) -> 0.15991181
B42: =$B$18 -> 10 | D42: =Q42*100 -> 1.1465882 | E42: =V42*100 -> 1.1465882 | F42: =AA42*100 -> 11.426947 | G42: =AF42*100 -> 15.613439 | H42: =AK42*100 -> 20.255119 | I42: =AP42*100 -> 24.740449 | K42: =AW42*100 -> 9.134146 | N42: ='[2]Moody''s Global Infra and Corp D'!$Y$61 -> 1e-05 | O42: =0.12*(1-EXP(-50*$N42))/(1-EXP(-50))+0.24*(1-(1-EXP(-50*$N42))/(1-EXP(-50))) -> 0.23994001 | P42: =(0.11852-0.05478*LN($N42))^2 -> 0.56129773 | Q42: =(N$32*NORMSDIST((1-O42)^(-0.5)*NORMSINV($N42)+(O42/(1-O42))^(0.5)*NORMSINV(0.999))-$N42*N$32)*((1+($B42-2.5)*P42)/(1-1.5*P42)) -> 0.011465882 | S42: ='[2]Moody''s Global Infra and Corp D'!$Y$62 -> 1e-05 | T42: =0.12*(1-EXP(-50*$S42))/(1-EXP(-50))+0.24*(1-(1-EXP(-50*$S42))/(1-EXP(-50))) -> 0.23994001 | U42: =(0.11852-0.05478*LN($S42))^2 -> 0.56129773 | V42: =(S$32*NORMSDIST((1-T42)^(-0.5)*NORMSINV($S42)+(T42/(1-T42))^(0.5)*NORMSINV(0.999))-$S42*S$32)*((1+($B42-2.5)*U42)/(1-1.5*U42)) -> 0.011465882 | W42: =MAX(X42-X41,0) -> 0.001 | X42: ='[2]Moody''s Global Infra and Corp D'!$Y$63 -> 0.004 | Y42: =0.12*(1-EXP(-50*$X42))/(1-EXP(-50))+0.24*(1-(1-EXP(-50*$X42))/(1-EXP(-50))) -> 0.21824769 | Z42: =(0.11852-0.05478*LN($X42))^2 -> 0.1772289 | AA42: =(X$32*NORMSDIST((1-Y42)^(-0.5)*NORMSINV($X42)+(Y42/(1-Y42))^(0.5)*NORMSINV(0.999))-$X42*X$32)*((1+($B42-2.5)*Z42)/(1-1.5*Z42)) -> 0.11426947 | AB42: =MAX(AC42-AC41,0) -> 0.001 | AC42: ='[2]Moody''s Global Infra and Corp D'!$Y$64 -> 0.014 | AD42: =0.12*(1-EXP(-50*$AC42))/(1-EXP(-50))+0.24*(1-(1-EXP(-50*$AC42))/(1-EXP(-50))) -> 0.17959024 | AE42: =(0.11852-0.05478*LN($AC42))^2 -> 0.12415706 | AF42: =(AC$32*NORMSDIST((1-AD42)^(-0.5)*NORMSINV($AC42)+(AD42/(1-AD42))^(0.5)*NORMSINV(0.999))-$AC42*AC$32)*((1+($B42-2.5)*AE42)/(1-1.5*AE42)) -> 0.15613439 | AG42: =MAX(AH42-AH41,0) -> 0.005 | AH42: ='[2]Moody''s Global Infra and Corp D'!$Y$65 -> 0.072 | AI42: =0.12*(1-EXP(-50*$AH42))/(1-EXP(-50))+0.24*(1-(1-EXP(-50*$AH42))/(1-EXP(-50))) -> 0.12327885 | AJ42: =(0.11852-0.05478*LN($AH42))^2 -> 0.068985582 | AK42: =(AH$32*NORMSDIST((1-AI42)^(-0.5)*NORMSINV($AH42)+(AI42/(1-AI42))^(0.5)*NORMSINV(0.999))-$AH42*AH$32)*((1+($B42-2.5)*AJ42)/(1-1.5*AJ42)) -> 0.20255119 | AL42: ='[9]default rates'!$BR$114 -> 0.00051822378 | AM42: ='[2]Moody''s Global Infra and Corp D'!$Y$66 -> 0.221 | AN42: =0.12*(1-EXP(-50*$AM42))/(1-EXP(-50))+0.24*(1-(1-EXP(-50*$AM42))/(1-EXP(-50))) -> 0.12000191 | AO42: =(0.11852-0.05478*LN($AM42))^2 -> 0.04048767 | AP42: =(AM$32*NORMSDIST((1-AN42)^(-0.5)*NORMSINV($AM42)+(AN42/(1-AN42))^(0.5)*NORMSINV(0.999))-$AM42*AM$32)*((1+($B42-2.5)*AO42)/(1-1.5*AO42)) -> 0.24740449 | AS42: ='[3]default rates'!$BA$146 -> 0.00051822378 | AT42: =AT41+AS42 -> 0.062038675 | AU42: =0.12*(1-EXP(-50*$AT42))/(1-EXP(-50))+0.24*(1-(1-EXP(-50*$AT42))/(1-EXP(-50))) -> 0.12539546 | AV42: =(0.11852-0.05478*LN($AT42))^2 -> 0.073337109 | AW42: =(AT$32*NORMSDIST((1-AU42)^(-0.5)*NORMSINV($AT42)+(AU42/(1-AU42))^(0.5)*NORMSINV(0.999))-$AT42*AT$32)*((1+($B42-2.5)*AV42)/(1-1.5*AV42)) -> 0.09134146 | AY42: ='[3]default rates'!$BP$333 -> 0.00090846933 | AZ42: =AZ41+AY42 -> 0.045332745 | BA42: =0.12*(1-EXP(-50*$AT42))/(1-EXP(-50))+0.24*(1-(1-EXP(-50*$AT42))/(1-EXP(-50))) -> 0.12539546 | BB42: =(0.11852-0.05478*LN($AT42))^2 -> 0.073337109 | BC42: =(AZ$32*NORMSDIST((1-BA42)^(-0.5)*NORMSINV($AZ42)+(BA42/(1-BA42))^(0.5)*NORMSINV(0.999))-$AZ42*AZ$32)*((1+($B42-2.5)*BB42)/(1-1.5*BB42)) -> 0.053408453 | BE42: ='[3]default rates'!$BA$146 -> 0.00051822378 | BF42: =BF41+BE42 -> 0.062038675 | BG42: =0.12*(1-EXP(-50*$AT42))/(1-EXP(-50))+0.24*(1-(1-EXP(-50*$AT42))/(1-EXP(-50))) -> 0.12539546 | BH42: =(0.11852-0.05478*LN($AT42))^2 -> 0.073337109 | BI42: =(BF$32*NORMSDIST((1-BG42)^(-0.5)*NORMSINV($BF42)+(BG42/(1-BG42))^(0.5)*NORMSINV(0.999))-$BF42*BF$32)*((1+($B42-2.5)*BH42)/(1-1.5*BH42)) -> 0.20031607 | BK42: ='[3]default rates'!$BP$333 -> 0.00090846933 | BL42: =BL41+BK42 -> 0.045332745 | BM42: =0.12*(1-EXP(-50*$AT42))/(1-EXP(-50))+0.24*(1-(1-EXP(-50*$AT42))/(1-EXP(-50))) -> 0.12539546 | BN42: =(0.11852-0.05478*LN($AT42))^2 -> 0.073337109 | BO42: =(BL$32*NORMSDIST((1-BM42)^(-0.5)*NORMSINV($BL42)+(BM42/(1-BM42))^(0.5)*NORMSINV(0.999))-$BL42*BL$32)*((1+($B42-2.5)*BN42)/(1-1.5*BN42)) -> 0.16934296
D44: Proposed: Infrastructure Investment in EEA or OECD* [broad] | N44: =N$32/AT$32*AT44 -> 0.4280047 | S44: =N44 -> 0.4280047 | X44: =N44 -> 0.4280047 | AC44: =X44 -> 0.4280047 | AH44: =X44 -> 0.4280047 | AM44: =AC44 -> 0.4280047 | AS44: Marginal PD ↓/Recovery → | AT44: =1-'[2]default rates (3)'!CR16/100 -> 0.1996 | AU44: stdev(rec.) | AV44: ='[2]default rates (3)'!CS16 -> 0.33250524 | AW44: =AV44*(AT44/(1-AT44)) -> 0.082918598 | AY44: Marginal PD ↓/Recovery → | AZ44: =1-'[3]default rates'!$CR$68/100 -> 0.15375083 | BA44: stdev(rec.) | BB44: ='[3]default rates'!$CS$68 -> 0.30009487 | BC44: =BB44*(AZ44/(1-AZ44)) -> 0.054522756 | BE44: Marginal PD ↓/Recovery → | BF44: =BF32 -> 0.45 | BG44: stdev(rec.) | BH44: =BF44/AT44*AV44 -> 0.74963606 | BI44: =BH44*(BF44/(1-BF44)) -> 0.6133386 | BK44: Marginal PD ↓/Recovery → | BL44: =BF44 -> 0.45 | BM44: stdev(rec.) | BN44: ='[3]default rates'!$CS$68 -> 0.30009487 | BO44: =BN44*(BL44/(1-BL44)) -> 0.24553217
B45: =$B$9 -> 1 | D45: =Q45*100 -> 0.032967089 | E45: =V45*100 -> 0.032967089 | F45: =AA45*100 -> 0.032967089 | G45: =AF45*100 -> 1.3907759 | H45: =AK45*100 -> 3.443997 | I45: =AP45*100 -> 7.7835965 | K45: =AW45*100 -> 2.8987499 | N45: ='[2]Moody''s Global Infra and Corp D'!$P$68 -> 9.7071977e-06 | O45: =0.12*(1-EXP(-50*$N45))/(1-EXP(-50))+0.24*(1-(1-EXP(-50*$N45))/(1-EXP(-50))) -> 0.23994177 | P45: =(0.11852-0.05478*LN($N45))^2 -> 0.56373965 | Q45: =(N$44*NORMSDIST((1-O45)^(-0.5)*NORMSINV($N45)+(O45/(1-O45))^(0.5)*NORMSINV(0.999))-$N45*N$44)*((1+($B45-2.5)*P45)/(1-1.5*P45)) -> 0.00032967089 | S45: ='[2]Moody''s Global Infra and Corp D'!$P$69 -> 9.7071977e-06 | T45: =0.12*(1-EXP(-50*$S45))/(1-EXP(-50))+0.24*(1-(1-EXP(-50*$S45))/(1-EXP(-50))) -> 0.23994177 | U45: =(0.11852-0.05478*LN($S45))^2 -> 0.56373965 | V45: =(S$44*NORMSDIST((1-T45)^(-0.5)*NORMSINV($S45)+(T45/(1-T45))^(0.5)*NORMSINV(0.999))-$S45*S$44)*((1+($B45-2.5)*U45)/(1-1.5*U45)) -> 0.00032967089 | X45: ='[2]Moody''s Global Infra and Corp D'!$P$70 -> 9.7071977e-06 | Y45: =0.12*(1-EXP(-50*$X45))/(1-EXP(-50))+0.24*(1-(1-EXP(-50*$X45))/(1-EXP(-50))) -> 0.23994177 | Z45: =(0.11852-0.05478*LN($X45))^2 -> 0.56373965 | AA45: =(X$44*NORMSDIST((1-Y45)^(-0.5)*NORMSINV($X45)+(Y45/(1-Y45))^(0.5)*NORMSINV(0.999))-$X45*X$44)*((1+($B45-2.5)*Z45)/(1-1.5*Z45)) -> 0.00032967089 | AC45: ='[2]Moody''s Global Infra and Corp D'!$P$71 -> 0.00097071977 | AD45: =0.12*(1-EXP(-50*$AC45))/(1-EXP(-50))+0.24*(1-(1-EXP(-50*$AC45))/(1-EXP(-50))) -> 0.23431477 | AE45: =(0.11852-0.05478*LN($AC45))^2 -> 0.24855685 | AF45: =(AC$44*NORMSDIST((1-AD45)^(-0.5)*NORMSINV($AC45)+(AD45/(1-AD45))^(0.5)*NORMSINV(0.999))-$AC45*AC$44)*((1+($B45-2.5)*AE45)/(1-1.5*AE45)) -> 0.013907759 | AH45: ='[2]Moody''s Global Infra and Corp D'!$P$72 -> 0.0038828791 | AI45: =0.12*(1-EXP(-50*$AH45))/(1-EXP(-50))+0.24*(1-(1-EXP(-50*$AH45))/(1-EXP(-50))) -> 0.21882472 | AJ45: =(0.11852-0.05478*LN($AH45))^2 -> 0.17860221 | AK45: =(AH$44*NORMSDIST((1-AI45)^(-0.5)*NORMSINV($AH45)+(AI45/(1-AI45))^(0.5)*NORMSINV(0.999))-$AH45*AH$44)*((1+($B45-2.5)*AJ45)/(1-1.5*AJ45)) -> 0.03443997 | AM45: ='[2]Moody''s Global Infra and Corp D'!$P$73 -> 0.024267994 | AN45: =0.12*(1-EXP(-50*$AM45))/(1-EXP(-50))+0.24*(1-(1-EXP(-50*$AM45))/(1-EXP(-50))) -> 0.15566223 | AO45: =(0.11852-0.05478*LN($AM45))^2 -> 0.10382878 | AP45: =(AM$44*NORMSDIST((1-AN45)^(-0.5)*NORMSINV($AM45)+(AN45/(1-AN45))^(0.5)*NORMSINV(0.999))-$AM45*AM$44)*((1+($B45-2.5)*AO45)/(1-1.5*AO45)) -> 0.077835965 | AS45: ='[3]default rates'!$AR$137 -> 0.012991738 | AT45: =AS45 -> 0.012991738 | AU45: =0.12*(1-EXP(-50*$AT45))/(1-EXP(-50))+0.24*(1-(1-EXP(-50*$AT45))/(1-EXP(-50))) -> 0.18267138 | AV45: =(0.11852-0.05478*LN($AT45))^2 -> 0.12705926 | AW45: =(AT$44*NORMSDIST((1-AU45)^(-0.5)*NORMSINV($AT45)+(AU45/(1-AU45))^(0.5)*NORMSINV(0.999))-$AT45*AT$44)*((1+($B45-2.5)*AV45)/(1-1.5*AV45)) -> 0.028987499 | AY45: ='[3]default rates'!$BG$315 -> 0.0076829535 | AZ45: =AY45 -> 0.0076829535 | BA45: =0.12*(1-EXP(-50*$AT45))/(1-EXP(-50))+0.24*(1-(1-EXP(-50*$AT45))/(1-EXP(-50))) -> 0.18267138 | BB45: =(0.11852-0.05478*LN($AT45))^2 -> 0.12705926 | BC45: =(AZ$44*NORMSDIST((1-BA45)^(-0.5)*NORMSINV($AZ45)+(BA45/(1-BA45))^(0.5)*NORMSINV(0.999))-$AZ45*AZ$44)*((1+($B45-2.5)*BB45)/(1-1.5*BB45)) -> 0.015923571 | BE45: ='[3]default rates'!$AR$137 -> 0.012991738 | BF45: =BE45 -> 0.012991738 | BG45: =0.12*(1-EXP(-50*$AT45))/(1-EXP(-50))+0.24*(1-(1-EXP(-50*$AT45))/(1-EXP(-50))) -> 0.18267138 | BH45: =(0.11852-0.05478*LN($AT45))^2 -> 0.12705926 | BI45: =(BF$44*NORMSDIST((1-BG45)^(-0.5)*NORMSINV($BF45)+(BG45/(1-BG45))^(0.5)*NORMSINV(0.999))-$BF45*BF$44)*((1+($B45-2.5)*BH45)/(1-1.5*BH45)) -> 0.065352579 | BK45: ='[3]default rates'!$BG$315 -> 0.0076829535 | BL45: =BK45 -> 0.0076829535 | BM45: =0.12*(1-EXP(-50*$AT45))/(1-EXP(-50))+0.24*(1-(1-EXP(-50*$AT45))/(1-EXP(-50))) -> 0.18267138 | BN45: =(0.11852-0.05478*LN($AT45))^2 -> 0.12705926 | BO45: =(BL$44*NORMSDIST((1-BM45)^(-0.5)*NORMSINV($BL45)+(BM45/(1-BM45))^(0.5)*NORMSINV(0.999))-$BL45*BL$44)*((1+($B45-2.5)*BN45)/(1-1.5*BN45)) -> 0.046605321
B46: =$B$10 -> 2 | D46: =Q46*100 -> 0.15334271 | E46: =V46*100 -> 0.15334271 | F46: =AA46*100 -> 0.15334271 | G46: =AF46*100 -> 2.9376305 | H46: =AK46*100 -> 7.1195617 | I46: =AP46*100 -> 11.131108 | K46: =AW46*100 -> 4.1265348 | N46: ='[2]Moody''s Global Infra and Corp D'!$Q$68 -> 9.7071977e-06 | O46: =0.12*(1-EXP(-50*$N46))/(1-EXP(-50))+0.24*(1-(1-EXP(-50*$N46))/(1-EXP(-50))) -> 0.23994177 | P46: =(0.11852-0.05478*LN($N46))^2 -> 0.56373965 | Q46: =(N$44*NORMSDIST((1-O46)^(-0.5)*NORMSINV($N46)+(O46/(1-O46))^(0.5)*NORMSINV(0.999))-$N46*N$44)*((1+($B46-2.5)*P46)/(1-1.5*P46)) -> 0.0015334271 | S46: ='[2]Moody''s Global Infra and Corp D'!$Q$69 -> 9.7071977e-06 | T46: =0.12*(1-EXP(-50*$S46))/(1-EXP(-50))+0.24*(1-(1-EXP(-50*$S46))/(1-EXP(-50))) -> 0.23994177 | U46: =(0.11852-0.05478*LN($S46))^2 -> 0.56373965 | V46: =(S$44*NORMSDIST((1-T46)^(-0.5)*NORMSINV($S46)+(T46/(1-T46))^(0.5)*NORMSINV(0.999))-$S46*S$44)*((1+($B46-2.5)*U46)/(1-1.5*U46)) -> 0.0015334271 | X46: ='[2]Moody''s Global Infra and Corp D'!$Q$70 -> 9.7071977e-06 | Y46: =0.12*(1-EXP(-50*$X46))/(1-EXP(-50))+0.24*(1-(1-EXP(-50*$X46))/(1-EXP(-50))) -> 0.23994177 | Z46: =(0.11852-0.05478*LN($X46))^2 -> 0.56373965 | AA46: =(X$44*NORMSDIST((1-Y46)^(-0.5)*NORMSINV($X46)+(Y46/(1-Y46))^(0.5)*NORMSINV(0.999))-$X46*X$44)*((1+($B46-2.5)*Z46)/(1-1.5*Z46)) -> 0.0015334271 | AC46: ='[2]Moody''s Global Infra and Corp D'!$Q$71 -> 0.0019414395 | AD46: =0.12*(1-EXP(-50*$AC46))/(1-EXP(-50))+0.24*(1-(1-EXP(-50*$AC46))/(1-EXP(-50))) -> 0.22889888 | AE46: =(0.11852-0.05478*LN($AC46))^2 -> 0.21213776 | AF46: =(AC$44*NORMSDIST((1-AD46)^(-0.5)*NORMSINV($AC46)+(AD46/(1-AD46))^(0.5)*NORMSINV(0.999))-$AC46*AC$44)*((1+($B46-2.5)*AE46)/(1-1.5*AE46)) -> 0.029376305 | AH46: ='[2]Moody''s Global Infra and Corp D'!$Q$72 -> 0.012619357 | AI46: =0.12*(1-EXP(-50*$AH46))/(1-EXP(-50))+0.24*(1-(1-EXP(-50*$AH46))/(1-EXP(-50))) -> 0.18384919 | AJ46: =(0.11852-0.05478*LN($AH46))^2 -> 0.12819753 | AK46: =(AH$44*NORMSDIST((1-AI46)^(-0.5)*NORMSINV($AH46)+(AI46/(1-AI46))^(0.5)*NORMSINV(0.999))-$AH46*AH$44)*((1+($B46-2.5)*AJ46)/(1-1.5*AJ46)) -> 0.071195617 | AM46: ='[2]Moody''s Global Infra and Corp D'!$Q$73 -> 0.052418867 | AN46: =0.12*(1-EXP(-50*$AM46))/(1-EXP(-50))+0.24*(1-(1-EXP(-50*$AM46))/(1-EXP(-50))) -> 0.12872811 | AO46: =(0.11852-0.05478*LN($AM46))^2 -> 0.078421399 | AP46: =(AM$44*NORMSDIST((1-AN46)^(-0.5)*NORMSINV($AM46)+(AN46/(1-AN46))^(0.5)*NORMSINV(0.999))-$AM46*AM$44)*((1+($B46-2.5)*AO46)/(1-1.5*AO46)) -> 0.11131108 | AS46: ='[3]default rates'!$AS$137 -> 0.012315024 | AT46: =AT45+AS46 -> 0.025306762 | AU46: =0.12*(1-EXP(-50*$AT46))/(1-EXP(-50))+0.24*(1-(1-EXP(-50*$AT46))/(1-EXP(-50))) -> 0.15385727 | AV46: =(0.11852-0.05478*LN($AT46))^2 -> 0.10235439 | AW46: =(AT$44*NORMSDIST((1-AU46)^(-0.5)*NORMSINV($AT46)+(AU46/(1-AU46))^(0.5)*NORMSINV(0.999))-$AT46*AT$44)*((1+($B46-2.5)*AV46)/(1-1.5*AV46)) -> 0.041265348 | AY46: ='[3]default rates'!$BH$315 -> 0.0073026133 | AZ46: =AZ45+AY46 -> 0.014985567 | BA46: =0.12*(1-EXP(-50*$AT46))/(1-EXP(-50))+0.24*(1-(1-EXP(-50*$AT46))/(1-EXP(-50))) -> 0.15385727 | BB46: =(0.11852-0.05478*LN($AT46))^2 -> 0.10235439 | BC46: =(AZ$44*NORMSDIST((1-BA46)^(-0.5)*NORMSINV($AZ46)+(BA46/(1-BA46))^(0.5)*NORMSINV(0.999))-$AZ46*AZ$44)*((1+($B46-2.5)*BB46)/(1-1.5*BB46)) -> 0.0230524 | BE46: ='[3]default rates'!$AS$137 -> 0.012315024 | BF46: =BF45+BE46 -> 0.025306762 | BG46: =0.12*(1-EXP(-50*$AT46))/(1-EXP(-50))+0.24*(1-(1-EXP(-50*$AT46))/(1-EXP(-50))) -> 0.15385727 | BH46: =(0.11852-0.05478*LN($AT46))^2 -> 0.10235439 | BI46: =(BF$44*NORMSDIST((1-BG46)^(-0.5)*NORMSINV($BF46)+(BG46/(1-BG46))^(0.5)*NORMSINV(0.999))-$BF46*BF$44)*((1+($B46-2.5)*BH46)/(1-1.5*BH46)) -> 0.093033099 | BK46: ='[3]default rates'!$BH$315 -> 0.0073026133 | BL46: =BL45+BK46 -> 0.014985567 | BM46: =0.12*(1-EXP(-50*$AT46))/(1-EXP(-50))+0.24*(1-(1-EXP(-50*$AT46))/(1-EXP(-50))) -> 0.15385727 | BN46: =(0.11852-0.05478*LN($AT46))^2 -> 0.10235439 | BO46: =(BL$44*NORMSDIST((1-BM46)^(-0.5)*NORMSINV($BL46)+(BM46/(1-BM46))^(0.5)*NORMSINV(0.999))-$BL46*BL$44)*((1+($B46-2.5)*BN46)/(1-1.5*BN46)) -> 0.067470074
B47: =$B$11 -> 3 | D47: =Q47*100 -> 0.27371833 | E47: =V47*100 -> 0.27371833 | F47: =AA47*100 -> 2.4931558 | G47: =AF47*100 -> 5.1243911 | H47: =AK47*100 -> 9.4918863 | I47: =AP47*100 -> 14.234214 | K47: =AW47*100 -> 4.9767718 | N47: ='[2]Moody''s Global Infra and Corp D'!$R$68 -> 9.7071977e-06 | O47: =0.12*(1-EXP(-50*$N47))/(1-EXP(-50))+0.24*(1-(1-EXP(-50*$N47))/(1-EXP(-50))) -> 0.23994177 | P47: =(0.11852-0.05478*LN($N47))^2 -> 0.56373965 | Q47: =(N$44*NORMSDIST((1-O47)^(-0.5)*NORMSINV($N47)+(O47/(1-O47))^(0.5)*NORMSINV(0.999))-$N47*N$44)*((1+($B47-2.5)*P47)/(1-1.5*P47)) -> 0.0027371833 | S47: ='[2]Moody''s Global Infra and Corp D'!$R$69 -> 9.7071977e-06 | T47: =0.12*(1-EXP(-50*$S47))/(1-EXP(-50))+0.24*(1-(1-EXP(-50*$S47))/(1-EXP(-50))) -> 0.23994177 | U47: =(0.11852-0.05478*LN($S47))^2 -> 0.56373965 | V47: =(S$44*NORMSDIST((1-T47)^(-0.5)*NORMSINV($S47)+(T47/(1-T47))^(0.5)*NORMSINV(0.999))-$S47*S$44)*((1+($B47-2.5)*U47)/(1-1.5*U47)) -> 0.0027371833 | X47: ='[2]Moody''s Global Infra and Corp D'!$R$70 -> 0.00097071977 | Y47: =0.12*(1-EXP(-50*$X47))/(1-EXP(-50))+0.24*(1-(1-EXP(-50*$X47))/(1-EXP(-50))) -> 0.23431477 | Z47: =(0.11852-0.05478*LN($X47))^2 -> 0.24855685 | AA47: =(X$44*NORMSDIST((1-Y47)^(-0.5)*NORMSINV($X47)+(Y47/(1-Y47))^(0.5)*NORMSINV(0.999))-$X47*X$44)*((1+($B47-2.5)*Z47)/(1-1.5*Z47)) -> 0.024931558 | AC47: ='[2]Moody''s Global Infra and Corp D'!$R$71 -> 0.0038828791 | AD47: =0.12*(1-EXP(-50*$AC47))/(1-EXP(-50))+0.24*(1-(1-EXP(-50*$AC47))/(1-EXP(-50))) -> 0.21882472 | AE47: =(0.11852-0.05478*LN($AC47))^2 -> 0.17860221 | AF47: =(AC$44*NORMSDIST((1-AD47)^(-0.5)*NORMSINV($AC47)+(AD47/(1-AD47))^(0.5)*NORMSINV(0.999))-$AC47*AC$44)*((1+($B47-2.5)*AE47)/(1-1.5*AE47)) -> 0.051243911 | AH47: ='[2]Moody''s Global Infra and Corp D'!$R$72 -> 0.022326555 | AI47: =0.12*(1-EXP(-50*$AH47))/(1-EXP(-50))+0.24*(1-(1-EXP(-50*$AH47))/(1-EXP(-50))) -> 0.15929762 | AJ47: =(0.11852-0.05478*LN($AH47))^2 -> 0.10679326 | AK47: =(AH$44*NORMSDIST((1-AI47)^(-0.5)*NORMSINV($AH47)+(AI47/(1-AI47))^(0.5)*NORMSINV(0.999))-$AH47*AH$44)*((1+($B47-2.5)*AJ47)/(1-1.5*AJ47)) -> 0.094918863 | AM47: ='[2]Moody''s Global Infra and Corp D'!$R$73 -> 0.08445262 | AN47: =0.12*(1-EXP(-50*$AM47))/(1-EXP(-50))+0.24*(1-(1-EXP(-50*$AM47))/(1-EXP(-50))) -> 0.1217592 | AO47: =(0.11852-0.05478*LN($AM47))^2 -> 0.064471461 | AP47: =(AM$44*NORMSDIST((1-AN47)^(-0.5)*NORMSINV($AM47)+(AN47/(1-AN47))^(0.5)*NORMSINV(0.999))-$AM47*AM$44)*((1+($B47-2.5)*AO47)/(1-1.5*AO47)) -> 0.14234214 | AS47: ='[3]default rates'!$AT$137 -> 0.009657298 | AT47: =AT46+AS47 -> 0.03496406 | AU47: =0.12*(1-EXP(-50*$AT47))/(1-EXP(-50))+0.24*(1-(1-EXP(-50*$AT47))/(1-EXP(-50))) -> 0.14089038 | AV47: =(0.11852-0.05478*LN($AT47))^2 -> 0.091337622 | AW47: =(AT$44*NORMSDIST((1-AU47)^(-0.5)*NORMSINV($AT47)+(AU47/(1-AU47))^(0.5)*NORMSINV(0.999))-$AT47*AT$44)*((1+($B47-2.5)*AV47)/(1-1.5*AV47)) -> 0.049767718 | AY47: ='[3]default rates'!$BI$315 -> 0.0069778527 | AZ47: =AZ46+AY47 -> 0.02196342 | BA47: =0.12*(1-EXP(-50*$AT47))/(1-EXP(-50))+0.24*(1-(1-EXP(-50*$AT47))/(1-EXP(-50))) -> 0.14089038 | BB47: =(0.11852-0.05478*LN($AT47))^2 -> 0.091337622 | BC47: =(AZ$44*NORMSDIST((1-BA47)^(-0.5)*NORMSINV($AZ47)+(BA47/(1-BA47))^(0.5)*NORMSINV(0.999))-$AZ47*AZ$44)*((1+($B47-2.5)*BB47)/(1-1.5*BB47)) -> 0.029103937 | BE47: ='[3]default rates'!$AT$137 -> 0.009657298 | BF47: =BF46+BE47 -> 0.03496406 | BG47: =0.12*(1-EXP(-50*$AT47))/(1-EXP(-50))+0.24*(1-(1-EXP(-50*$AT47))/(1-EXP(-50))) -> 0.14089038 | BH47: =(0.11852-0.05478*LN($AT47))^2 -> 0.091337622 | BI47: =(BF$44*NORMSDIST((1-BG47)^(-0.5)*NORMSINV($BF47)+(BG47/(1-BG47))^(0.5)*NORMSINV(0.999))-$BF47*BF$44)*((1+($B47-2.5)*BH47)/(1-1.5*BH47)) -> 0.11220177 | BK47: ='[3]default rates'!$BI$315 -> 0.0069778527 | BL47: =BL46+BK47 -> 0.02196342 | BM47: =0.12*(1-EXP(-50*$AT47))/(1-EXP(-50))+0.24*(1-(1-EXP(-50*$AT47))/(1-EXP(-50))) -> 0.14089038 | BN47: =(0.11852-0.05478*LN($AT47))^2 -> 0.091337622 | BO47: =(BL$44*NORMSDIST((1-BM47)^(-0.5)*NORMSINV($BL47)+(BM47/(1-BM47))^(0.5)*NORMSINV(0.999))-$BL47*BL$44)*((1+($B47-2.5)*BN47)/(1-1.5*BN47)) -> 0.085181794
B48: =$B$12 -> 4 | D48: =Q48*100 -> 0.39409396 | E48: =V48*100 -> 0.39409396 | F48: =AA48*100 -> 3.0443457 | G48: =AF48*100 -> 6.5456043 | H48: =AK48*100 -> 11.522949 | I48: =AP48*100 -> 16.598147 | K48: =AW48*100 -> 5.688224 | N48: ='[2]Moody''s Global Infra and Corp D'!$S$68 -> 9.7071977e-06 | O48: =0.12*(1-EXP(-50*$N48))/(1-EXP(-50))+0.24*(1-(1-EXP(-50*$N48))/(1-EXP(-50))) -> 0.23994177 | P48: =(0.11852-0.05478*LN($N48))^2 -> 0.56373965 | Q48: =(N$44*NORMSDIST((1-O48)^(-0.5)*NORMSINV($N48)+(O48/(1-O48))^(0.5)*NORMSINV(0.999))-$N48*N$44)*((1+($B48-2.5)*P48)/(1-1.5*P48)) -> 0.0039409396 | S48: ='[2]Moody''s Global Infra and Corp D'!$S$69 -> 9.7071977e-06 | T48: =0.12*(1-EXP(-50*$S48))/(1-EXP(-50))+0.24*(1-(1-EXP(-50*$S48))/(1-EXP(-50))) -> 0.23994177 | U48: =(0.11852-0.05478*LN($S48))^2 -> 0.56373965 | V48: =(S$44*NORMSDIST((1-T48)^(-0.5)*NORMSINV($S48)+(T48/(1-T48))^(0.5)*NORMSINV(0.999))-$S48*S$44)*((1+($B48-2.5)*U48)/(1-1.5*U48)) -> 0.0039409396 | X48: ='[2]Moody''s Global Infra and Corp D'!$S$70 -> 0.00097071977 | Y48: =0.12*(1-EXP(-50*$X48))/(1-EXP(-50))+0.24*(1-(1-EXP(-50*$X48))/(1-EXP(-50))) -> 0.23431477 | Z48: =(0.11852-0.05478*LN($X48))^2 -> 0.24855685 | AA48: =(X$44*NORMSDIST((1-Y48)^(-0.5)*NORMSINV($X48)+(Y48/(1-Y48))^(0.5)*NORMSINV(0.999))-$X48*X$44)*((1+($B48-2.5)*Z48)/(1-1.5*Z48)) -> 0.030443457 | AC48: ='[2]Moody''s Global Infra and Corp D'!$S$71 -> 0.0048535988 | AD48: =0.12*(1-EXP(-50*$AC48))/(1-EXP(-50))+0.24*(1-(1-EXP(-50*$AC48))/(1-EXP(-50))) -> 0.21414271 | AE48: =(0.11852-0.05478*LN($AC48))^2 -> 0.16841974 | AF48: =(AC$44*NORMSDIST((1-AD48)^(-0.5)*NORMSINV($AC48)+(AD48/(1-AD48))^(0.5)*NORMSINV(0.999))-$AC48*AC$44)*((1+($B48-2.5)*AE48)/(1-1.5*AE48)) -> 0.065456043 | AH48: ='[2]Moody''s Global Infra and Corp D'!$S$72 -> 0.033975192 | AI48: =0.12*(1-EXP(-50*$AH48))/(1-EXP(-50))+0.24*(1-(1-EXP(-50*$AH48))/(1-EXP(-50))) -> 0.14194923 | AJ48: =(0.11852-0.05478*LN($AH48))^2 -> 0.092290059 | AK48: =(AH$44*NORMSDIST((1-AI48)^(-0.5)*NORMSINV($AH48)+(AI48/(1-AI48))^(0.5)*NORMSINV(0.999))-$AH48*AH$44)*((1+($B48-2.5)*AJ48)/(1-1.5*AJ48)) -> 0.11522949 | AM48: ='[2]Moody''s Global Infra and Corp D'!$S$73 -> 0.11163277 | AN48: =0.12*(1-EXP(-50*$AM48))/(1-EXP(-50))+0.24*(1-(1-EXP(-50*$AM48))/(1-EXP(-50))) -> 0.12045197 | AO48: =(0.11852-0.05478*LN($AM48))^2 -> 0.056943024 | AP48: =(AM$44*NORMSDIST((1-AN48)^(-0.5)*NORMSINV($AM48)+(AN48/(1-AN48))^(0.5)*NORMSINV(0.999))-$AM48*AM$44)*((1+($B48-2.5)*AO48)/(1-1.5*AO48)) -> 0.16598147 | AS48: ='[3]default rates'!$AU$137 -> 0.0075053741 | AT48: =AT47+AS48 -> 0.042469434 | AU48: =0.12*(1-EXP(-50*$AT48))/(1-EXP(-50))+0.24*(1-(1-EXP(-50*$AT48))/(1-EXP(-50))) -> 0.13435388 | AV48: =(0.11852-0.05478*LN($AT48))^2 -> 0.085012139 | AW48: =(AT$44*NORMSDIST((1-AU48)^(-0.5)*NORMSINV($AT48)+(AU48/(1-AU48))^(0.5)*NORMSINV(0.999))-$AT48*AT$44)*((1+($B48-2.5)*AV48)/(1-1.5*AV48)) -> 0.05688224 | AY48: ='[3]default rates'!$BJ$315 -> 0.0065900969 | AZ48: =AZ47+AY48 -> 0.028553517 | BA48: =0.12*(1-EXP(-50*$AT48))/(1-EXP(-50))+0.24*(1-(1-EXP(-50*$AT48))/(1-EXP(-50))) -> 0.13435388 | BB48: =(0.11852-0.05478*LN($AT48))^2 -> 0.085012139 | BC48: =(AZ$44*NORMSDIST((1-BA48)^(-0.5)*NORMSINV($AZ48)+(BA48/(1-BA48))^(0.5)*NORMSINV(0.999))-$AZ48*AZ$44)*((1+($B48-2.5)*BB48)/(1-1.5*BB48)) -> 0.034862797 | BE48: ='[3]default rates'!$AU$137 -> 0.0075053741 | BF48: =BF47+BE48 -> 0.042469434 | BG48: =0.12*(1-EXP(-50*$AT48))/(1-EXP(-50))+0.24*(1-(1-EXP(-50*$AT48))/(1-EXP(-50))) -> 0.13435388 | BH48: =(0.11852-0.05478*LN($AT48))^2 -> 0.085012139 | BI48: =(BF$44*NORMSDIST((1-BG48)^(-0.5)*NORMSINV($BF48)+(BG48/(1-BG48))^(0.5)*NORMSINV(0.999))-$BF48*BF$44)*((1+($B48-2.5)*BH48)/(1-1.5*BH48)) -> 0.12824152 | BK48: ='[3]default rates'!$BJ$315 -> 0.0065900969 | BL48: =BL47+BK48 -> 0.028553517 | BM48: =0.12*(1-EXP(-50*$AT48))/(1-EXP(-50))+0.24*(1-(1-EXP(-50*$AT48))/(1-EXP(-50))) -> 0.13435388 | BN48: =(0.11852-0.05478*LN($AT48))^2 -> 0.085012139 | BO48: =(BL$44*NORMSDIST((1-BM48)^(-0.5)*NORMSINV($BL48)+(BM48/(1-BM48))^(0.5)*NORMSINV(0.999))-$BL48*BL$44)*((1+($B48-2.5)*BN48)/(1-1.5*BN48)) -> 0.1020369
B49: =$B$13 -> 5 | D49: =Q49*100 -> 0.51446958 | E49: =V49*100 -> 0.51446958 | F49: =AA49*100 -> 5.0290076 | G49: =AF49*100 -> 8.3748527 | H49: =AK49*100 -> 13.354501 | I49: =AP49*100 -> 18.437142 | K49: =AW49*100 -> 6.3196706 | N49: ='[2]Moody''s Global Infra and Corp D'!$T$68 -> 9.7071977e-06 | O49: =0.12*(1-EXP(-50*$N49))/(1-EXP(-50))+0.24*(1-(1-EXP(-50*$N49))/(1-EXP(-50))) -> 0.23994177 | P49: =(0.11852-0.05478*LN($N49))^2 -> 0.56373965 | Q49: =(N$44*NORMSDIST((1-O49)^(-0.5)*NORMSINV($N49)+(O49/(1-O49))^(0.5)*NORMSINV(0.999))-$N49*N$44)*((1+($B49-2.5)*P49)/(1-1.5*P49)) -> 0.0051446958 | S49: ='[2]Moody''s Global Infra and Corp D'!$T$69 -> 9.7071977e-06 | T49: =0.12*(1-EXP(-50*$S49))/(1-EXP(-50))+0.24*(1-(1-EXP(-50*$S49))/(1-EXP(-50))) -> 0.23994177 | U49: =(0.11852-0.05478*LN($S49))^2 -> 0.56373965 | V49: =(S$44*NORMSDIST((1-T49)^(-0.5)*NORMSINV($S49)+(T49/(1-T49))^(0.5)*NORMSINV(0.999))-$S49*S$44)*((1+($B49-2.5)*U49)/(1-1.5*U49)) -> 0.0051446958 | X49: ='[2]Moody''s Global Infra and Corp D'!$T$70 -> 0.0019414395 | Y49: =0.12*(1-EXP(-50*$X49))/(1-EXP(-50))+0.24*(1-(1-EXP(-50*$X49))/(1-EXP(-50))) -> 0.22889888 | Z49: =(0.11852-0.05478*LN($X49))^2 -> 0.21213776 | AA49: =(X$44*NORMSDIST((1-Y49)^(-0.5)*NORMSINV($X49)+(Y49/(1-Y49))^(0.5)*NORMSINV(0.999))-$X49*X$44)*((1+($B49-2.5)*Z49)/(1-1.5*Z49)) -> 0.050290076 | AC49: ='[2]Moody''s Global Infra and Corp D'!$T$71 -> 0.0067950384 | AD49: =0.12*(1-EXP(-50*$AC49))/(1-EXP(-50))+0.24*(1-(1-EXP(-50*$AC49))/(1-EXP(-50))) -> 0.20543363 | AE49: =(0.11852-0.05478*LN($AC49))^2 -> 0.15363092 | AF49: =(AC$44*NORMSDIST((1-AD49)^(-0.5)*NORMSINV($AC49)+(AD49/(1-AD49))^(0.5)*NORMSINV(0.999))-$AC49*AC$44)*((1+($B49-2.5)*AE49)/(1-1.5*AE49)) -> 0.083748527 | AH49: ='[2]Moody''s Global Infra and Corp D'!$T$72 -> 0.045623829 | AI49: =0.12*(1-EXP(-50*$AH49))/(1-EXP(-50))+0.24*(1-(1-EXP(-50*$AH49))/(1-EXP(-50))) -> 0.13225949 | AJ49: =(0.11852-0.05478*LN($AH49))^2 -> 0.082738881 | AK49: =(AH$44*NORMSDIST((1-AI49)^(-0.5)*NORMSINV($AH49)+(AI49/(1-AI49))^(0.5)*NORMSINV(0.999))-$AH49*AH$44)*((1+($B49-2.5)*AJ49)/(1-1.5*AJ49)) -> 0.13354501 | AM49: ='[2]Moody''s Global Infra and Corp D'!$T$73 -> 0.13493005 | AN49: =0.12*(1-EXP(-50*$AM49))/(1-EXP(-50))+0.24*(1-(1-EXP(-50*$AM49))/(1-EXP(-50))) -> 0.120141 | AO49: =(0.11852-0.05478*LN($AM49))^2 -> 0.052095449 | AP49: =(AM$44*NORMSDIST((1-AN49)^(-0.5)*NORMSINV($AM49)+(AN49/(1-AN49))^(0.5)*NORMSINV(0.999))-$AM49*AM$44)*((1+($B49-2.5)*AO49)/(1-1.5*AO49)) -> 0.18437142 | AS49: ='[3]default rates'!$AV$137 -> 0.0057977504 | AT49: =AT48+AS49 -> 0.048267185 | AU49: =0.12*(1-EXP(-50*$AT49))/(1-EXP(-50))+0.24*(1-(1-EXP(-50*$AT49))/(1-EXP(-50))) -> 0.13074169 | AV49: =(0.11852-0.05478*LN($AT49))^2 -> 0.080973462 | AW49: =(AT$44*NORMSDIST((1-AU49)^(-0.5)*NORMSINV($AT49)+(AU49/(1-AU49))^(0.5)*NORMSINV(0.999))-$AT49*AT$44)*((1+($B49-2.5)*AV49)/(1-1.5*AV49)) -> 0.063196706 | AY49: ='[3]default rates'!$BK$315 -> 0.0051442093 | AZ49: =AZ48+AY49 -> 0.033697726 | BA49: =0.12*(1-EXP(-50*$AT49))/(1-EXP(-50))+0.24*(1-(1-EXP(-50*$AT49))/(1-EXP(-50))) -> 0.13074169 | BB49: =(0.11852-0.05478*LN($AT49))^2 -> 0.080973462 | BC49: =(AZ$44*NORMSDIST((1-BA49)^(-0.5)*NORMSINV($AZ49)+(BA49/(1-BA49))^(0.5)*NORMSINV(0.999))-$AZ49*AZ$44)*((1+($B49-2.5)*BB49)/(1-1.5*BB49)) -> 0.039760504 | BE49: ='[3]default rates'!$AV$137 -> 0.0057977504 | BF49: =BF48+BE49 -> 0.048267185 | BG49: =0.12*(1-EXP(-50*$AT49))/(1-EXP(-50))+0.24*(1-(1-EXP(-50*$AT49))/(1-EXP(-50))) -> 0.13074169 | BH49: =(0.11852-0.05478*LN($AT49))^2 -> 0.080973462 | BI49: =(BF$44*NORMSDIST((1-BG49)^(-0.5)*NORMSINV($BF49)+(BG49/(1-BG49))^(0.5)*NORMSINV(0.999))-$BF49*BF$44)*((1+($B49-2.5)*BH49)/(1-1.5*BH49)) -> 0.14247754 | BK49: ='[3]default rates'!$BK$315 -> 0.0051442093 | BL49: =BL48+BK49 -> 0.033697726 | BM49: =0.12*(1-EXP(-50*$AT49))/(1-EXP(-50))+0.24*(1-(1-EXP(-50*$AT49))/(1-EXP(-50))) -> 0.13074169 | BN49: =(0.11852-0.05478*LN($AT49))^2 -> 0.080973462 | BO49: =(BL$44*NORMSDIST((1-BM49)^(-0.5)*NORMSINV($BL49)+(BM49/(1-BM49))^(0.5)*NORMSINV(0.999))-$BL49*BL$44)*((1+($B49-2.5)*BN49)/(1-1.5*BN49)) -> 0.11637158
B50: =$B$14 -> 6 | D50: =Q50*100 -> 0.6348452 | E50: =V50*100 -> 0.6348452 | F50: =AA50*100 -> 5.7261333 | G50: =AF50*100 -> 9.6932107 | H50: =AK50*100 -> 14.835167 | I50: =AP50*100 -> 19.84549 | K50: =AW50*100 -> 6.8735005 | N50: ='[2]Moody''s Global Infra and Corp D'!$U$68 -> 9.7071977e-06 | O50: =0.12*(1-EXP(-50*$N50))/(1-EXP(-50))+0.24*(1-(1-EXP(-50*$N50))/(1-EXP(-50))) -> 0.23994177 | P50: =(0.11852-0.05478*LN($N50))^2 -> 0.56373965 | Q50: =(N$44*NORMSDIST((1-O50)^(-0.5)*NORMSINV($N50)+(O50/(1-O50))^(0.5)*NORMSINV(0.999))-$N50*N$44)*((1+($B50-2.5)*P50)/(1-1.5*P50)) -> 0.006348452 | S50: ='[2]Moody''s Global Infra and Corp D'!$U$69 -> 9.7071977e-06 | T50: =0.12*(1-EXP(-50*$S50))/(1-EXP(-50))+0.24*(1-(1-EXP(-50*$S50))/(1-EXP(-50))) -> 0.23994177 | U50: =(0.11852-0.05478*LN($S50))^2 -> 0.56373965 | V50: =(S$44*NORMSDIST((1-T50)^(-0.5)*NORMSINV($S50)+(T50/(1-T50))^(0.5)*NORMSINV(0.999))-$S50*S$44)*((1+($B50-2.5)*U50)/(1-1.5*U50)) -> 0.006348452 | X50: ='[2]Moody''s Global Infra and Corp D'!$U$70 -> 0.0019414395 | Y50: =0.12*(1-EXP(-50*$X50))/(1-EXP(-50))+0.24*(1-(1-EXP(-50*$X50))/(1-EXP(-50))) -> 0.22889888 | Z50: =(0.11852-0.05478*LN($X50))^2 -> 0.21213776 | AA50: =(X$44*NORMSDIST((1-Y50)^(-0.5)*NORMSINV($X50)+(Y50/(1-Y50))^(0.5)*NORMSINV(0.999))-$X50*X$44)*((1+($B50-2.5)*Z50)/(1-1.5*Z50)) -> 0.057261333 | AC50: ='[2]Moody''s Global Infra and Corp D'!$U$71 -> 0.0077657581 | AD50: =0.12*(1-EXP(-50*$AC50))/(1-EXP(-50))+0.24*(1-(1-EXP(-50*$AC50))/(1-EXP(-50))) -> 0.20138605 | AE50: =(0.11852-0.05478*LN($AC50))^2 -> 0.1479502 | AF50: =(AC$44*NORMSDIST((1-AD50)^(-0.5)*NORMSINV($AC50)+(AD50/(1-AD50))^(0.5)*NORMSINV(0.999))-$AC50*AC$44)*((1+($B50-2.5)*AE50)/(1-1.5*AE50)) -> 0.096932107 | AH50: ='[2]Moody''s Global Infra and Corp D'!$U$72 -> 0.053389587 | AI50: =0.12*(1-EXP(-50*$AH50))/(1-EXP(-50))+0.24*(1-(1-EXP(-50*$AH50))/(1-EXP(-50))) -> 0.12831459 | AJ50: =(0.11852-0.05478*LN($AH50))^2 -> 0.07785944 | AK50: =(AH$44*NORMSDIST((1-AI50)^(-0.5)*NORMSINV($AH50)+(AI50/(1-AI50))^(0.5)*NORMSINV(0.999))-$AH50*AH$44)*((1+($B50-2.5)*AJ50)/(1-1.5*AJ50)) -> 0.14835167 | AM50: ='[2]Moody''s Global Infra and Corp D'!$U$73 -> 0.152403 | AN50: =0.12*(1-EXP(-50*$AM50))/(1-EXP(-50))+0.24*(1-(1-EXP(-50*$AM50))/(1-EXP(-50))) -> 0.12005886 | AO50: =(0.11852-0.05478*LN($AM50))^2 -> 0.049094865 | AP50: =(AM$44*NORMSDIST((1-AN50)^(-0.5)*NORMSINV($AM50)+(AN50/(1-AN50))^(0.5)*NORMSINV(0.999))-$AM50*AM$44)*((1+($B50-2.5)*AO50)/(1-1.5*AO50)) -> 0.1984549 | AS50: ='[3]default rates'!$AW$137 -> 0.0037865959 | AT50: =AT49+AS50 -> 0.05205378 | AU50: =0.12*(1-EXP(-50*$AT50))/(1-EXP(-50))+0.24*(1-(1-EXP(-50*$AT50))/(1-EXP(-50))) -> 0.12888889 | AV50: =(0.11852-0.05478*LN($AT50))^2 -> 0.07863598 | AW50: =(AT$44*NORMSDIST((1-AU50)^(-0.5)*NORMSINV($AT50)+(AU50/(1-AU50))^(0.5)*NORMSINV(0.999))-$AT50*AT$44)*((1+($B50-2.5)*AV50)/(1-1.5*AV50)) -> 0.068735005 | AY50: ='[3]default rates'!$BL$315 -> 0.0034635566 | AZ50: =AZ49+AY50 -> 0.037161282 | BA50: =0.12*(1-EXP(-50*$AT50))/(1-EXP(-50))+0.24*(1-(1-EXP(-50*$AT50))/(1-EXP(-50))) -> 0.12888889 | BB50: =(0.11852-0.05478*LN($AT50))^2 -> 0.07863598 | BC50: =(AZ$44*NORMSDIST((1-BA50)^(-0.5)*NORMSINV($AZ50)+(BA50/(1-BA50))^(0.5)*NORMSINV(0.999))-$AZ50*AZ$44)*((1+($B50-2.5)*BB50)/(1-1.5*BB50)) -> 0.04391242 | BE50: ='[3]default rates'!$AW$137 -> 0.0037865959 | BF50: =BF49+BE50 -> 0.05205378 | BG50: =0.12*(1-EXP(-50*$AT50))/(1-EXP(-50))+0.24*(1-(1-EXP(-50*$AT50))/(1-EXP(-50))) -> 0.12888889 | BH50: =(0.11852-0.05478*LN($AT50))^2 -> 0.07863598 | BI50: =(BF$44*NORMSDIST((1-BG50)^(-0.5)*NORMSINV($BF50)+(BG50/(1-BG50))^(0.5)*NORMSINV(0.999))-$BF50*BF$44)*((1+($B50-2.5)*BH50)/(1-1.5*BH50)) -> 0.15496369 | BK50: ='[3]default rates'!$BL$315 -> 0.0034635566 | BL50: =BL49+BK50 -> 0.037161282 | BM50: =0.12*(1-EXP(-50*$AT50))/(1-EXP(-50))+0.24*(1-(1-EXP(-50*$AT50))/(1-EXP(-50))) -> 0.12888889 | BN50: =(0.11852-0.05478*LN($AT50))^2 -> 0.07863598 | BO50: =(BL$44*NORMSDIST((1-BM50)^(-0.5)*NORMSINV($BL50)+(BM50/(1-BM50))^(0.5)*NORMSINV(0.999))-$BL50*BL$44)*((1+($B50-2.5)*BN50)/(1-1.5*BN50)) -> 0.12852346
B51: =$B$15 -> 7 | D51: =Q51*100 -> 0.75522082 | E51: =V51*100 -> 0.75522082 | F51: =AA51*100 -> 7.5995123 | G51: =AF51*100 -> 11.286827 | H51: =AK51*100 -> 16.084973 | I51: =AP51*100 -> 21.103014 | K51: =AW51*100 -> 7.3778976 | N51: ='[2]Moody''s Global Infra and Corp D'!$V$68 -> 9.7071977e-06 | O51: =0.12*(1-EXP(-50*$N51))/(1-EXP(-50))+0.24*(1-(1-EXP(-50*$N51))/(1-EXP(-50))) -> 0.23994177 | P51: =(0.11852-0.05478*LN($N51))^2 -> 0.56373965 | Q51: =(N$44*NORMSDIST((1-O51)^(-0.5)*NORMSINV($N51)+(O51/(1-O51))^(0.5)*NORMSINV(0.999))-$N51*N$44)*((1+($B51-2.5)*P51)/(1-1.5*P51)) -> 0.0075522082 | S51: ='[2]Moody''s Global Infra and Corp D'!$V$69 -> 9.7071977e-06 | T51: =0.12*(1-EXP(-50*$S51))/(1-EXP(-50))+0.24*(1-(1-EXP(-50*$S51))/(1-EXP(-50))) -> 0.23994177 | U51: =(0.11852-0.05478*LN($S51))^2 -> 0.56373965 | V51: =(S$44*NORMSDIST((1-T51)^(-0.5)*NORMSINV($S51)+(T51/(1-T51))^(0.5)*NORMSINV(0.999))-$S51*S$44)*((1+($B51-2.5)*U51)/(1-1.5*U51)) -> 0.0075522082 | X51: ='[2]Moody''s Global Infra and Corp D'!$V$70 -> 0.0029121593 | Y51: =0.12*(1-EXP(-50*$X51))/(1-EXP(-50))+0.24*(1-(1-EXP(-50*$X51))/(1-EXP(-50))) -> 0.22373959 | Z51: =(0.11852-0.05478*LN($X51))^2 -> 0.19217069 | AA51: =(X$44*NORMSDIST((1-Y51)^(-0.5)*NORMSINV($X51)+(Y51/(1-Y51))^(0.5)*NORMSINV(0.999))-$X51*X$44)*((1+($B51-2.5)*Z51)/(1-1.5*Z51)) -> 0.075995123 | AC51: ='[2]Moody''s Global Infra and Corp D'!$V$71 -> 0.0097071977 | AD51: =0.12*(1-EXP(-50*$AC51))/(1-EXP(-50))+0.24*(1-(1-EXP(-50*$AC51))/(1-EXP(-50))) -> 0.19385708 | AE51: =(0.11852-0.05478*LN($AC51))^2 -> 0.13869602 | AF51: =(AC$44*NORMSDIST((1-AD51)^(-0.5)*NORMSINV($AC51)+(AD51/(1-AD51))^(0.5)*NORMSINV(0.999))-$AC51*AC$44)*((1+($B51-2.5)*AE51)/(1-1.5*AE51)) -> 0.11286827 | AH51: ='[2]Moody''s Global Infra and Corp D'!$V$72 -> 0.058243186 | AI51: =0.12*(1-EXP(-50*$AH51))/(1-EXP(-50))+0.24*(1-(1-EXP(-50*$AH51))/(1-EXP(-50))) -> 0.12652299 | AJ51: =(0.11852-0.05478*LN($AH51))^2 -> 0.075222147 | AK51: =(AH$44*NORMSDIST((1-AI51)^(-0.5)*NORMSINV($AH51)+(AI51/(1-AI51))^(0.5)*NORMSINV(0.999))-$AH51*AH$44)*((1+($B51-2.5)*AJ51)/(1-1.5*AJ51)) -> 0.16084973 | AM51: ='[2]Moody''s Global Infra and Corp D'!$V$73 -> 0.16987596 | AN51: =0.12*(1-EXP(-50*$AM51))/(1-EXP(-50))+0.24*(1-(1-EXP(-50*$AM51))/(1-EXP(-50))) -> 0.12002457 | AO51: =(0.11852-0.05478*LN($AM51))^2 -> 0.04649534 | AP51: =(AM$44*NORMSDIST((1-AN51)^(-0.5)*NORMSINV($AM51)+(AN51/(1-AN51))^(0.5)*NORMSINV(0.999))-$AM51*AM$44)*((1+($B51-2.5)*AO51)/(1-1.5*AO51)) -> 0.21103014 | AS51: ='[3]default rates'!$AX$137 -> 0.0024306611 | AT51: =AT50+AS51 -> 0.054484442 | AU51: =0.12*(1-EXP(-50*$AT51))/(1-EXP(-50))+0.24*(1-(1-EXP(-50*$AT51))/(1-EXP(-50))) -> 0.12787167 | AV51: =(0.11852-0.05478*LN($AT51))^2 -> 0.077240105 | AW51: =(AT$44*NORMSDIST((1-AU51)^(-0.5)*NORMSINV($AT51)+(AU51/(1-AU51))^(0.5)*NORMSINV(0.999))-$AT51*AT$44)*((1+($B51-2.5)*AV51)/(1-1.5*AV51)) -> 0.073778976 | AY51: ='[3]default rates'!$BM$315 -> 0.0029963573 | AZ51: =AZ50+AY51 -> 0.04015764 | BA51: =0.12*(1-EXP(-50*$AT51))/(1-EXP(-50))+0.24*(1-(1-EXP(-50*$AT51))/(1-EXP(-50))) -> 0.12787167 | BB51: =(0.11852-0.05478*LN($AT51))^2 -> 0.077240105 | BC51: =(AZ$44*NORMSDIST((1-BA51)^(-0.5)*NORMSINV($AZ51)+(BA51/(1-BA51))^(0.5)*NORMSINV(0.999))-$AZ51*AZ$44)*((1+($B51-2.5)*BB51)/(1-1.5*BB51)) -> 0.048069997 | BE51: ='[3]default rates'!$AX$137 -> 0.0024306611 | BF51: =BF50+BE51 -> 0.054484442 | BG51: =0.12*(1-EXP(-50*$AT51))/(1-EXP(-50))+0.24*(1-(1-EXP(-50*$AT51))/(1-EXP(-50))) -> 0.12787167 | BH51: =(0.11852-0.05478*LN($AT51))^2 -> 0.077240105 | BI51: =(BF$44*NORMSDIST((1-BG51)^(-0.5)*NORMSINV($BF51)+(BG51/(1-BG51))^(0.5)*NORMSINV(0.999))-$BF51*BF$44)*((1+($B51-2.5)*BH51)/(1-1.5*BH51)) -> 0.16633537 | BK51: ='[3]default rates'!$BM$315 -> 0.0029963573 | BL51: =BL50+BK51 -> 0.04015764 | BM51: =0.12*(1-EXP(-50*$AT51))/(1-EXP(-50))+0.24*(1-(1-EXP(-50*$AT51))/(1-EXP(-50))) -> 0.12787167 | BN51: =(0.11852-0.05478*LN($AT51))^2 -> 0.077240105 | BO51: =(BL$44*NORMSDIST((1-BM51)^(-0.5)*NORMSINV($BL51)+(BM51/(1-BM51))^(0.5)*NORMSINV(0.999))-$BL51*BL$44)*((1+($B51-2.5)*BN51)/(1-1.5*BN51)) -> 0.14069191
B52: =$B$16 -> 8 | D52: =Q52*100 -> 0.87559644 | E52: =V52*100 -> 0.87559644 | F52: =AA52*100 -> 8.3826678 | G52: =AF52*100 -> 12.520997 | H52: =AK52*100 -> 17.189302 | I52: =AP52*100 -> 22.175486 | K52: =AW52*100 -> 7.8544725 | N52: ='[2]Moody''s Global Infra and Corp D'!$W$68 -> 9.7071977e-06 | O52: =0.12*(1-EXP(-50*$N52))/(1-EXP(-50))+0.24*(1-(1-EXP(-50*$N52))/(1-EXP(-50))) -> 0.23994177 | P52: =(0.11852-0.05478*LN($N52))^2 -> 0.56373965 | Q52: =(N$44*NORMSDIST((1-O52)^(-0.5)*NORMSINV($N52)+(O52/(1-O52))^(0.5)*NORMSINV(0.999))-$N52*N$44)*((1+($B52-2.5)*P52)/(1-1.5*P52)) -> 0.0087559644 | S52: ='[2]Moody''s Global Infra and Corp D'!$W$69 -> 9.7071977e-06 | T52: =0.12*(1-EXP(-50*$S52))/(1-EXP(-50))+0.24*(1-(1-EXP(-50*$S52))/(1-EXP(-50))) -> 0.23994177 | U52: =(0.11852-0.05478*LN($S52))^2 -> 0.56373965 | V52: =(S$44*NORMSDIST((1-T52)^(-0.5)*NORMSINV($S52)+(T52/(1-T52))^(0.5)*NORMSINV(0.999))-$S52*S$44)*((1+($B52-2.5)*U52)/(1-1.5*U52)) -> 0.0087559644 | X52: ='[2]Moody''s Global Infra and Corp D'!$W$70 -> 0.0029121593 | Y52: =0.12*(1-EXP(-50*$X52))/(1-EXP(-50))+0.24*(1-(1-EXP(-50*$X52))/(1-EXP(-50))) -> 0.22373959 | Z52: =(0.11852-0.05478*LN($X52))^2 -> 0.19217069 | AA52: =(X$44*NORMSDIST((1-Y52)^(-0.5)*NORMSINV($X52)+(Y52/(1-Y52))^(0.5)*NORMSINV(0.999))-$X52*X$44)*((1+($B52-2.5)*Z52)/(1-1.5*Z52)) -> 0.083826678 | AC52: ='[2]Moody''s Global Infra and Corp D'!$W$71 -> 0.010677917 | AD52: =0.12*(1-EXP(-50*$AC52))/(1-EXP(-50))+0.24*(1-(1-EXP(-50*$AC52))/(1-EXP(-50))) -> 0.19035796 | AE52: =(0.11852-0.05478*LN($AC52))^2 -> 0.13483441 | AF52: =(AC$44*NORMSDIST((1-AD52)^(-0.5)*NORMSINV($AC52)+(AD52/(1-AD52))^(0.5)*NORMSINV(0.999))-$AC52*AC$44)*((1+($B52-2.5)*AE52)/(1-1.5*AE52)) -> 0.12520997 | AH52: ='[2]Moody''s Global Infra and Corp D'!$W$72 -> 0.061155345 | AI52: =0.12*(1-EXP(-50*$AH52))/(1-EXP(-50))+0.24*(1-(1-EXP(-50*$AH52))/(1-EXP(-50))) -> 0.1256391 | AJ52: =(0.11852-0.05478*LN($AH52))^2 -> 0.073763212 | AK52: =(AH$44*NORMSDIST((1-AI52)^(-0.5)*NORMSINV($AH52)+(AI52/(1-AI52))^(0.5)*NORMSINV(0.999))-$AH52*AH$44)*((1+($B52-2.5)*AJ52)/(1-1.5*AJ52)) -> 0.17189302 | AM52: ='[2]Moody''s Global Infra and Corp D'!$W$73 -> 0.18443676 | AN52: =0.12*(1-EXP(-50*$AM52))/(1-EXP(-50))+0.24*(1-(1-EXP(-50*$AM52))/(1-EXP(-50))) -> 0.12001186 | AO52: =(0.11852-0.05478*LN($AM52))^2 -> 0.044572827 | AP52: =(AM$44*NORMSDIST((1-AN52)^(-0.5)*NORMSINV($AM52)+(AN52/(1-AN52))^(0.5)*NORMSINV(0.999))-$AM52*AM$44)*((1+($B52-2.5)*AO52)/(1-1.5*AO52)) -> 0.22175486 | AS52: ='[3]default rates'!$AY$137 -> 0.0016487525 | AT52: =AT51+AS52 -> 0.056133194 | AU52: =0.12*(1-EXP(-50*$AT52))/(1-EXP(-50))+0.24*(1-(1-EXP(-50*$AT52))/(1-EXP(-50))) -> 0.12724877 | AV52: =(0.11852-0.05478*LN($AT52))^2 -> 0.076335021 | AW52: =(AT$44*NORMSDIST((1-AU52)^(-0.5)*NORMSINV($AT52)+(AU52/(1-AU52))^(0.5)*NORMSINV(0.999))-$AT52*AT$44)*((1+($B52-2.5)*AV52)/(1-1.5*AV52)) -> 0.078544725 | AY52: ='[3]default rates'!$BN$315 -> 0.0023759782 | AZ52: =AZ51+AY52 -> 0.042533618 | BA52: =0.12*(1-EXP(-50*$AT52))/(1-EXP(-50))+0.24*(1-(1-EXP(-50*$AT52))/(1-EXP(-50))) -> 0.12724877 | BB52: =(0.11852-0.05478*LN($AT52))^2 -> 0.076335021 | BC52: =(AZ$44*NORMSDIST((1-BA52)^(-0.5)*NORMSINV($AZ52)+(BA52/(1-BA52))^(0.5)*NORMSINV(0.999))-$AZ52*AZ$44)*((1+($B52-2.5)*BB52)/(1-1.5*BB52)) -> 0.052026332 | BE52: ='[3]default rates'!$AY$137 -> 0.0016487525 | BF52: =BF51+BE52 -> 0.056133194 | BG52: =0.12*(1-EXP(-50*$AT52))/(1-EXP(-50))+0.24*(1-(1-EXP(-50*$AT52))/(1-EXP(-50))) -> 0.12724877 | BH52: =(0.11852-0.05478*LN($AT52))^2 -> 0.076335021 | BI52: =(BF$44*NORMSDIST((1-BG52)^(-0.5)*NORMSINV($BF52)+(BG52/(1-BG52))^(0.5)*NORMSINV(0.999))-$BF52*BF$44)*((1+($B52-2.5)*BH52)/(1-1.5*BH52)) -> 0.17707979 | BK52: ='[3]default rates'!$BN$315 -> 0.0023759782 | BL52: =BL51+BK52 -> 0.042533618 | BM52: =0.12*(1-EXP(-50*$AT52))/(1-EXP(-50))+0.24*(1-(1-EXP(-50*$AT52))/(1-EXP(-50))) -> 0.12724877 | BN52: =(0.11852-0.05478*LN($AT52))^2 -> 0.076335021 | BO52: =(BL$44*NORMSDIST((1-BM52)^(-0.5)*NORMSINV($BL52)+(BM52/(1-BM52))^(0.5)*NORMSINV(0.999))-$BL52*BL$44)*((1+($B52-2.5)*BN52)/(1-1.5*BN52)) -> 0.15227136
B53: =$B$17 -> 9 | D53: =Q53*100 -> 0.99597207 | E53: =V53*100 -> 0.99597207 | F53: =AA53*100 -> 9.1658234 | G53: =AF53*100 -> 13.946107 | H53: =AK53*100 -> 18.352248 | I53: =AP53*100 -> 23.159999 | K53: =AW53*100 -> 8.3073339 | N53: ='[2]Moody''s Global Infra and Corp D'!$X$68 -> 9.7071977e-06 | O53: =0.12*(1-EXP(-50*$N53))/(1-EXP(-50))+0.24*(1-(1-EXP(-50*$N53))/(1-EXP(-50))) -> 0.23994177 | P53: =(0.11852-0.05478*LN($N53))^2 -> 0.56373965 | Q53: =(N$44*NORMSDIST((1-O53)^(-0.5)*NORMSINV($N53)+(O53/(1-O53))^(0.5)*NORMSINV(0.999))-$N53*N$44)*((1+($B53-2.5)*P53)/(1-1.5*P53)) -> 0.0099597207 | S53: ='[2]Moody''s Global Infra and Corp D'!$X$69 -> 9.7071977e-06 | T53: =0.12*(1-EXP(-50*$S53))/(1-EXP(-50))+0.24*(1-(1-EXP(-50*$S53))/(1-EXP(-50))) -> 0.23994177 | U53: =(0.11852-0.05478*LN($S53))^2 -> 0.56373965 | V53: =(S$44*NORMSDIST((1-T53)^(-0.5)*NORMSINV($S53)+(T53/(1-T53))^(0.5)*NORMSINV(0.999))-$S53*S$44)*((1+($B53-2.5)*U53)/(1-1.5*U53)) -> 0.0099597207 | X53: ='[2]Moody''s Global Infra and Corp D'!$X$70 -> 0.0029121593 | Y53: =0.12*(1-EXP(-50*$X53))/(1-EXP(-50))+0.24*(1-(1-EXP(-50*$X53))/(1-EXP(-50))) -> 0.22373959 | Z53: =(0.11852-0.05478*LN($X53))^2 -> 0.19217069 | AA53: =(X$44*NORMSDIST((1-Y53)^(-0.5)*NORMSINV($X53)+(Y53/(1-Y53))^(0.5)*NORMSINV(0.999))-$X53*X$44)*((1+($B53-2.5)*Z53)/(1-1.5*Z53)) -> 0.091658234 | AC53: ='[2]Moody''s Global Infra and Corp D'!$X$71 -> 0.012619357 | AD53: =0.12*(1-EXP(-50*$AC53))/(1-EXP(-50))+0.24*(1-(1-EXP(-50*$AC53))/(1-EXP(-50))) -> 0.18384919 | AE53: =(0.11852-0.05478*LN($AC53))^2 -> 0.12819753 | AF53: =(AC$44*NORMSDIST((1-AD53)^(-0.5)*NORMSINV($AC53)+(AD53/(1-AD53))^(0.5)*NORMSINV(0.999))-$AC53*AC$44)*((1+($B53-2.5)*AE53)/(1-1.5*AE53)) -> 0.13946107 | AH53: ='[2]Moody''s Global Infra and Corp D'!$X$72 -> 0.065038224 | AI53: =0.12*(1-EXP(-50*$AH53))/(1-EXP(-50))+0.24*(1-(1-EXP(-50*$AH53))/(1-EXP(-50))) -> 0.12464402 | AJ53: =(0.11852-0.05478*LN($AH53))^2 -> 0.071942877 | AK53: =(AH$44*NORMSDIST((1-AI53)^(-0.5)*NORMSINV($AH53)+(AI53/(1-AI53))^(0.5)*NORMSINV(0.999))-$AH53*AH$44)*((1+($B53-2.5)*AJ53)/(1-1.5*AJ53)) -> 0.18352248 | AM53: ='[2]Moody''s Global Infra and Corp D'!$X$73 -> 0.19996827 | AN53: =0.12*(1-EXP(-50*$AM53))/(1-EXP(-50))+0.24*(1-(1-EXP(-50*$AM53))/(1-EXP(-50))) -> 0.12000546 | AO53: =(0.11852-0.05478*LN($AM53))^2 -> 0.042722286 | AP53: =(AM$44*NORMSDIST((1-AN53)^(-0.5)*NORMSINV($AM53)+(AN53/(1-AN53))^(0.5)*NORMSINV(0.999))-$AM53*AM$44)*((1+($B53-2.5)*AO53)/(1-1.5*AO53)) -> 0.23159999 | AS53: ='[3]default rates'!$AZ$137 -> 0.0009529832 | AT53: =AT52+AS53 -> 0.057086177 | AU53: =0.12*(1-EXP(-50*$AT53))/(1-EXP(-50))+0.24*(1-(1-EXP(-50*$AT53))/(1-EXP(-50))) -> 0.12691147 | AV53: =(0.11852-0.05478*LN($AT53))^2 -> 0.075826284 | AW53: =(AT$44*NORMSDIST((1-AU53)^(-0.5)*NORMSINV($AT53)+(AU53/(1-AU53))^(0.5)*NORMSINV(0.999))-$AT53*AT$44)*((1+($B53-2.5)*AV53)/(1-1.5*AV53)) -> 0.083073339 | AY53: ='[3]default rates'!$BO$315 -> 0.0014665122 | AZ53: =AZ52+AY53 -> 0.04400013 | BA53: =0.12*(1-EXP(-50*$AT53))/(1-EXP(-50))+0.24*(1-(1-EXP(-50*$AT53))/(1-EXP(-50))) -> 0.12691147 | BB53: =(0.11852-0.05478*LN($AT53))^2 -> 0.075826284 | BC53: =(AZ$44*NORMSDIST((1-BA53)^(-0.5)*NORMSINV($AZ53)+(BA53/(1-BA53))^(0.5)*NORMSINV(0.999))-$AZ53*AZ$44)*((1+($B53-2.5)*BB53)/(1-1.5*BB53)) -> 0.055580181 | BE53: ='[3]default rates'!$AZ$137 -> 0.0009529832 | BF53: =BF52+BE53 -> 0.057086177 | BG53: =0.12*(1-EXP(-50*$AT53))/(1-EXP(-50))+0.24*(1-(1-EXP(-50*$AT53))/(1-EXP(-50))) -> 0.12691147 | BH53: =(0.11852-0.05478*LN($AT53))^2 -> 0.075826284 | BI53: =(BF$44*NORMSDIST((1-BG53)^(-0.5)*NORMSINV($BF53)+(BG53/(1-BG53))^(0.5)*NORMSINV(0.999))-$BF53*BF$44)*((1+($B53-2.5)*BH53)/(1-1.5*BH53)) -> 0.18728959 | BK53: ='[3]default rates'!$BO$315 -> 0.0014665122 | BL53: =BL52+BK53 -> 0.04400013 | BM53: =0.12*(1-EXP(-50*$AT53))/(1-EXP(-50))+0.24*(1-(1-EXP(-50*$AT53))/(1-EXP(-50))) -> 0.12691147 | BN53: =(0.11852-0.05478*LN($AT53))^2 -> 0.075826284 | BO53: =(BL$44*NORMSDIST((1-BM53)^(-0.5)*NORMSINV($BL53)+(BM53/(1-BM53))^(0.5)*NORMSINV(0.999))-$BL53*BL$44)*((1+($B53-2.5)*BN53)/(1-1.5*BN53)) -> 0.16267282
B54: =$B$18 -> 10 | D54: =Q54*100 -> 1.1163477 | E54: =V54*100 -> 1.1163477 | F54: =AA54*100 -> 11.005771 | G54: =AF54*100 -> 15.113087 | H54: =AK54*100 -> 19.568261 | I54: =AP54*100 -> 24.036885 | K54: =AW54*100 -> 8.7464146 | N54: ='[2]Moody''s Global Infra and Corp D'!$Y$68 -> 9.7071977e-06 | O54: =0.12*(1-EXP(-50*$N54))/(1-EXP(-50))+0.24*(1-(1-EXP(-50*$N54))/(1-EXP(-50))) -> 0.23994177 | P54: =(0.11852-0.05478*LN($N54))^2 -> 0.56373965 | Q54: =(N$44*NORMSDIST((1-O54)^(-0.5)*NORMSINV($N54)+(O54/(1-O54))^(0.5)*NORMSINV(0.999))-$N54*N$44)*((1+($B54-2.5)*P54)/(1-1.5*P54)) -> 0.011163477 | S54: ='[2]Moody''s Global Infra and Corp D'!$Y$69 -> 9.7071977e-06 | T54: =0.12*(1-EXP(-50*$S54))/(1-EXP(-50))+0.24*(1-(1-EXP(-50*$S54))/(1-EXP(-50))) -> 0.23994177 | U54: =(0.11852-0.05478*LN($S54))^2 -> 0.56373965 | V54: =(S$44*NORMSDIST((1-T54)^(-0.5)*NORMSINV($S54)+(T54/(1-T54))^(0.5)*NORMSINV(0.999))-$S54*S$44)*((1+($B54-2.5)*U54)/(1-1.5*U54)) -> 0.011163477 | X54: ='[2]Moody''s Global Infra and Corp D'!$Y$70 -> 0.0038828791 | Y54: =0.12*(1-EXP(-50*$X54))/(1-EXP(-50))+0.24*(1-(1-EXP(-50*$X54))/(1-EXP(-50))) -> 0.21882472 | Z54: =(0.11852-0.05478*LN($X54))^2 -> 0.17860221 | AA54: =(X$44*NORMSDIST((1-Y54)^(-0.5)*NORMSINV($X54)+(Y54/(1-Y54))^(0.5)*NORMSINV(0.999))-$X54*X$44)*((1+($B54-2.5)*Z54)/(1-1.5*Z54)) -> 0.11005771 | AC54: ='[2]Moody''s Global Infra and Corp D'!$Y$71 -> 0.013590077 | AD54: =0.12*(1-EXP(-50*$AC54))/(1-EXP(-50))+0.24*(1-(1-EXP(-50*$AC54))/(1-EXP(-50))) -> 0.18082421 | AE54: =(0.11852-0.05478*LN($AC54))^2 -> 0.12530693 | AF54: =(AC$44*NORMSDIST((1-AD54)^(-0.5)*NORMSINV($AC54)+(AD54/(1-AD54))^(0.5)*NORMSINV(0.999))-$AC54*AC$44)*((1+($B54-2.5)*AE54)/(1-1.5*AE54)) -> 0.15113087 | AH54: ='[2]Moody''s Global Infra and Corp D'!$Y$72 -> 0.069891823 | AI54: =0.12*(1-EXP(-50*$AH54))/(1-EXP(-50))+0.24*(1-(1-EXP(-50*$AH54))/(1-EXP(-50))) -> 0.12364334 | AJ54: =(0.11852-0.05478*LN($AH54))^2 -> 0.069843383 | AK54: =(AH$44*NORMSDIST((1-AI54)^(-0.5)*NORMSINV($AH54)+(AI54/(1-AI54))^(0.5)*NORMSINV(0.999))-$AH54*AH$44)*((1+($B54-2.5)*AJ54)/(1-1.5*AJ54)) -> 0.19568261 | AM54: ='[2]Moody''s Global Infra and Corp D'!$Y$73 -> 0.21452907 | AN54: =0.12*(1-EXP(-50*$AM54))/(1-EXP(-50))+0.24*(1-(1-EXP(-50*$AM54))/(1-EXP(-50))) -> 0.12000263 | AO54: =(0.11852-0.05478*LN($AM54))^2 -> 0.041145446 | AP54: =(AM$44*NORMSDIST((1-AN54)^(-0.5)*NORMSINV($AM54)+(AN54/(1-AN54))^(0.5)*NORMSINV(0.999))-$AM54*AM$44)*((1+($B54-2.5)*AO54)/(1-1.5*AO54)) -> 0.24036885 | AS54: ='[3]default rates'!$BA$137 -> 0.00054075237 | AT54: =AT53+AS54 -> 0.05762693 | AU54: =0.12*(1-EXP(-50*$AT54))/(1-EXP(-50))+0.24*(1-(1-EXP(-50*$AT54))/(1-EXP(-50))) -> 0.12672711 | AV54: =(0.11852-0.05478*LN($AT54))^2 -> 0.075542117 | AW54: =(AT$44*NORMSDIST((1-AU54)^(-0.5)*NORMSINV($AT54)+(AU54/(1-AU54))^(0.5)*NORMSINV(0.999))-$AT54*AT$44)*((1+($B54-2.5)*AV54)/(1-1.5*AV54)) -> 0.087464146 | AY54: ='[3]default rates'!$BP$315 -> 0.00093985146 | AZ54: =AZ53+AY54 -> 0.044939982 | BA54: =0.12*(1-EXP(-50*$AT54))/(1-EXP(-50))+0.24*(1-(1-EXP(-50*$AT54))/(1-EXP(-50))) -> 0.12672711 | BB54: =(0.11852-0.05478*LN($AT54))^2 -> 0.075542117 | BC54: =(AZ$44*NORMSDIST((1-BA54)^(-0.5)*NORMSINV($AZ54)+(BA54/(1-BA54))^(0.5)*NORMSINV(0.999))-$AZ54*AZ$44)*((1+($B54-2.5)*BB54)/(1-1.5*BB54)) -> 0.058915398 | BE54: ='[3]default rates'!$BA$137 -> 0.00054075237 | BF54: =BF53+BE54 -> 0.05762693 | BG54: =0.12*(1-EXP(-50*$AT54))/(1-EXP(-50))+0.24*(1-(1-EXP(-50*$AT54))/(1-EXP(-50))) -> 0.12672711 | BH54: =(0.11852-0.05478*LN($AT54))^2 -> 0.075542117 | BI54: =(BF$44*NORMSDIST((1-BG54)^(-0.5)*NORMSINV($BF54)+(BG54/(1-BG54))^(0.5)*NORMSINV(0.999))-$BF54*BF$44)*((1+($B54-2.5)*BH54)/(1-1.5*BH54)) -> 0.19718871 | BK54: ='[3]default rates'!$BP$315 -> 0.00093985146 | BL54: =BL53+BK54 -> 0.044939982 | BM54: =0.12*(1-EXP(-50*$AT54))/(1-EXP(-50))+0.24*(1-(1-EXP(-50*$AT54))/(1-EXP(-50))) -> 0.12672711 | BN54: =(0.11852-0.05478*LN($AT54))^2 -> 0.075542117 | BO54: =(BL$44*NORMSDIST((1-BM54)^(-0.5)*NORMSINV($BL54)+(BM54/(1-BM54))^(0.5)*NORMSINV(0.999))-$BL54*BL$44)*((1+($B54-2.5)*BN54)/(1-1.5*BN54)) -> 0.17243438
D56: ='[2]Table - SII - Interim'!D41:R41 -> Infrastructure Investment in EMDEs 5/ | N56: =N$32/AT$32*AT56 -> 0.44813672 | S56: =N56 -> 0.44813672 | X56: =N56 -> 0.44813672 | AC56: =X56 -> 0.44813672 | AH56: =X56 -> 0.44813672 | AM56: =AC56 -> 0.44813672 | AS56: Marginal PD ↓/Recovery → | AT56: =1-'[2]default rates (3)'!CR17/100 -> 0.20898857 | AU56: stdev(rec.) | AV56: ='[2]default rates (3)'!CS17 -> 0.34630561 | AW56: =AV56*(AT56/(1-AT56)) -> 0.09149541 | AY56: Marginal PD ↓/Recovery → | AZ56: =1-'[3]default rates'!$CR$24/100 -> 0.15765 | BA56: stdev(rec.) | BB56: ='[3]default rates'!$CS$24 -> 0.22295077 | BC56: =BB56*(AZ56/(1-AZ56)) -> 0.041726347 | BE56: Marginal PD ↓/Recovery → | BF56: =BF32 -> 0.45 | BG56: stdev(rec.) | BH56: =BF56/AT56*AV56 -> 0.74567487 | BI56: =BH56*(BF56/(1-BF56)) -> 0.61009762 | BK56: Marginal PD ↓/Recovery → | BL56: =BF56 -> 0.45 | BM56: stdev(rec.) | BN56: ='[3]default rates'!$CS$24 -> 0.22295077 | BO56: =BN56*(BL56/(1-BL56)) -> 0.18241426
B57: =$B$9 -> 1 | D57: =Q57*100 -> 0.048736138 | E57: =V57*100 -> 0.048736138 | F57: =AA57*100 -> 0.048736138 | G57: =AF57*100 -> 1.920585 | H57: =AK57*100 -> 4.4836751 | I57: =AP57*100 -> 9.3188221 | K57: =AW57*100 -> 3.7703027 | N57: ='[2]Moody''s Global Infra and Corp D'!$P$75 -> 1.4413195e-05 | O57: =0.12*(1-EXP(-50*$N57))/(1-EXP(-50))+0.24*(1-(1-EXP(-50*$N57))/(1-EXP(-50))) -> 0.23991355 | P57: =(0.11852-0.05478*LN($N57))^2 -> 0.53169288 | Q57: =(N$56*NORMSDIST((1-O57)^(-0.5)*NORMSINV($N57)+(O57/(1-O57))^(0.5)*NORMSINV(0.999))-$N57*N$56)*((1+($B57-2.5)*P57)/(1-1.5*P57)) -> 0.00048736138 | S57: ='[2]Moody''s Global Infra and Corp D'!$P$76 -> 1.4413195e-05 | T57: =0.12*(1-EXP(-50*$S57))/(1-EXP(-50))+0.24*(1-(1-EXP(-50*$S57))/(1-EXP(-50))) -> 0.23991355 | U57: =(0.11852-0.05478*LN($S57))^2 -> 0.53169288 | V57: =(S$56*NORMSDIST((1-T57)^(-0.5)*NORMSINV($S57)+(T57/(1-T57))^(0.5)*NORMSINV(0.999))-$S57*S$56)*((1+($B57-2.5)*U57)/(1-1.5*U57)) -> 0.00048736138 | X57: ='[2]Moody''s Global Infra and Corp D'!$P$77 -> 1.4413195e-05 | Y57: =0.12*(1-EXP(-50*$X57))/(1-EXP(-50))+0.24*(1-(1-EXP(-50*$X57))/(1-EXP(-50))) -> 0.23991355 | Z57: =(0.11852-0.05478*LN($X57))^2 -> 0.53169288 | AA57: =(X$56*NORMSDIST((1-Y57)^(-0.5)*NORMSINV($X57)+(Y57/(1-Y57))^(0.5)*NORMSINV(0.999))-$X57*X$56)*((1+($B57-2.5)*Z57)/(1-1.5*Z57)) -> 0.00048736138 | AC57: ='[2]Moody''s Global Infra and Corp D'!$P$78 -> 0.0014413195 | AD57: =0.12*(1-EXP(-50*$AC57))/(1-EXP(-50))+0.24*(1-(1-EXP(-50*$AC57))/(1-EXP(-50))) -> 0.23165634 | AE57: =(0.11852-0.05478*LN($AC57))^2 -> 0.22743505 | AF57: =(AC$56*NORMSDIST((1-AD57)^(-0.5)*NORMSINV($AC57)+(AD57/(1-AD57))^(0.5)*NORMSINV(0.999))-$AC57*AC$56)*((1+($B57-2.5)*AE57)/(1-1.5*AE57)) -> 0.01920585 | AH57: ='[2]Moody''s Global Infra and Corp D'!$P$79 -> 0.005765278 | AI57: =0.12*(1-EXP(-50*$AH57))/(1-EXP(-50))+0.24*(1-(1-EXP(-50*$AH57))/(1-EXP(-50))) -> 0.20994765 | AJ57: =(0.11852-0.05478*LN($AH57))^2 -> 0.16076917 | AK57: =(AH$56*NORMSDIST((1-AI57)^(-0.5)*NORMSINV($AH57)+(AI57/(1-AI57))^(0.5)*NORMSINV(0.999))-$AH57*AH$56)*((1+($B57-2.5)*AJ57)/(1-1.5*AJ57)) -> 0.044836751 | AM57: ='[2]Moody''s Global Infra and Corp D'!$P$80 -> 0.036032988 | AN57: =0.12*(1-EXP(-50*$AM57))/(1-EXP(-50))+0.24*(1-(1-EXP(-50*$AM57))/(1-EXP(-50))) -> 0.13980318 | AO57: =(0.11852-0.05478*LN($AM57))^2 -> 0.090343223 | AP57: =(AM$56*NORMSDIST((1-AN57)^(-0.5)*NORMSINV($AM57)+(AN57/(1-AN57))^(0.5)*NORMSINV(0.999))-$AM57*AM$56)*((1+($B57-2.5)*AO57)/(1-1.5*AO57)) -> 0.093188221 | AS57: ='[3]default rates'!$AR$143 -> 0.02369795 | AT57: =AS57 -> 0.02369795 | AU57: =0.12*(1-EXP(-50*$AT57))/(1-EXP(-50))+0.24*(1-(1-EXP(-50*$AT57))/(1-EXP(-50))) -> 0.1566933 | AV57: =(0.11852-0.05478*LN($AT57))^2 -> 0.10466962 | AW57: =(AT$56*NORMSDIST((1-AU57)^(-0.5)*NORMSINV($AT57)+(AU57/(1-AU57))^(0.5)*NORMSINV(0.999))-$AT57*AT$56)*((1+($B57-2.5)*AV57)/(1-1.5*AV57)) -> 0.037703027 | AY57: ='[3]default rates'!$BG$327 -> 0.011145167 | AZ57: =AY57 -> 0.011145167 | BA57: =0.12*(1-EXP(-50*$AT57))/(1-EXP(-50))+0.24*(1-(1-EXP(-50*$AT57))/(1-EXP(-50))) -> 0.1566933 | BB57: =(0.11852-0.05478*LN($AT57))^2 -> 0.10466962 | BC57: =(AZ$56*NORMSDIST((1-BA57)^(-0.5)*NORMSINV($AZ57)+(BA57/(1-BA57))^(0.5)*NORMSINV(0.999))-$AZ57*AZ$56)*((1+($B57-2.5)*BB57)/(1-1.5*BB57)) -> 0.017746924 | BE57: ='[3]default rates'!$AR$143 -> 0.02369795 | BF57: =BE57 -> 0.02369795 | BG57: =0.12*(1-EXP(-50*$AT57))/(1-EXP(-50))+0.24*(1-(1-EXP(-50*$AT57))/(1-EXP(-50))) -> 0.1566933 | BH57: =(0.11852-0.05478*LN($AT57))^2 -> 0.10466962 | BI57: =(BF$56*NORMSDIST((1-BG57)^(-0.5)*NORMSINV($BF57)+(BG57/(1-BG57))^(0.5)*NORMSINV(0.999))-$BF57*BF$56)*((1+($B57-2.5)*BH57)/(1-1.5*BH57)) -> 0.081183207 | BK57: ='[3]default rates'!$BG$327 -> 0.011145167 | BL57: =BK57 -> 0.011145167 | BM57: =0.12*(1-EXP(-50*$AT57))/(1-EXP(-50))+0.24*(1-(1-EXP(-50*$AT57))/(1-EXP(-50))) -> 0.1566933 | BN57: =(0.11852-0.05478*LN($AT57))^2 -> 0.10466962 | BO57: =(BL$56*NORMSDIST((1-BM57)^(-0.5)*NORMSINV($BL57)+(BM57/(1-BM57))^(0.5)*NORMSINV(0.999))-$BL57*BL$56)*((1+($B57-2.5)*BN57)/(1-1.5*BN57)) -> 0.050657251
B58: =$B$10 -> 2 | D58: =Q58*100 -> 0.17672473 | E58: =V58*100 -> 0.17672473 | F58: =AA58*100 -> 0.17672473 | G58: =AF58*100 -> 3.8358303 | H58: =AK58*100 -> 8.4747121 | I58: =AP58*100 -> 13.532131 | K58: =AW58*100 -> 5.2104341 | N58: ='[2]Moody''s Global Infra and Corp D'!$Q$75 -> 1.4413195e-05 | O58: =0.12*(1-EXP(-50*$N58))/(1-EXP(-50))+0.24*(1-(1-EXP(-50*$N58))/(1-EXP(-50))) -> 0.23991355 | P58: =(0.11852-0.05478*LN($N58))^2 -> 0.53169288 | Q58: =(N$56*NORMSDIST((1-O58)^(-0.5)*NORMSINV($N58)+(O58/(1-O58))^(0.5)*NORMSINV(0.999))-$N58*N$56)*((1+($B58-2.5)*P58)/(1-1.5*P58)) -> 0.0017672473 | S58: ='[2]Moody''s Global Infra and Corp D'!$Q$76 -> 1.4413195e-05 | T58: =0.12*(1-EXP(-50*$N58))/(1-EXP(-50))+0.24*(1-(1-EXP(-50*$N58))/(1-EXP(-50))) -> 0.23991355 | U58: =(0.11852-0.05478*LN($N58))^2 -> 0.53169288 | V58: =(S$56*NORMSDIST((1-T58)^(-0.5)*NORMSINV($S58)+(T58/(1-T58))^(0.5)*NORMSINV(0.999))-$S58*S$56)*((1+($B58-2.5)*U58)/(1-1.5*U58)) -> 0.0017672473 | X58: ='[2]Moody''s Global Infra and Corp D'!$Q$77 -> 1.4413195e-05 | Y58: =0.12*(1-EXP(-50*$X58))/(1-EXP(-50))+0.24*(1-(1-EXP(-50*$X58))/(1-EXP(-50))) -> 0.23991355 | Z58: =(0.11852-0.05478*LN($X58))^2 -> 0.53169288 | AA58: =(X$56*NORMSDIST((1-Y58)^(-0.5)*NORMSINV($X58)+(Y58/(1-Y58))^(0.5)*NORMSINV(0.999))-$X58*X$56)*((1+($B58-2.5)*Z58)/(1-1.5*Z58)) -> 0.0017672473 | AC58: ='[2]Moody''s Global Infra and Corp D'!$Q$78 -> 0.002882639 | AD58: =0.12*(1-EXP(-50*$AC58))/(1-EXP(-50))+0.24*(1-(1-EXP(-50*$AC58))/(1-EXP(-50))) -> 0.22389282 | AE58: =(0.11852-0.05478*LN($AC58))^2 -> 0.19266034 | AF58: =(AC$56*NORMSDIST((1-AD58)^(-0.5)*NORMSINV($AC58)+(AD58/(1-AD58))^(0.5)*NORMSINV(0.999))-$AC58*AC$56)*((1+($B58-2.5)*AE58)/(1-1.5*AE58)) -> 0.038358303 | AH58: ='[2]Moody''s Global Infra and Corp D'!$Q$79 -> 0.018737154 | AI58: =0.12*(1-EXP(-50*$AH58))/(1-EXP(-50))+0.24*(1-(1-EXP(-50*$AH58))/(1-EXP(-50))) -> 0.16702287 | AJ58: =(0.11852-0.05478*LN($AH58))^2 -> 0.11316064 | AK58: =(AH$56*NORMSDIST((1-AI58)^(-0.5)*NORMSINV($AH58)+(AI58/(1-AI58))^(0.5)*NORMSINV(0.999))-$AH58*AH$56)*((1+($B58-2.5)*AJ58)/(1-1.5*AJ58)) -> 0.084747121 | AM58: ='[2]Moody''s Global Infra and Corp D'!$Q$80 -> 0.077831253 | AN58: =0.12*(1-EXP(-50*$AM58))/(1-EXP(-50))+0.24*(1-(1-EXP(-50*$AM58))/(1-EXP(-50))) -> 0.12244961 | AO58: =(0.11852-0.05478*LN($AM58))^2 -> 0.06676279 | AP58: =(AM$56*NORMSDIST((1-AN58)^(-0.5)*NORMSINV($AM58)+(AN58/(1-AN58))^(0.5)*NORMSINV(0.999))-$AM58*AM$56)*((1+($B58-2.5)*AO58)/(1-1.5*AO58)) -> 0.13532131 | AS58: ='[3]default rates'!$AS$143 -> 0.022731383 | AT58: =AT57+AS58 -> 0.046429333 | AU58: =0.12*(1-EXP(-50*$AT58))/(1-EXP(-50))+0.24*(1-(1-EXP(-50*$AT58))/(1-EXP(-50))) -> 0.13177555 | AV58: =(0.11852-0.05478*LN($AT58))^2 -> 0.08218826 | AW58: =(AT$56*NORMSDIST((1-AU58)^(-0.5)*NORMSINV($AT58)+(AU58/(1-AU58))^(0.5)*NORMSINV(0.999))-$AT58*AT$56)*((1+($B58-2.5)*AV58)/(1-1.5*AV58)) -> 0.052104341 | AY58: ='[3]default rates'!$BH$327 -> 0.012095615 | AZ58: =AZ57+AY58 -> 0.023240782 | BA58: =0.12*(1-EXP(-50*$AT58))/(1-EXP(-50))+0.24*(1-(1-EXP(-50*$AT58))/(1-EXP(-50))) -> 0.13177555 | BB58: =(0.11852-0.05478*LN($AT58))^2 -> 0.08218826 | BC58: =(AZ$56*NORMSDIST((1-BA58)^(-0.5)*NORMSINV($AZ58)+(BA58/(1-BA58))^(0.5)*NORMSINV(0.999))-$AZ58*AZ$56)*((1+($B58-2.5)*BB58)/(1-1.5*BB58)) -> 0.026245274 | BE58: ='[3]default rates'!$AS$143 -> 0.022731383 | BF58: =BF57+BE58 -> 0.046429333 | BG58: =0.12*(1-EXP(-50*$AT58))/(1-EXP(-50))+0.24*(1-(1-EXP(-50*$AT58))/(1-EXP(-50))) -> 0.13177555 | BH58: =(0.11852-0.05478*LN($AT58))^2 -> 0.08218826 | BI58: =(BF$56*NORMSDIST((1-BG58)^(-0.5)*NORMSINV($BF58)+(BG58/(1-BG58))^(0.5)*NORMSINV(0.999))-$BF58*BF$56)*((1+($B58-2.5)*BH58)/(1-1.5*BH58)) -> 0.11219252 | BK58: ='[3]default rates'!$BH$327 -> 0.012095615 | BL58: =BL57+BK58 -> 0.023240782 | BM58: =0.12*(1-EXP(-50*$AT58))/(1-EXP(-50))+0.24*(1-(1-EXP(-50*$AT58))/(1-EXP(-50))) -> 0.13177555 | BN58: =(0.11852-0.05478*LN($AT58))^2 -> 0.08218826 | BO58: =(BL$56*NORMSDIST((1-BM58)^(-0.5)*NORMSINV($BL58)+(BM58/(1-BM58))^(0.5)*NORMSINV(0.999))-$BL58*BL$56)*((1+($B58-2.5)*BN58)/(1-1.5*BN58)) -> 0.074915149
B59: =$B$11 -> 3 | D59: =Q59*100 -> 0.30471331 | E59: =V59*100 -> 0.30471331 | F59: =AA59*100 -> 3.2465623 | G59: =AF59*100 -> 6.3834979 | H59: =AK59*100 -> 11.013659 | I59: =AP59*100 -> 17.121375 | K59: =AW59*100 -> 6.2397328 | N59: ='[2]Moody''s Global Infra and Corp D'!$R$75 -> 1.4413195e-05 | O59: =0.12*(1-EXP(-50*$N59))/(1-EXP(-50))+0.24*(1-(1-EXP(-50*$N59))/(1-EXP(-50))) -> 0.23991355 | P59: =(0.11852-0.05478*LN($N59))^2 -> 0.53169288 | Q59: =(N$56*NORMSDIST((1-O59)^(-0.5)*NORMSINV($N59)+(O59/(1-O59))^(0.5)*NORMSINV(0.999))-$N59*N$56)*((1+($B59-2.5)*P59)/(1-1.5*P59)) -> 0.0030471331 | S59: ='[2]Moody''s Global Infra and Corp D'!$R$76 -> 1.4413195e-05 | T59: =0.12*(1-EXP(-50*$N59))/(1-EXP(-50))+0.24*(1-(1-EXP(-50*$N59))/(1-EXP(-50))) -> 0.23991355 | U59: =(0.11852-0.05478*LN($N59))^2 -> 0.53169288 | V59: =(S$56*NORMSDIST((1-T59)^(-0.5)*NORMSINV($S59)+(T59/(1-T59))^(0.5)*NORMSINV(0.999))-$S59*S$56)*((1+($B59-2.5)*U59)/(1-1.5*U59)) -> 0.0030471331 | X59: ='[2]Moody''s Global Infra and Corp D'!$R$77 -> 0.0014413195 | Y59: =0.12*(1-EXP(-50*$X59))/(1-EXP(-50))+0.24*(1-(1-EXP(-50*$X59))/(1-EXP(-50))) -> 0.23165634 | Z59: =(0.11852-0.05478*LN($X59))^2 -> 0.22743505 | AA59: =(X$56*NORMSDIST((1-Y59)^(-0.5)*NORMSINV($X59)+(Y59/(1-Y59))^(0.5)*NORMSINV(0.999))-$X59*X$56)*((1+($B59-2.5)*Z59)/(1-1.5*Z59)) -> 0.032465623 | AC59: ='[2]Moody''s Global Infra and Corp D'!$R$78 -> 0.005765278 | AD59: =0.12*(1-EXP(-50*$AC59))/(1-EXP(-50))+0.24*(1-(1-EXP(-50*$AC59))/(1-EXP(-50))) -> 0.20994765 | AE59: =(0.11852-0.05478*LN($AC59))^2 -> 0.16076917 | AF59: =(AC$56*NORMSDIST((1-AD59)^(-0.5)*NORMSINV($AC59)+(AD59/(1-AD59))^(0.5)*NORMSINV(0.999))-$AC59*AC$56)*((1+($B59-2.5)*AE59)/(1-1.5*AE59)) -> 0.063834979 | AH59: ='[2]Moody''s Global Infra and Corp D'!$R$79 -> 0.033150349 | AI59: =0.12*(1-EXP(-50*$AH59))/(1-EXP(-50))+0.24*(1-(1-EXP(-50*$AH59))/(1-EXP(-50))) -> 0.14287339 | AJ59: =(0.11852-0.05478*LN($AH59))^2 -> 0.093109894 | AK59: =(AH$56*NORMSDIST((1-AI59)^(-0.5)*NORMSINV($AH59)+(AI59/(1-AI59))^(0.5)*NORMSINV(0.999))-$AH59*AH$56)*((1+($B59-2.5)*AJ59)/(1-1.5*AJ59)) -> 0.11013659 | AM59: ='[2]Moody''s Global Infra and Corp D'!$R$80 -> 0.1253948 | AN59: =0.12*(1-EXP(-50*$AM59))/(1-EXP(-50))+0.24*(1-(1-EXP(-50*$AM59))/(1-EXP(-50))) -> 0.12022713 | AO59: =(0.11852-0.05478*LN($AM59))^2 -> 0.053944273 | AP59: =(AM$56*NORMSDIST((1-AN59)^(-0.5)*NORMSINV($AM59)+(AN59/(1-AN59))^(0.5)*NORMSINV(0.999))-$AM59*AM$56)*((1+($B59-2.5)*AO59)/(1-1.5*AO59)) -> 0.17121375 | AS59: ='[3]default rates'!$AT$143 -> 0.016121094 | AT59: =AT58+AS59 -> 0.062550427 | AU59: =0.12*(1-EXP(-50*$AT59))/(1-EXP(-50))+0.24*(1-(1-EXP(-50*$AT59))/(1-EXP(-50))) -> 0.12525916 | AV59: =(0.11852-0.05478*LN($AT59))^2 -> 0.073093572 | AW59: =(AT$56*NORMSDIST((1-AU59)^(-0.5)*NORMSINV($AT59)+(AU59/(1-AU59))^(0.5)*NORMSINV(0.999))-$AT59*AT$56)*((1+($B59-2.5)*AV59)/(1-1.5*AV59)) -> 0.062397328 | AY59: ='[3]default rates'!$BI$327 -> 0.013010114 | AZ59: =AZ58+AY59 -> 0.036250896 | BA59: =0.12*(1-EXP(-50*$AT59))/(1-EXP(-50))+0.24*(1-(1-EXP(-50*$AT59))/(1-EXP(-50))) -> 0.12525916 | BB59: =(0.11852-0.05478*LN($AT59))^2 -> 0.073093572 | BC59: =(AZ$56*NORMSDIST((1-BA59)^(-0.5)*NORMSINV($AZ59)+(BA59/(1-BA59))^(0.5)*NORMSINV(0.999))-$AZ59*AZ$56)*((1+($B59-2.5)*BB59)/(1-1.5*BB59)) -> 0.034893169 | BE59: ='[3]default rates'!$AT$143 -> 0.016121094 | BF59: =BF58+BE59 -> 0.062550427 | BG59: =0.12*(1-EXP(-50*$AT59))/(1-EXP(-50))+0.24*(1-(1-EXP(-50*$AT59))/(1-EXP(-50))) -> 0.12525916 | BH59: =(0.11852-0.05478*LN($AT59))^2 -> 0.073093572 | BI59: =(BF$56*NORMSDIST((1-BG59)^(-0.5)*NORMSINV($BF59)+(BG59/(1-BG59))^(0.5)*NORMSINV(0.999))-$BF59*BF$56)*((1+($B59-2.5)*BH59)/(1-1.5*BH59)) -> 0.13435566 | BK59: ='[3]default rates'!$BI$327 -> 0.013010114 | BL59: =BL58+BK59 -> 0.036250896 | BM59: =0.12*(1-EXP(-50*$AT59))/(1-EXP(-50))+0.24*(1-(1-EXP(-50*$AT59))/(1-EXP(-50))) -> 0.12525916 | BN59: =(0.11852-0.05478*LN($AT59))^2 -> 0.073093572 | BO59: =(BL$56*NORMSDIST((1-BM59)^(-0.5)*NORMSINV($BL59)+(BM59/(1-BM59))^(0.5)*NORMSINV(0.999))-$BL59*BL$56)*((1+($B59-2.5)*BN59)/(1-1.5*BN59)) -> 0.099599911
B60: =$B$12 -> 4 | D60: =Q60*100 -> 0.4327019 | E60: =V60*100 -> 0.4327019 | F60: =AA60*100 -> 3.9095509 | G60: =AF60*100 -> 7.9608457 | H60: =AK60*100 -> 13.404 | I60: =AP60*100 -> 19.436259 | K60: =AW60*100 -> 7.0260618 | N60: ='[2]Moody''s Global Infra and Corp D'!$S$75 -> 1.4413195e-05 | O60: =0.12*(1-EXP(-50*$N60))/(1-EXP(-50))+0.24*(1-(1-EXP(-50*$N60))/(1-EXP(-50))) -> 0.23991355 | P60: =(0.11852-0.05478*LN($N60))^2 -> 0.53169288 | Q60: =(N$56*NORMSDIST((1-O60)^(-0.5)*NORMSINV($N60)+(O60/(1-O60))^(0.5)*NORMSINV(0.999))-$N60*N$56)*((1+($B60-2.5)*P60)/(1-1.5*P60)) -> 0.004327019 | S60: ='[2]Moody''s Global Infra and Corp D'!$S$76 -> 1.4413195e-05 | T60: =0.12*(1-EXP(-50*$N60))/(1-EXP(-50))+0.24*(1-(1-EXP(-50*$N60))/(1-EXP(-50))) -> 0.23991355 | U60: =(0.11852-0.05478*LN($N60))^2 -> 0.53169288 | V60: =(S$56*NORMSDIST((1-T60)^(-0.5)*NORMSINV($S60)+(T60/(1-T60))^(0.5)*NORMSINV(0.999))-$S60*S$56)*((1+($B60-2.5)*U60)/(1-1.5*U60)) -> 0.004327019 | X60: ='[2]Moody''s Global Infra and Corp D'!$S$77 -> 0.0014413195 | Y60: =0.12*(1-EXP(-50*$X60))/(1-EXP(-50))+0.24*(1-(1-EXP(-50*$X60))/(1-EXP(-50))) -> 0.23165634 | Z60: =(0.11852-0.05478*LN($X60))^2 -> 0.22743505 | AA60: =(X$56*NORMSDIST((1-Y60)^(-0.5)*NORMSINV($X60)+(Y60/(1-Y60))^(0.5)*NORMSINV(0.999))-$X60*X$56)*((1+($B60-2.5)*Z60)/(1-1.5*Z60)) -> 0.039095509 | AC60: ='[2]Moody''s Global Infra and Corp D'!$S$78 -> 0.0072065975 | AD60: =0.12*(1-EXP(-50*$AC60))/(1-EXP(-50))+0.24*(1-(1-EXP(-50*$AC60))/(1-EXP(-50))) -> 0.20369355 | AE60: =(0.11852-0.05478*LN($AC60))^2 -> 0.15111607 | AF60: =(AC$56*NORMSDIST((1-AD60)^(-0.5)*NORMSINV($AC60)+(AD60/(1-AD60))^(0.5)*NORMSINV(0.999))-$AC60*AC$56)*((1+($B60-2.5)*AE60)/(1-1.5*AE60)) -> 0.079608457 | AH60: ='[2]Moody''s Global Infra and Corp D'!$S$79 -> 0.050446183 | AI60: =0.12*(1-EXP(-50*$AH60))/(1-EXP(-50))+0.24*(1-(1-EXP(-50*$AH60))/(1-EXP(-50))) -> 0.12963288 | AJ60: =(0.11852-0.05478*LN($AH60))^2 -> 0.079602723 | AK60: =(AH$56*NORMSDIST((1-AI60)^(-0.5)*NORMSINV($AH60)+(AI60/(1-AI60))^(0.5)*NORMSINV(0.999))-$AH60*AH$56)*((1+($B60-2.5)*AJ60)/(1-1.5*AJ60)) -> 0.13404 | AM60: ='[2]Moody''s Global Infra and Corp D'!$S$80 -> 0.16575174 | AN60: =0.12*(1-EXP(-50*$AM60))/(1-EXP(-50))+0.24*(1-(1-EXP(-50*$AM60))/(1-EXP(-50))) -> 0.12003019 | AO60: =(0.11852-0.05478*LN($AM60))^2 -> 0.047077773 | AP60: =(AM$56*NORMSDIST((1-AN60)^(-0.5)*NORMSINV($AM60)+(AN60/(1-AN60))^(0.5)*NORMSINV(0.999))-$AM60*AM$56)*((1+($B60-2.5)*AO60)/(1-1.5*AO60)) -> 0.19436259 | AS60: ='[3]default rates'!$AU$143 -> 0.010365535 | AT60: =AT59+AS60 -> 0.072915963 | AU60: =0.12*(1-EXP(-50*$AT60))/(1-EXP(-50))+0.24*(1-(1-EXP(-50*$AT60))/(1-EXP(-50))) -> 0.12313207 | AV60: =(0.11852-0.05478*LN($AT60))^2 -> 0.06862229 | AW60: =(AT$56*NORMSDIST((1-AU60)^(-0.5)*NORMSINV($AT60)+(AU60/(1-AU60))^(0.5)*NORMSINV(0.999))-$AT60*AT$56)*((1+($B60-2.5)*AV60)/(1-1.5*AV60)) -> 0.070260618 | AY60: ='[3]default rates'!$BJ$327 -> 0.010490023 | AZ60: =AZ59+AY60 -> 0.046740919 | BA60: =0.12*(1-EXP(-50*$AT60))/(1-EXP(-50))+0.24*(1-(1-EXP(-50*$AT60))/(1-EXP(-50))) -> 0.12313207 | BB60: =(0.11852-0.05478*LN($AT60))^2 -> 0.06862229 | BC60: =(AZ$56*NORMSDIST((1-BA60)^(-0.5)*NORMSINV($AZ60)+(BA60/(1-BA60))^(0.5)*NORMSINV(0.999))-$AZ60*AZ$56)*((1+($B60-2.5)*BB60)/(1-1.5*BB60)) -> 0.041975312 | BE60: ='[3]default rates'!$AU$143 -> 0.010365535 | BF60: =BF59+BE60 -> 0.072915963 | BG60: =0.12*(1-EXP(-50*$AT60))/(1-EXP(-50))+0.24*(1-(1-EXP(-50*$AT60))/(1-EXP(-50))) -> 0.12313207 | BH60: =(0.11852-0.05478*LN($AT60))^2 -> 0.06862229 | BI60: =(BF$56*NORMSDIST((1-BG60)^(-0.5)*NORMSINV($BF60)+(BG60/(1-BG60))^(0.5)*NORMSINV(0.999))-$BF60*BF$56)*((1+($B60-2.5)*BH60)/(1-1.5*BH60)) -> 0.15128712 | BK60: ='[3]default rates'!$BJ$327 -> 0.010490023 | BL60: =BL59+BK60 -> 0.046740919 | BM60: =0.12*(1-EXP(-50*$AT60))/(1-EXP(-50))+0.24*(1-(1-EXP(-50*$AT60))/(1-EXP(-50))) -> 0.12313207 | BN60: =(0.11852-0.05478*LN($AT60))^2 -> 0.06862229 | BO60: =(BL$56*NORMSDIST((1-BM60)^(-0.5)*NORMSINV($BL60)+(BM60/(1-BM60))^(0.5)*NORMSINV(0.999))-$BL60*BL$56)*((1+($B60-2.5)*BN60)/(1-1.5*BN60)) -> 0.11981535
B61: =$B$13 -> 5 | D61: =Q61*100 -> 0.56069049 | E61: =V61*100 -> 0.56069049 | F61: =AA61*100 -> 6.2892011 | G61: =AF61*100 -> 9.9075435 | H61: =AK61*100 -> 15.64143 | I61: =AP61*100 -> 21.012031 | K61: =AW61*100 -> 7.6880724 | N61: ='[2]Moody''s Global Infra and Corp D'!$T$75 -> 1.4413195e-05 | O61: =0.12*(1-EXP(-50*$N61))/(1-EXP(-50))+0.24*(1-(1-EXP(-50*$N61))/(1-EXP(-50))) -> 0.23991355 | P61: =(0.11852-0.05478*LN($N61))^2 -> 0.53169288 | Q61: =(N$56*NORMSDIST((1-O61)^(-0.5)*NORMSINV($N61)+(O61/(1-O61))^(0.5)*NORMSINV(0.999))-$N61*N$56)*((1+($B61-2.5)*P61)/(1-1.5*P61)) -> 0.0056069049 | S61: ='[2]Moody''s Global Infra and Corp D'!$T$76 -> 1.4413195e-05 | T61: =0.12*(1-EXP(-50*$N61))/(1-EXP(-50))+0.24*(1-(1-EXP(-50*$N61))/(1-EXP(-50))) -> 0.23991355 | U61: =(0.11852-0.05478*LN($N61))^2 -> 0.53169288 | V61: =(S$56*NORMSDIST((1-T61)^(-0.5)*NORMSINV($S61)+(T61/(1-T61))^(0.5)*NORMSINV(0.999))-$S61*S$56)*((1+($B61-2.5)*U61)/(1-1.5*U61)) -> 0.0056069049 | X61: ='[2]Moody''s Global Infra and Corp D'!$T$77 -> 0.002882639 | Y61: =0.12*(1-EXP(-50*$X61))/(1-EXP(-50))+0.24*(1-(1-EXP(-50*$X61))/(1-EXP(-50))) -> 0.22389282 | Z61: =(0.11852-0.05478*LN($X61))^2 -> 0.19266034 | AA61: =(X$56*NORMSDIST((1-Y61)^(-0.5)*NORMSINV($X61)+(Y61/(1-Y61))^(0.5)*NORMSINV(0.999))-$X61*X$56)*((1+($B61-2.5)*Z61)/(1-1.5*Z61)) -> 0.062892011 | AC61: ='[2]Moody''s Global Infra and Corp D'!$T$78 -> 0.010089237 | AD61: =0.12*(1-EXP(-50*$AC61))/(1-EXP(-50))+0.24*(1-(1-EXP(-50*$AC61))/(1-EXP(-50))) -> 0.19245965 | AE61: =(0.11852-0.05478*LN($AC61))^2 -> 0.13712546 | AF61: =(AC$56*NORMSDIST((1-AD61)^(-0.5)*NORMSINV($AC61)+(AD61/(1-AD61))^(0.5)*NORMSINV(0.999))-$AC61*AC$56)*((1+($B61-2.5)*AE61)/(1-1.5*AE61)) -> 0.099075435 | AH61: ='[2]Moody''s Global Infra and Corp D'!$T$79 -> 0.067742017 | AI61: =0.12*(1-EXP(-50*$AH61))/(1-EXP(-50))+0.24*(1-(1-EXP(-50*$AH61))/(1-EXP(-50))) -> 0.12405679 | AJ61: =(0.11852-0.05478*LN($AH61))^2 -> 0.070750906 | AK61: =(AH$56*NORMSDIST((1-AI61)^(-0.5)*NORMSINV($AH61)+(AI61/(1-AI61))^(0.5)*NORMSINV(0.999))-$AH61*AH$56)*((1+($B61-2.5)*AJ61)/(1-1.5*AJ61)) -> 0.1564143 | AM61: ='[2]Moody''s Global Infra and Corp D'!$T$80 -> 0.20034341 | AN61: =0.12*(1-EXP(-50*$AM61))/(1-EXP(-50))+0.24*(1-(1-EXP(-50*$AM61))/(1-EXP(-50))) -> 0.12000536 | AO61: =(0.11852-0.05478*LN($AM61))^2 -> 0.042679853 | AP61: =(AM$56*NORMSDIST((1-AN61)^(-0.5)*NORMSINV($AM61)+(AN61/(1-AN61))^(0.5)*NORMSINV(0.999))-$AM61*AM$56)*((1+($B61-2.5)*AO61)/(1-1.5*AO61)) -> 0.21012031 | AS61: ='[3]default rates'!$AV$143 -> 0.0071835897 | AT61: =AT60+AS61 -> 0.080099553 | AU61: =0.12*(1-EXP(-50*$AT61))/(1-EXP(-50))+0.24*(1-(1-EXP(-50*$AT61))/(1-EXP(-50))) -> 0.12218696 | AV61: =(0.11852-0.05478*LN($AT61))^2 -> 0.065952038 | AW61: =(AT$56*NORMSDIST((1-AU61)^(-0.5)*NORMSINV($AT61)+(AU61/(1-AU61))^(0.5)*NORMSINV(0.999))-$AT61*AT$56)*((1+($B61-2.5)*AV61)/(1-1.5*AV61)) -> 0.076880724 | AY61: ='[3]default rates'!$BK$327 -> 0.0074488674 | AZ61: =AZ60+AY61 -> 0.054189787 | BA61: =0.12*(1-EXP(-50*$AT61))/(1-EXP(-50))+0.24*(1-(1-EXP(-50*$AT61))/(1-EXP(-50))) -> 0.12218696 | BB61: =(0.11852-0.05478*LN($AT61))^2 -> 0.065952038 | BC61: =(AZ$56*NORMSDIST((1-BA61)^(-0.5)*NORMSINV($AZ61)+(BA61/(1-BA61))^(0.5)*NORMSINV(0.999))-$AZ61*AZ$56)*((1+($B61-2.5)*BB61)/(1-1.5*BB61)) -> 0.047550723 | BE61: ='[3]default rates'!$AV$143 -> 0.0071835897 | BF61: =BF60+BE61 -> 0.080099553 | BG61: =0.12*(1-EXP(-50*$AT61))/(1-EXP(-50))+0.24*(1-(1-EXP(-50*$AT61))/(1-EXP(-50))) -> 0.12218696 | BH61: =(0.11852-0.05478*LN($AT61))^2 -> 0.065952038 | BI61: =(BF$56*NORMSDIST((1-BG61)^(-0.5)*NORMSINV($BF61)+(BG61/(1-BG61))^(0.5)*NORMSINV(0.999))-$BF61*BF$56)*((1+($B61-2.5)*BH61)/(1-1.5*BH61)) -> 0.16554171 | BK61: ='[3]default rates'!$BK$327 -> 0.0074488674 | BL61: =BL60+BK61 -> 0.054189787 | BM61: =0.12*(1-EXP(-50*$AT61))/(1-EXP(-50))+0.24*(1-(1-EXP(-50*$AT61))/(1-EXP(-50))) -> 0.12218696 | BN61: =(0.11852-0.05478*LN($AT61))^2 -> 0.065952038 | BO61: =(BL$56*NORMSDIST((1-BM61)^(-0.5)*NORMSINV($BL61)+(BM61/(1-BM61))^(0.5)*NORMSINV(0.999))-$BL61*BL$56)*((1+($B61-2.5)*BN61)/(1-1.5*BN61)) -> 0.13572994
B62: =$B$14 -> 6 | D62: =Q62*100 -> 0.68867908 | E62: =V62*100 -> 0.68867908 | F62: =AA62*100 -> 7.1069914 | G62: =AF62*100 -> 11.293752 | H62: =AK62*100 -> 17.365224 | I62: =AP62*100 -> 22.113923 | K62: =AW62*100 -> 8.2162892 | N62: ='[2]Moody''s Global Infra and Corp D'!$U$75 -> 1.4413195e-05 | O62: =0.12*(1-EXP(-50*$N62))/(1-EXP(-50))+0.24*(1-(1-EXP(-50*$N62))/(1-EXP(-50))) -> 0.23991355 | P62: =(0.11852-0.05478*LN($N62))^2 -> 0.53169288 | Q62: =(N$56*NORMSDIST((1-O62)^(-0.5)*NORMSINV($N62)+(O62/(1-O62))^(0.5)*NORMSINV(0.999))-$N62*N$56)*((1+($B62-2.5)*P62)/(1-1.5*P62)) -> 0.0068867908 | S62: ='[2]Moody''s Global Infra and Corp D'!$U$76 -> 1.4413195e-05 | T62: =0.12*(1-EXP(-50*$N62))/(1-EXP(-50))+0.24*(1-(1-EXP(-50*$N62))/(1-EXP(-50))) -> 0.23991355 | U62: =(0.11852-0.05478*LN($N62))^2 -> 0.53169288 | V62: =(S$56*NORMSDIST((1-T62)^(-0.5)*NORMSINV($S62)+(T62/(1-T62))^(0.5)*NORMSINV(0.999))-$S62*S$56)*((1+($B62-2.5)*U62)/(1-1.5*U62)) -> 0.0068867908 | X62: ='[2]Moody''s Global Infra and Corp D'!$U$77 -> 0.002882639 | Y62: =0.12*(1-EXP(-50*$X62))/(1-EXP(-50))+0.24*(1-(1-EXP(-50*$X62))/(1-EXP(-50))) -> 0.22389282 | Z62: =(0.11852-0.05478*LN($X62))^2 -> 0.19266034 | AA62: =(X$56*NORMSDIST((1-Y62)^(-0.5)*NORMSINV($X62)+(Y62/(1-Y62))^(0.5)*NORMSINV(0.999))-$X62*X$56)*((1+($B62-2.5)*Z62)/(1-1.5*Z62)) -> 0.071069914 | AC62: ='[2]Moody''s Global Infra and Corp D'!$U$78 -> 0.011530556 | AD62: =0.12*(1-EXP(-50*$AC62))/(1-EXP(-50))+0.24*(1-(1-EXP(-50*$AC62))/(1-EXP(-50))) -> 0.1874215 | AE62: =(0.11852-0.05478*LN($AC62))^2 -> 0.13176152 | AF62: =(AC$56*NORMSDIST((1-AD62)^(-0.5)*NORMSINV($AC62)+(AD62/(1-AD62))^(0.5)*NORMSINV(0.999))-$AC62*AC$56)*((1+($B62-2.5)*AE62)/(1-1.5*AE62)) -> 0.11293752 | AH62: ='[2]Moody''s Global Infra and Corp D'!$U$79 -> 0.079272573 | AI62: =0.12*(1-EXP(-50*$AH62))/(1-EXP(-50))+0.24*(1-(1-EXP(-50*$AH62))/(1-EXP(-50))) -> 0.12227929 | AJ62: =(0.11852-0.05478*LN($AH62))^2 -> 0.066244361 | AK62: =(AH$56*NORMSDIST((1-AI62)^(-0.5)*NORMSINV($AH62)+(AI62/(1-AI62))^(0.5)*NORMSINV(0.999))-$AH62*AH$56)*((1+($B62-2.5)*AJ62)/(1-1.5*AJ62)) -> 0.17365224 | AM62: ='[2]Moody''s Global Infra and Corp D'!$U$80 -> 0.22628716 | AN62: =0.12*(1-EXP(-50*$AM62))/(1-EXP(-50))+0.24*(1-(1-EXP(-50*$AM62))/(1-EXP(-50))) -> 0.12000146 | AO62: =(0.11852-0.05478*LN($AM62))^2 -> 0.039968153 | AP62: =(AM$56*NORMSDIST((1-AN62)^(-0.5)*NORMSINV($AM62)+(AN62/(1-AN62))^(0.5)*NORMSINV(0.999))-$AM62*AM$56)*((1+($B62-2.5)*AO62)/(1-1.5*AO62)) -> 0.22113923 | AS62: ='[3]default rates'!$AW$143 -> 0.0031126848 | AT62: =AT61+AS62 -> 0.083212237 | AU62: =0.12*(1-EXP(-50*$AT62))/(1-EXP(-50))+0.24*(1-(1-EXP(-50*$AT62))/(1-EXP(-50))) -> 0.12187176 | AV62: =(0.11852-0.05478*LN($AT62))^2 -> 0.064883729 | AW62: =(AT$56*NORMSDIST((1-AU62)^(-0.5)*NORMSINV($AT62)+(AU62/(1-AU62))^(0.5)*NORMSINV(0.999))-$AT62*AT$56)*((1+($B62-2.5)*AV62)/(1-1.5*AV62)) -> 0.082162892 | AY62: ='[3]default rates'!$BL$327 -> 0.0078896388 | AZ62: =AZ61+AY62 -> 0.062079426 | BA62: =0.12*(1-EXP(-50*$AT62))/(1-EXP(-50))+0.24*(1-(1-EXP(-50*$AT62))/(1-EXP(-50))) -> 0.12187176 | BB62: =(0.11852-0.05478*LN($AT62))^2 -> 0.064883729 | BC62: =(AZ$56*NORMSDIST((1-BA62)^(-0.5)*NORMSINV($AZ62)+(BA62/(1-BA62))^(0.5)*NORMSINV(0.999))-$AZ62*AZ$56)*((1+($B62-2.5)*BB62)/(1-1.5*BB62)) -> 0.053609094 | BE62: ='[3]default rates'!$AW$143 -> 0.0031126848 | BF62: =BF61+BE62 -> 0.083212237 | BG62: =0.12*(1-EXP(-50*$AT62))/(1-EXP(-50))+0.24*(1-(1-EXP(-50*$AT62))/(1-EXP(-50))) -> 0.12187176 | BH62: =(0.11852-0.05478*LN($AT62))^2 -> 0.064883729 | BI62: =(BF$56*NORMSDIST((1-BG62)^(-0.5)*NORMSINV($BF62)+(BG62/(1-BG62))^(0.5)*NORMSINV(0.999))-$BF62*BF$56)*((1+($B62-2.5)*BH62)/(1-1.5*BH62)) -> 0.17691542 | BK62: ='[3]default rates'!$BL$327 -> 0.0078896388 | BL62: =BL61+BK62 -> 0.062079426 | BM62: =0.12*(1-EXP(-50*$AT62))/(1-EXP(-50))+0.24*(1-(1-EXP(-50*$AT62))/(1-EXP(-50))) -> 0.12187176 | BN62: =(0.11852-0.05478*LN($AT62))^2 -> 0.064883729 | BO62: =(BL$56*NORMSDIST((1-BM62)^(-0.5)*NORMSINV($BL62)+(BM62/(1-BM62))^(0.5)*NORMSINV(0.999))-$BL62*BL$56)*((1+($B62-2.5)*BN62)/(1-1.5*BN62)) -> 0.1530231
B63: =$B$15 -> 7 | D63: =Q63*100 -> 0.81666766 | E63: =V63*100 -> 0.81666766 | F63: =AA63*100 -> 9.2373903 | G63: =AF63*100 -> 12.910321 | H63: =AK63*100 -> 18.751763 | I63: =AP63*100 -> 22.993328 | K63: =AW63*100 -> 8.6824696 | N63: ='[2]Moody''s Global Infra and Corp D'!$V$75 -> 1.4413195e-05 | O63: =0.12*(1-EXP(-50*$N63))/(1-EXP(-50))+0.24*(1-(1-EXP(-50*$N63))/(1-EXP(-50))) -> 0.23991355 | P63: =(0.11852-0.05478*LN($N63))^2 -> 0.53169288 | Q63: =(N$56*NORMSDIST((1-O63)^(-0.5)*NORMSINV($N63)+(O63/(1-O63))^(0.5)*NORMSINV(0.999))-$N63*N$56)*((1+($B63-2.5)*P63)/(1-1.5*P63)) -> 0.0081666766 | S63: ='[2]Moody''s Global Infra and Corp D'!$V$76 -> 1.4413195e-05 | T63: =0.12*(1-EXP(-50*$N63))/(1-EXP(-50))+0.24*(1-(1-EXP(-50*$N63))/(1-EXP(-50))) -> 0.23991355 | U63: =(0.11852-0.05478*LN($N63))^2 -> 0.53169288 | V63: =(S$56*NORMSDIST((1-T63)^(-0.5)*NORMSINV($S63)+(T63/(1-T63))^(0.5)*NORMSINV(0.999))-$S63*S$56)*((1+($B63-2.5)*U63)/(1-1.5*U63)) -> 0.0081666766 | X63: ='[2]Moody''s Global Infra and Corp D'!$V$77 -> 0.0043239585 | Y63: =0.12*(1-EXP(-50*$X63))/(1-EXP(-50))+0.24*(1-(1-EXP(-50*$X63))/(1-EXP(-50))) -> 0.2166691 | Z63: =(0.11852-0.05478*LN($X63))^2 -> 0.17365517 | AA63: =(X$56*NORMSDIST((1-Y63)^(-0.5)*NORMSINV($X63)+(Y63/(1-Y63))^(0.5)*NORMSINV(0.999))-$X63*X$56)*((1+($B63-2.5)*Z63)/(1-1.5*Z63)) -> 0.092373903 | AC63: ='[2]Moody''s Global Infra and Corp D'!$V$78 -> 0.014413195 | AD63: =0.12*(1-EXP(-50*$AC63))/(1-EXP(-50))+0.24*(1-(1-EXP(-50*$AC63))/(1-EXP(-50))) -> 0.17837175 | AE63: =(0.11852-0.05478*LN($AC63))^2 -> 0.12303672 | AF63: =(AC$56*NORMSDIST((1-AD63)^(-0.5)*NORMSINV($AC63)+(AD63/(1-AD63))^(0.5)*NORMSINV(0.999))-$AC63*AC$56)*((1+($B63-2.5)*AE63)/(1-1.5*AE63)) -> 0.12910321 | AH63: ='[2]Moody''s Global Infra and Corp D'!$V$79 -> 0.08647917 | AI63: =0.12*(1-EXP(-50*$AH63))/(1-EXP(-50))+0.24*(1-(1-EXP(-50*$AH63))/(1-EXP(-50))) -> 0.12158968 | AJ63: =(0.11852-0.05478*LN($AH63))^2 -> 0.063813487 | AK63: =(AH$56*NORMSDIST((1-AI63)^(-0.5)*NORMSINV($AH63)+(AI63/(1-AI63))^(0.5)*NORMSINV(0.999))-$AH63*AH$56)*((1+($B63-2.5)*AJ63)/(1-1.5*AJ63)) -> 0.18751763 | AM63: ='[2]Moody''s Global Infra and Corp D'!$V$80 -> 0.25223091 | AN63: =0.12*(1-EXP(-50*$AM63))/(1-EXP(-50))+0.24*(1-(1-EXP(-50*$AM63))/(1-EXP(-50))) -> 0.1200004 | AO63: =(0.11852-0.05478*LN($AM63))^2 -> 0.03762612 | AP63: =(AM$56*NORMSDIST((1-AN63)^(-0.5)*NORMSINV($AM63)+(AN63/(1-AN63))^(0.5)*NORMSINV(0.999))-$AM63*AM$56)*((1+($B63-2.5)*AO63)/(1-1.5*AO63)) -> 0.22993328 | AS63: ='[3]default rates'!$AX$143 -> 0.0010911258 | AT63: =AT62+AS63 -> 0.084303363 | AU63: =0.12*(1-EXP(-50*$AT63))/(1-EXP(-50))+0.24*(1-(1-EXP(-50*$AT63))/(1-EXP(-50))) -> 0.12177238 | AV63: =(0.11852-0.05478*LN($AT63))^2 -> 0.064520679 | AW63: =(AT$56*NORMSDIST((1-AU63)^(-0.5)*NORMSINV($AT63)+(AU63/(1-AU63))^(0.5)*NORMSINV(0.999))-$AT63*AT$56)*((1+($B63-2.5)*AV63)/(1-1.5*AV63)) -> 0.086824696 | AY63: ='[3]default rates'!$BM$327 -> 0 | AZ63: =AZ62+AY63 -> 0.062079426 | BA63: =0.12*(1-EXP(-50*$AT63))/(1-EXP(-50))+0.24*(1-(1-EXP(-50*$AT63))/(1-EXP(-50))) -> 0.12177238 | BB63: =(0.11852-0.05478*LN($AT63))^2 -> 0.064520679 | BC63: =(AZ$56*NORMSDIST((1-BA63)^(-0.5)*NORMSINV($AZ63)+(BA63/(1-BA63))^(0.5)*NORMSINV(0.999))-$AZ63*AZ$56)*((1+($B63-2.5)*BB63)/(1-1.5*BB63)) -> 0.056303158 | BE63: ='[3]default rates'!$AX$143 -> 0.0010911258 | BF63: =BF62+BE63 -> 0.084303363 | BG63: =0.12*(1-EXP(-50*$AT63))/(1-EXP(-50))+0.24*(1-(1-EXP(-50*$AT63))/(1-EXP(-50))) -> 0.12177238 | BH63: =(0.11852-0.05478*LN($AT63))^2 -> 0.064520679 | BI63: =(BF$56*NORMSDIST((1-BG63)^(-0.5)*NORMSINV($BF63)+(BG63/(1-BG63))^(0.5)*NORMSINV(0.999))-$BF63*BF$56)*((1+($B63-2.5)*BH63)/(1-1.5*BH63)) -> 0.18695335 | BK63: ='[3]default rates'!$BM$327 -> 0 | BL63: =BL62+BK63 -> 0.062079426 | BM63: =0.12*(1-EXP(-50*$AT63))/(1-EXP(-50))+0.24*(1-(1-EXP(-50*$AT63))/(1-EXP(-50))) -> 0.12177238 | BN63: =(0.11852-0.05478*LN($AT63))^2 -> 0.064520679 | BO63: =(BL$56*NORMSDIST((1-BM63)^(-0.5)*NORMSINV($BL63)+(BM63/(1-BM63))^(0.5)*NORMSINV(0.999))-$BL63*BL$56)*((1+($B63-2.5)*BN63)/(1-1.5*BN63)) -> 0.16071311
B64: =$B$16 -> 8 | D64: =Q64*100 -> 0.94465625 | E64: =V64*100 -> 0.94465625 | F64: =AA64*100 -> 10.137849 | G64: =AF64*100 -> 14.172998 | H64: =AK64*100 -> 19.937244 | I64: =AP64*100 -> 23.69029 | K64: =AW64*100 -> 9.137884 | N64: ='[2]Moody''s Global Infra and Corp D'!$W$75 -> 1.4413195e-05 | O64: =0.12*(1-EXP(-50*$N64))/(1-EXP(-50))+0.24*(1-(1-EXP(-50*$N64))/(1-EXP(-50))) -> 0.23991355 | P64: =(0.11852-0.05478*LN($N64))^2 -> 0.53169288 | Q64: =(N$56*NORMSDIST((1-O64)^(-0.5)*NORMSINV($N64)+(O64/(1-O64))^(0.5)*NORMSINV(0.999))-$N64*N$56)*((1+($B64-2.5)*P64)/(1-1.5*P64)) -> 0.0094465625 | S64: ='[2]Moody''s Global Infra and Corp D'!$W$76 -> 1.4413195e-05 | T64: =0.12*(1-EXP(-50*$N64))/(1-EXP(-50))+0.24*(1-(1-EXP(-50*$N64))/(1-EXP(-50))) -> 0.23991355 | U64: =(0.11852-0.05478*LN($N64))^2 -> 0.53169288 | V64: =(S$56*NORMSDIST((1-T64)^(-0.5)*NORMSINV($S64)+(T64/(1-T64))^(0.5)*NORMSINV(0.999))-$S64*S$56)*((1+($B64-2.5)*U64)/(1-1.5*U64)) -> 0.0094465625 | X64: ='[2]Moody''s Global Infra and Corp D'!$W$77 -> 0.0043239585 | Y64: =0.12*(1-EXP(-50*$X64))/(1-EXP(-50))+0.24*(1-(1-EXP(-50*$X64))/(1-EXP(-50))) -> 0.2166691 | Z64: =(0.11852-0.05478*LN($X64))^2 -> 0.17365517 | AA64: =(X$56*NORMSDIST((1-Y64)^(-0.5)*NORMSINV($X64)+(Y64/(1-Y64))^(0.5)*NORMSINV(0.999))-$X64*X$56)*((1+($B64-2.5)*Z64)/(1-1.5*Z64)) -> 0.10137849 | AC64: ='[2]Moody''s Global Infra and Corp D'!$W$78 -> 0.015854515 | AD64: =0.12*(1-EXP(-50*$AC64))/(1-EXP(-50))+0.24*(1-(1-EXP(-50*$AC64))/(1-EXP(-50))) -> 0.17431313 | AE64: =(0.11852-0.05478*LN($AC64))^2 -> 0.11940121 | AF64: =(AC$56*NORMSDIST((1-AD64)^(-0.5)*NORMSINV($AC64)+(AD64/(1-AD64))^(0.5)*NORMSINV(0.999))-$AC64*AC$56)*((1+($B64-2.5)*AE64)/(1-1.5*AE64)) -> 0.14172998 | AH64: ='[2]Moody''s Global Infra and Corp D'!$W$79 -> 0.090803129 | AI64: =0.12*(1-EXP(-50*$AH64))/(1-EXP(-50))+0.24*(1-(1-EXP(-50*$AH64))/(1-EXP(-50))) -> 0.12128061 | AJ64: =(0.11852-0.05478*LN($AH64))^2 -> 0.062470299 | AK64: =(AH$56*NORMSDIST((1-AI64)^(-0.5)*NORMSINV($AH64)+(AI64/(1-AI64))^(0.5)*NORMSINV(0.999))-$AH64*AH$56)*((1+($B64-2.5)*AJ64)/(1-1.5*AJ64)) -> 0.19937244 | AM64: ='[2]Moody''s Global Infra and Corp D'!$W$80 -> 0.27385071 | AN64: =0.12*(1-EXP(-50*$AM64))/(1-EXP(-50))+0.24*(1-(1-EXP(-50*$AM64))/(1-EXP(-50))) -> 0.12000014 | AO64: =(0.11852-0.05478*LN($AM64))^2 -> 0.035898704 | AP64: =(AM$56*NORMSDIST((1-AN64)^(-0.5)*NORMSINV($AM64)+(AN64/(1-AN64))^(0.5)*NORMSINV(0.999))-$AM64*AM$56)*((1+($B64-2.5)*AO64)/(1-1.5*AO64)) -> 0.2369029 | AS64: ='[3]default rates'!$AY$143 -> 0.00074394258 | AT64: =AT63+AS64 -> 0.085047306 | AU64: =0.12*(1-EXP(-50*$AT64))/(1-EXP(-50))+0.24*(1-(1-EXP(-50*$AT64))/(1-EXP(-50))) -> 0.12170766 | AV64: =(0.11852-0.05478*LN($AT64))^2 -> 0.064276406 | AW64: =(AT$56*NORMSDIST((1-AU64)^(-0.5)*NORMSINV($AT64)+(AU64/(1-AU64))^(0.5)*NORMSINV(0.999))-$AT64*AT$56)*((1+($B64-2.5)*AV64)/(1-1.5*AV64)) -> 0.09137884 | AY64: ='[3]default rates'!$BN$327 -> 0 | AZ64: =AZ63+AY64 -> 0.062079426 | BA64: =0.12*(1-EXP(-50*$AT64))/(1-EXP(-50))+0.24*(1-(1-EXP(-50*$AT64))/(1-EXP(-50))) -> 0.12170766 | BB64: =(0.11852-0.05478*LN($AT64))^2 -> 0.064276406 | BC64: =(AZ$56*NORMSDIST((1-BA64)^(-0.5)*NORMSINV($AZ64)+(BA64/(1-BA64))^(0.5)*NORMSINV(0.999))-$AZ64*AZ$56)*((1+($B64-2.5)*BB64)/(1-1.5*BB64)) -> 0.059011857 | BE64: ='[3]default rates'!$AY$143 -> 0.00074394258 | BF64: =BF63+BE64 -> 0.085047306 | BG64: =0.12*(1-EXP(-50*$AT64))/(1-EXP(-50))+0.24*(1-(1-EXP(-50*$AT64))/(1-EXP(-50))) -> 0.12170766 | BH64: =(0.11852-0.05478*LN($AT64))^2 -> 0.064276406 | BI64: =(BF$56*NORMSDIST((1-BG64)^(-0.5)*NORMSINV($BF64)+(BG64/(1-BG64))^(0.5)*NORMSINV(0.999))-$BF64*BF$56)*((1+($B64-2.5)*BH64)/(1-1.5*BH64)) -> 0.19675946 | BK64: ='[3]default rates'!$BN$327 -> 0 | BL64: =BL63+BK64 -> 0.062079426 | BM64: =0.12*(1-EXP(-50*$AT64))/(1-EXP(-50))+0.24*(1-(1-EXP(-50*$AT64))/(1-EXP(-50))) -> 0.12170766 | BN64: =(0.11852-0.05478*LN($AT64))^2 -> 0.064276406 | BO64: =(BL$56*NORMSDIST((1-BM64)^(-0.5)*NORMSINV($BL64)+(BM64/(1-BM64))^(0.5)*NORMSINV(0.999))-$BL64*BL$56)*((1+($B64-2.5)*BN64)/(1-1.5*BN64)) -> 0.16844488
B65: =$B$17 -> 9 | D65: =Q65*100 -> 1.0726448 | E65: =V65*100 -> 1.0726448 | F65: =AA65*100 -> 11.038308 | G65: =AF65*100 -> 15.590344 | H65: =AK65*100 -> 21.185583 | I65: =AP65*100 -> 24.235973 | K65: =AW65*100 -> 9.5825587 | N65: ='[2]Moody''s Global Infra and Corp D'!$X$75 -> 1.4413195e-05 | O65: =0.12*(1-EXP(-50*$N65))/(1-EXP(-50))+0.24*(1-(1-EXP(-50*$N65))/(1-EXP(-50))) -> 0.23991355 | P65: =(0.11852-0.05478*LN($N65))^2 -> 0.53169288 | Q65: =(N$56*NORMSDIST((1-O65)^(-0.5)*NORMSINV($N65)+(O65/(1-O65))^(0.5)*NORMSINV(0.999))-$N65*N$56)*((1+($B65-2.5)*P65)/(1-1.5*P65)) -> 0.010726448 | S65: ='[2]Moody''s Global Infra and Corp D'!$X$76 -> 1.4413195e-05 | T65: =0.12*(1-EXP(-50*$N65))/(1-EXP(-50))+0.24*(1-(1-EXP(-50*$N65))/(1-EXP(-50))) -> 0.23991355 | U65: =(0.11852-0.05478*LN($N65))^2 -> 0.53169288 | V65: =(S$56*NORMSDIST((1-T65)^(-0.5)*NORMSINV($S65)+(T65/(1-T65))^(0.5)*NORMSINV(0.999))-$S65*S$56)*((1+($B65-2.5)*U65)/(1-1.5*U65)) -> 0.010726448 | X65: ='[2]Moody''s Global Infra and Corp D'!$X$77 -> 0.0043239585 | Y65: =0.12*(1-EXP(-50*$X65))/(1-EXP(-50))+0.24*(1-(1-EXP(-50*$X65))/(1-EXP(-50))) -> 0.2166691 | Z65: =(0.11852-0.05478*LN($X65))^2 -> 0.17365517 | AA65: =(X$56*NORMSDIST((1-Y65)^(-0.5)*NORMSINV($X65)+(Y65/(1-Y65))^(0.5)*NORMSINV(0.999))-$X65*X$56)*((1+($B65-2.5)*Z65)/(1-1.5*Z65)) -> 0.11038308 | AC65: ='[2]Moody''s Global Infra and Corp D'!$X$78 -> 0.018737154 | AD65: =0.12*(1-EXP(-50*$AC65))/(1-EXP(-50))+0.24*(1-(1-EXP(-50*$AC65))/(1-EXP(-50))) -> 0.16702287 | AE65: =(0.11852-0.05478*LN($AC65))^2 -> 0.11316064 | AF65: =(AC$56*NORMSDIST((1-AD65)^(-0.5)*NORMSINV($AC65)+(AD65/(1-AD65))^(0.5)*NORMSINV(0.999))-$AC65*AC$56)*((1+($B65-2.5)*AE65)/(1-1.5*AE65)) -> 0.15590344 | AH65: ='[2]Moody''s Global Infra and Corp D'!$X$79 -> 0.096568407 | AI65: =0.12*(1-EXP(-50*$AH65))/(1-EXP(-50))+0.24*(1-(1-EXP(-50*$AH65))/(1-EXP(-50))) -> 0.1209599 | AJ65: =(0.11852-0.05478*LN($AH65))^2 -> 0.060796 | AK65: =(AH$56*NORMSDIST((1-AI65)^(-0.5)*NORMSINV($AH65)+(AI65/(1-AI65))^(0.5)*NORMSINV(0.999))-$AH65*AH$56)*((1+($B65-2.5)*AJ65)/(1-1.5*AJ65)) -> 0.21185583 | AM65: ='[2]Moody''s Global Infra and Corp D'!$X$80 -> 0.29691182 | AN65: =0.12*(1-EXP(-50*$AM65))/(1-EXP(-50))+0.24*(1-(1-EXP(-50*$AM65))/(1-EXP(-50))) -> 0.12000004 | AO65: =(0.11852-0.05478*LN($AM65))^2 -> 0.03423997 | AP65: =(AM$56*NORMSDIST((1-AN65)^(-0.5)*NORMSINV($AM65)+(AN65/(1-AN65))^(0.5)*NORMSINV(0.999))-$AM65*AM$56)*((1+($B65-2.5)*AO65)/(1-1.5*AO65)) -> 0.24235973 | AS65: ='[3]default rates'!$AZ$143 -> 0.00038095238 | AT65: =AT64+AS65 -> 0.085428258 | AU65: =0.12*(1-EXP(-50*$AT65))/(1-EXP(-50))+0.24*(1-(1-EXP(-50*$AT65))/(1-EXP(-50))) -> 0.12167545 | AV65: =(0.11852-0.05478*LN($AT65))^2 -> 0.064152324 | AW65: =(AT$56*NORMSDIST((1-AU65)^(-0.5)*NORMSINV($AT65)+(AU65/(1-AU65))^(0.5)*NORMSINV(0.999))-$AT65*AT$56)*((1+($B65-2.5)*AV65)/(1-1.5*AV65)) -> 0.095825587 | AY65: ='[3]default rates'!$BO$327 -> 0 | AZ65: =AZ64+AY65 -> 0.062079426 | BA65: =0.12*(1-EXP(-50*$AT65))/(1-EXP(-50))+0.24*(1-(1-EXP(-50*$AT65))/(1-EXP(-50))) -> 0.12167545 | BB65: =(0.11852-0.05478*LN($AT65))^2 -> 0.064152324 | BC65: =(AZ$56*NORMSDIST((1-BA65)^(-0.5)*NORMSINV($AZ65)+(BA65/(1-BA65))^(0.5)*NORMSINV(0.999))-$AZ65*AZ$56)*((1+($B65-2.5)*BB65)/(1-1.5*BB65)) -> 0.061753817 | BE65: ='[3]default rates'!$AZ$143 -> 0.00038095238 | BF65: =BF64+BE65 -> 0.085428258 | BG65: =0.12*(1-EXP(-50*$AT65))/(1-EXP(-50))+0.24*(1-(1-EXP(-50*$AT65))/(1-EXP(-50))) -> 0.12167545 | BH65: =(0.11852-0.05478*LN($AT65))^2 -> 0.064152324 | BI65: =(BF$56*NORMSDIST((1-BG65)^(-0.5)*NORMSINV($BF65)+(BG65/(1-BG65))^(0.5)*NORMSINV(0.999))-$BF65*BF$56)*((1+($B65-2.5)*BH65)/(1-1.5*BH65)) -> 0.20633432 | BK65: ='[3]default rates'!$BO$327 -> 0 | BL65: =BL64+BK65 -> 0.062079426 | BM65: =0.12*(1-EXP(-50*$AT65))/(1-EXP(-50))+0.24*(1-(1-EXP(-50*$AT65))/(1-EXP(-50))) -> 0.12167545 | BN65: =(0.11852-0.05478*LN($AT65))^2 -> 0.064152324 | BO65: =(BL$56*NORMSDIST((1-BM65)^(-0.5)*NORMSINV($BL65)+(BM65/(1-BM65))^(0.5)*NORMSINV(0.999))-$BL65*BL$56)*((1+($B65-2.5)*BN65)/(1-1.5*BN65)) -> 0.1762716
B66: =$B$18 -> 10 | D66: =Q66*100 -> 1.2006334 | E66: =V66*100 -> 1.2006334 | F66: =AA66*100 -> 13.032878 | G66: =AF66*100 -> 16.771637 | H66: =AK66*100 -> 22.479023 | I66: =AP66*100 -> 24.658969 | K66: =AW66*100 -> 10.027137 | N66: ='[2]Moody''s Global Infra and Corp D'!$Y$75 -> 1.4413195e-05 | O66: =0.12*(1-EXP(-50*$N66))/(1-EXP(-50))+0.24*(1-(1-EXP(-50*$N66))/(1-EXP(-50))) -> 0.23991355 | P66: =(0.11852-0.05478*LN($N66))^2 -> 0.53169288 | Q66: =(N$56*NORMSDIST((1-O66)^(-0.5)*NORMSINV($N66)+(O66/(1-O66))^(0.5)*NORMSINV(0.999))-$N66*N$56)*((1+($B66-2.5)*P66)/(1-1.5*P66)) -> 0.012006334 | S66: ='[2]Moody''s Global Infra and Corp D'!$Y$76 -> 1.4413195e-05 | T66: =0.12*(1-EXP(-50*$N66))/(1-EXP(-50))+0.24*(1-(1-EXP(-50*$N66))/(1-EXP(-50))) -> 0.23991355 | U66: =(0.11852-0.05478*LN($N66))^2 -> 0.53169288 | V66: =(S$56*NORMSDIST((1-T66)^(-0.5)*NORMSINV($S66)+(T66/(1-T66))^(0.5)*NORMSINV(0.999))-$S66*S$56)*((1+($B66-2.5)*U66)/(1-1.5*U66)) -> 0.012006334 | X66: ='[2]Moody''s Global Infra and Corp D'!$Y$77 -> 0.005765278 | Y66: =0.12*(1-EXP(-50*$X66))/(1-EXP(-50))+0.24*(1-(1-EXP(-50*$X66))/(1-EXP(-50))) -> 0.20994765 | Z66: =(0.11852-0.05478*LN($X66))^2 -> 0.16076917 | AA66: =(X$56*NORMSDIST((1-Y66)^(-0.5)*NORMSINV($X66)+(Y66/(1-Y66))^(0.5)*NORMSINV(0.999))-$X66*X$56)*((1+($B66-2.5)*Z66)/(1-1.5*Z66)) -> 0.13032878 | AC66: ='[2]Moody''s Global Infra and Corp D'!$Y$78 -> 0.020178473 | AD66: =0.12*(1-EXP(-50*$AC66))/(1-EXP(-50))+0.24*(1-(1-EXP(-50*$AC66))/(1-EXP(-50))) -> 0.16375335 | AE66: =(0.11852-0.05478*LN($AC66))^2 -> 0.11044585 | AF66: =(AC$56*NORMSDIST((1-AD66)^(-0.5)*NORMSINV($AC66)+(AD66/(1-AD66))^(0.5)*NORMSINV(0.999))-$AC66*AC$56)*((1+($B66-2.5)*AE66)/(1-1.5*AE66)) -> 0.16771637 | AH66: ='[2]Moody''s Global Infra and Corp D'!$Y$79 -> 0.103775 | AI66: =0.12*(1-EXP(-50*$AH66))/(1-EXP(-50))+0.24*(1-(1-EXP(-50*$AH66))/(1-EXP(-50))) -> 0.12066948 | AJ66: =(0.11852-0.05478*LN($AH66))^2 -> 0.05886725 | AK66: =(AH$56*NORMSDIST((1-AI66)^(-0.5)*NORMSINV($AH66)+(AI66/(1-AI66))^(0.5)*NORMSINV(0.999))-$AH66*AH$56)*((1+($B66-2.5)*AJ66)/(1-1.5*AJ66)) -> 0.22479023 | AM66: ='[2]Moody''s Global Infra and Corp D'!$Y$80 -> 0.31853161 | AN66: =0.12*(1-EXP(-50*$AM66))/(1-EXP(-50))+0.24*(1-(1-EXP(-50*$AM66))/(1-EXP(-50))) -> 0.12000001 | AO66: =(0.11852-0.05478*LN($AM66))^2 -> 0.032829874 | AP66: =(AM$56*NORMSDIST((1-AN66)^(-0.5)*NORMSINV($AM66)+(AN66/(1-AN66))^(0.5)*NORMSINV(0.999))-$AM66*AM$56)*((1+($B66-2.5)*AO66)/(1-1.5*AO66)) -> 0.24658969 | AS66: ='[3]default rates'!$BA$143 -> 0.00038639876 | AT66: =AT65+AS66 -> 0.085814657 | AU66: =0.12*(1-EXP(-50*$AT66))/(1-EXP(-50))+0.24*(1-(1-EXP(-50*$AT66))/(1-EXP(-50))) -> 0.12164339 | AV66: =(0.11852-0.05478*LN($AT66))^2 -> 0.064027155 | AW66: =(AT$56*NORMSDIST((1-AU66)^(-0.5)*NORMSINV($AT66)+(AU66/(1-AU66))^(0.5)*NORMSINV(0.999))-$AT66*AT$56)*((1+($B66-2.5)*AV66)/(1-1.5*AV66)) -> 0.10027137 | AY66: ='[3]default rates'!$BP$327 -> 0 | AZ66: =AZ65+AY66 -> 0.062079426 | BA66: =0.12*(1-EXP(-50*$AT66))/(1-EXP(-50))+0.24*(1-(1-EXP(-50*$AT66))/(1-EXP(-50))) -> 0.12164339 | BB66: =(0.11852-0.05478*LN($AT66))^2 -> 0.064027155 | BC66: =(AZ$56*NORMSDIST((1-BA66)^(-0.5)*NORMSINV($AZ66)+(BA66/(1-BA66))^(0.5)*NORMSINV(0.999))-$AZ66*AZ$56)*((1+($B66-2.5)*BB66)/(1-1.5*BB66)) -> 0.064482307 | BE66: ='[3]default rates'!$BA$143 -> 0.00038639876 | BF66: =BF65+BE66 -> 0.085814657 | BG66: =0.12*(1-EXP(-50*$AT66))/(1-EXP(-50))+0.24*(1-(1-EXP(-50*$AT66))/(1-EXP(-50))) -> 0.12164339 | BH66: =(0.11852-0.05478*LN($AT66))^2 -> 0.064027155 | BI66: =(BF$56*NORMSDIST((1-BG66)^(-0.5)*NORMSINV($BF66)+(BG66/(1-BG66))^(0.5)*NORMSINV(0.999))-$BF66*BF$56)*((1+($B66-2.5)*BH66)/(1-1.5*BH66)) -> 0.2159071 | BK66: ='[3]default rates'!$BP$327 -> 0 | BL66: =BL65+BK66 -> 0.062079426 | BM66: =0.12*(1-EXP(-50*$AT66))/(1-EXP(-50))+0.24*(1-(1-EXP(-50*$AT66))/(1-EXP(-50))) -> 0.12164339 | BN66: =(0.11852-0.05478*LN($AT66))^2 -> 0.064027155 | BO66: =(BL$56*NORMSDIST((1-BM66)^(-0.5)*NORMSINV($BL66)+(BM66/(1-BM66))^(0.5)*NORMSINV(0.999))-$BL66*BL$56)*((1+($B66-2.5)*BN66)/(1-1.5*BN66)) -> 0.18405987
D68: ='[2]Table - SII - Interim'!D48:R48 -> Infrastructure Investment in EMDEs 6/ | N68: =N$32/AT$32*AT68 -> 0.47449771 | S68: =N68 -> 0.47449771 | X68: =N68 -> 0.47449771 | AC68: =X68 -> 0.47449771 | AH68: =X68 -> 0.47449771 | AM68: =AC68 -> 0.47449771 | AS68: Marginal PD ↓/Recovery → | AT68: =1-'[2]default rates (3)'!CR18/100 -> 0.22128202 | AU68: stdev(rec.) | AV68: ='[2]default rates (3)'!CS18 -> 0.35259965 | AW68: =AV68*(AT68/(1-AT68)) -> 0.1001954 | AY68: Marginal PD ↓/Recovery → | AZ68: =1-'[3]default rates'!$CR$25/100 -> 0.15765 | BA68: stdev(rec.) | BB68: ='[3]default rates'!$CS$25 -> 0.22295077 | BC68: =BB68*(AZ68/(1-AZ68)) -> 0.041726347 | BE68: Marginal PD ↓/Recovery → | BF68: =BF32 -> 0.45 | BG68: stdev(rec.) | BH68: =BF68/AT68*AV68 -> 0.71704807 | BI68: =BH68*(BF68/(1-BF68)) -> 0.58667569 | BK68: Marginal PD ↓/Recovery → | BL68: =BF68 -> 0.45 | BM68: stdev(rec.) | BN68: ='[3]default rates'!$CS$25 -> 0.22295077 | BO68: =BN68*(BL68/(1-BL68)) -> 0.18241426
B69: =$B$9 -> 1 | D69: =Q69*100 -> 0.11913766 | E69: =V69*100 -> 0.11913766 | F69: =AA69*100 -> 0.02682939 | G69: =AF69*100 -> 1.5541305 | H69: =AK69*100 -> 4.2660511 | I69: =AP69*100 -> 9.2171957 | K69: =AW69*100 -> 3.8689692 | N69: ='[2]Moody''s Global Infra and Corp D'!$P$82 -> 3.8235787e-05 | O69: =0.12*(1-EXP(-50*$N69))/(1-EXP(-50))+0.24*(1-(1-EXP(-50*$N69))/(1-EXP(-50))) -> 0.2397708 | P69: =(0.11852-0.05478*LN($N69))^2 -> 0.45660812 | Q69: =(N$68*NORMSDIST((1-O69)^(-0.5)*NORMSINV($N69)+(O69/(1-O69))^(0.5)*NORMSINV(0.999))-$N69*N$68)*((1+($B69-2.5)*P69)/(1-1.5*P69)) -> 0.0011913766 | S69: ='[2]Moody''s Global Infra and Corp D'!$P$83 -> 3.8235787e-05 | T69: =0.12*(1-EXP(-50*$S69))/(1-EXP(-50))+0.24*(1-(1-EXP(-50*$S69))/(1-EXP(-50))) -> 0.2397708 | U69: =(0.11852-0.05478*LN($S69))^2 -> 0.45660812 | V69: =(S$68*NORMSDIST((1-T69)^(-0.5)*NORMSINV($S69)+(T69/(1-T69))^(0.5)*NORMSINV(0.999))-$S69*S$68)*((1+($B69-2.5)*U69)/(1-1.5*U69)) -> 0.0011913766 | X69: ='[2]Moody''s Global Infra and Corp D'!$P$84 -> 6.8322084e-06 | Y69: =0.12*(1-EXP(-50*$X69))/(1-EXP(-50))+0.24*(1-(1-EXP(-50*$X69))/(1-EXP(-50))) -> 0.23995901 | Z69: =(0.11852-0.05478*LN($X69))^2 -> 0.59300133 | AA69: =(X$68*NORMSDIST((1-Y69)^(-0.5)*NORMSINV($X69)+(Y69/(1-Y69))^(0.5)*NORMSINV(0.999))-$X69*X$68)*((1+($B69-2.5)*Z69)/(1-1.5*Z69)) -> 0.0002682939 | AC69: ='[2]Moody''s Global Infra and Corp D'!$P$85 -> 0.00098155514 | AD69: =0.12*(1-EXP(-50*$AC69))/(1-EXP(-50))+0.24*(1-(1-EXP(-50*$AC69))/(1-EXP(-50))) -> 0.23425285 | AE69: =(0.11852-0.05478*LN($AC69))^2 -> 0.24795089 | AF69: =(AC$68*NORMSDIST((1-AD69)^(-0.5)*NORMSINV($AC69)+(AD69/(1-AD69))^(0.5)*NORMSINV(0.999))-$AC69*AC$68)*((1+($B69-2.5)*AE69)/(1-1.5*AE69)) -> 0.015541305 | AH69: ='[2]Moody''s Global Infra and Corp D'!$P$86 -> 0.0047247696 | AI69: =0.12*(1-EXP(-50*$AH69))/(1-EXP(-50))+0.24*(1-(1-EXP(-50*$AH69))/(1-EXP(-50))) -> 0.21475108 | AJ69: =(0.11852-0.05478*LN($AH69))^2 -> 0.16963148 | AK69: =(AH$68*NORMSDIST((1-AI69)^(-0.5)*NORMSINV($AH69)+(AI69/(1-AI69))^(0.5)*NORMSINV(0.999))-$AH69*AH$68)*((1+($B69-2.5)*AJ69)/(1-1.5*AJ69)) -> 0.042660511 | AM69: ='[2]Moody''s Global Infra and Corp D'!$P$87 -> 0.02952981 | AN69: =0.12*(1-EXP(-50*$AM69))/(1-EXP(-50))+0.24*(1-(1-EXP(-50*$AM69))/(1-EXP(-50))) -> 0.14741256 | AO69: =(0.11852-0.05478*LN($AM69))^2 -> 0.097016431 | AP69: =(AM$68*NORMSDIST((1-AN69)^(-0.5)*NORMSINV($AM69)+(AN69/(1-AN69))^(0.5)*NORMSINV(0.999))-$AM69*AM$68)*((1+($B69-2.5)*AO69)/(1-1.5*AO69)) -> 0.092171957 | AS69: ='[3]default rates'!$AR$140 -> 0.021607024 | AT69: =AS69 -> 0.021607024 | AU69: =0.12*(1-EXP(-50*$AT69))/(1-EXP(-50))+0.24*(1-(1-EXP(-50*$AT69))/(1-EXP(-50))) -> 0.16073715 | AV69: =(0.11852-0.05478*LN($AT69))^2 -> 0.10796934 | AW69: =(AT$68*NORMSDIST((1-AU69)^(-0.5)*NORMSINV($AT69)+(AU69/(1-AU69))^(0.5)*NORMSINV(0.999))-$AT69*AT$68)*((1+($B69-2.5)*AV69)/(1-1.5*AV69)) -> 0.038689692 | AY69: ='[3]default rates'!$BG$321 -> 0.010022942 | AZ69: =AY69 -> 0.010022942 | BA69: =0.12*(1-EXP(-50*$AT69))/(1-EXP(-50))+0.24*(1-(1-EXP(-50*$AT69))/(1-EXP(-50))) -> 0.16073715 | BB69: =(0.11852-0.05478*LN($AT69))^2 -> 0.10796934 | BC69: =(AZ$68*NORMSDIST((1-BA69)^(-0.5)*NORMSINV($AZ69)+(BA69/(1-BA69))^(0.5)*NORMSINV(0.999))-$AZ69*AZ$68)*((1+($B69-2.5)*BB69)/(1-1.5*BB69)) -> 0.01699142 | BE69: ='[3]default rates'!$AR$140 -> 0.021607024 | BF69: =BE69 -> 0.021607024 | BG69: =0.12*(1-EXP(-50*$AT69))/(1-EXP(-50))+0.24*(1-(1-EXP(-50*$AT69))/(1-EXP(-50))) -> 0.16073715 | BH69: =(0.11852-0.05478*LN($AT69))^2 -> 0.10796934 | BI69: =(BF$68*NORMSDIST((1-BG69)^(-0.5)*NORMSINV($BF69)+(BG69/(1-BG69))^(0.5)*NORMSINV(0.999))-$BF69*BF$68)*((1+($B69-2.5)*BH69)/(1-1.5*BH69)) -> 0.078679513 | BK69: ='[3]default rates'!$BG$321 -> 0.010022942 | BL69: =BK69 -> 0.010022942 | BM69: =0.12*(1-EXP(-50*$AT69))/(1-EXP(-50))+0.24*(1-(1-EXP(-50*$AT69))/(1-EXP(-50))) -> 0.16073715 | BN69: =(0.11852-0.05478*LN($AT69))^2 -> 0.10796934 | BO69: =(BL$68*NORMSDIST((1-BM69)^(-0.5)*NORMSINV($BL69)+(BM69/(1-BM69))^(0.5)*NORMSINV(0.999))-$BL69*BL$68)*((1+($B69-2.5)*BN69)/(1-1.5*BN69)) -> 0.048500723
B70: =$B$10 -> 2 | D70: =Q70*100 -> 0.29178547 | E70: =V70*100 -> 0.29178547 | F70: =AA70*100 -> 0.17081265 | G70: =AF70*100 -> 3.2775751 | H70: =AK70*100 -> 8.4301147 | I70: =AP70*100 -> 13.265743 | K70: =AW70*100 -> 5.3491544 | N70: ='[2]Moody''s Global Infra and Corp D'!$Q$82 -> 3.8235787e-05 | O70: =0.12*(1-EXP(-50*$N70))/(1-EXP(-50))+0.24*(1-(1-EXP(-50*$N70))/(1-EXP(-50))) -> 0.2397708 | P70: =(0.11852-0.05478*LN($N70))^2 -> 0.45660812 | Q70: =(N$68*NORMSDIST((1-O70)^(-0.5)*NORMSINV($N70)+(O70/(1-O70))^(0.5)*NORMSINV(0.999))-$N70*N$68)*((1+($B70-2.5)*P70)/(1-1.5*P70)) -> 0.0029178547 | S70: ='[2]Moody''s Global Infra and Corp D'!$Q$83 -> 3.8235787e-05 | T70: =0.12*(1-EXP(-50*$N70))/(1-EXP(-50))+0.24*(1-(1-EXP(-50*$N70))/(1-EXP(-50))) -> 0.2397708 | U70: =(0.11852-0.05478*LN($N70))^2 -> 0.45660812 | V70: =(S$68*NORMSDIST((1-T70)^(-0.5)*NORMSINV($S70)+(T70/(1-T70))^(0.5)*NORMSINV(0.999))-$S70*S$68)*((1+($B70-2.5)*U70)/(1-1.5*U70)) -> 0.0029178547 | X70: ='[2]Moody''s Global Infra and Corp D'!$Q$84 -> 6.8322084e-06 | Y70: =0.12*(1-EXP(-50*$X70))/(1-EXP(-50))+0.24*(1-(1-EXP(-50*$X70))/(1-EXP(-50))) -> 0.23995901 | Z70: =(0.11852-0.05478*LN($X70))^2 -> 0.59300133 | AA70: =(X$68*NORMSDIST((1-Y70)^(-0.5)*NORMSINV($X70)+(Y70/(1-Y70))^(0.5)*NORMSINV(0.999))-$X70*X$68)*((1+($B70-2.5)*Z70)/(1-1.5*Z70)) -> 0.0017081265 | AC70: ='[2]Moody''s Global Infra and Corp D'!$Q$85 -> 0.0019631103 | AD70: =0.12*(1-EXP(-50*$AC70))/(1-EXP(-50))+0.24*(1-(1-EXP(-50*$AC70))/(1-EXP(-50))) -> 0.22878095 | AE70: =(0.11852-0.05478*LN($AC70))^2 -> 0.21157799 | AF70: =(AC$68*NORMSDIST((1-AD70)^(-0.5)*NORMSINV($AC70)+(AD70/(1-AD70))^(0.5)*NORMSINV(0.999))-$AC70*AC$68)*((1+($B70-2.5)*AE70)/(1-1.5*AE70)) -> 0.032775751 | AH70: ='[2]Moody''s Global Infra and Corp D'!$Q$86 -> 0.015355501 | AI70: =0.12*(1-EXP(-50*$AH70))/(1-EXP(-50))+0.24*(1-(1-EXP(-50*$AH70))/(1-EXP(-50))) -> 0.17568533 | AJ70: =(0.11852-0.05478*LN($AH70))^2 -> 0.120615 | AK70: =(AH$68*NORMSDIST((1-AI70)^(-0.5)*NORMSINV($AH70)+(AI70/(1-AI70))^(0.5)*NORMSINV(0.999))-$AH70*AH$68)*((1+($B70-2.5)*AJ70)/(1-1.5*AJ70)) -> 0.084301147 | AM70: ='[2]Moody''s Global Infra and Corp D'!$Q$87 -> 0.06378439 | AN70: =0.12*(1-EXP(-50*$AM70))/(1-EXP(-50))+0.24*(1-(1-EXP(-50*$AM70))/(1-EXP(-50))) -> 0.12494448 | AO70: =(0.11852-0.05478*LN($AM70))^2 -> 0.07251607 | AP70: =(AM$68*NORMSDIST((1-AN70)^(-0.5)*NORMSINV($AM70)+(AN70/(1-AN70))^(0.5)*NORMSINV(0.999))-$AM70*AM$68)*((1+($B70-2.5)*AO70)/(1-1.5*AO70)) -> 0.13265743 | AS70: ='[3]default rates'!$AS$140 -> 0.020716569 | AT70: =AT69+AS70 -> 0.042323593 | AU70: =0.12*(1-EXP(-50*$AT70))/(1-EXP(-50))+0.24*(1-(1-EXP(-50*$AT70))/(1-EXP(-50))) -> 0.13445893 | AV70: =(0.11852-0.05478*LN($AT70))^2 -> 0.085122061 | AW70: =(AT$68*NORMSDIST((1-AU70)^(-0.5)*NORMSINV($AT70)+(AU70/(1-AU70))^(0.5)*NORMSINV(0.999))-$AT70*AT$68)*((1+($B70-2.5)*AV70)/(1-1.5*AV70)) -> 0.053491544 | AY70: ='[3]default rates'!$BH$321 -> 0.010871526 | AZ70: =AZ69+AY70 -> 0.020894468 | BA70: =0.12*(1-EXP(-50*$AT70))/(1-EXP(-50))+0.24*(1-(1-EXP(-50*$AT70))/(1-EXP(-50))) -> 0.13445893 | BB70: =(0.11852-0.05478*LN($AT70))^2 -> 0.085122061 | BC70: =(AZ$68*NORMSDIST((1-BA70)^(-0.5)*NORMSINV($AZ70)+(BA70/(1-BA70))^(0.5)*NORMSINV(0.999))-$AZ70*AZ$68)*((1+($B70-2.5)*BB70)/(1-1.5*BB70)) -> 0.025110531 | BE70: ='[3]default rates'!$AS$140 -> 0.020716569 | BF70: =BF69+BE70 -> 0.042323593 | BG70: =0.12*(1-EXP(-50*$AT70))/(1-EXP(-50))+0.24*(1-(1-EXP(-50*$AT70))/(1-EXP(-50))) -> 0.13445893 | BH70: =(0.11852-0.05478*LN($AT70))^2 -> 0.085122061 | BI70: =(BF$68*NORMSDIST((1-BG70)^(-0.5)*NORMSINV($BF70)+(BG70/(1-BG70))^(0.5)*NORMSINV(0.999))-$BF70*BF$68)*((1+($B70-2.5)*BH70)/(1-1.5*BH70)) -> 0.10878062 | BK70: ='[3]default rates'!$BH$321 -> 0.010871526 | BL70: =BL69+BK70 -> 0.020894468 | BM70: =0.12*(1-EXP(-50*$AT70))/(1-EXP(-50))+0.24*(1-(1-EXP(-50*$AT70))/(1-EXP(-50))) -> 0.13445893 | BN70: =(0.11852-0.05478*LN($AT70))^2 -> 0.085122061 | BO70: =(BL$68*NORMSDIST((1-BM70)^(-0.5)*NORMSINV($BL70)+(BM70/(1-BM70))^(0.5)*NORMSINV(0.999))-$BL70*BL$68)*((1+($B70-2.5)*BN70)/(1-1.5*BN70)) -> 0.07167611
B71: =$B$11 -> 3 | D71: =Q71*100 -> 0.46443329 | E71: =V71*100 -> 0.46443329 | F71: =AA71*100 -> 2.2660723 | G71: =AF71*100 -> 5.710242 | H71: =AK71*100 -> 11.068277 | I71: =AP71*100 -> 16.938679 | K71: =AW71*100 -> 6.3979966 | N71: ='[2]Moody''s Global Infra and Corp D'!$R$82 -> 3.8235787e-05 | O71: =0.12*(1-EXP(-50*$N71))/(1-EXP(-50))+0.24*(1-(1-EXP(-50*$N71))/(1-EXP(-50))) -> 0.2397708 | P71: =(0.11852-0.05478*LN($N71))^2 -> 0.45660812 | Q71: =(N$68*NORMSDIST((1-O71)^(-0.5)*NORMSINV($N71)+(O71/(1-O71))^(0.5)*NORMSINV(0.999))-$N71*N$68)*((1+($B71-2.5)*P71)/(1-1.5*P71)) -> 0.0046443329 | S71: ='[2]Moody''s Global Infra and Corp D'!$R$83 -> 3.8235787e-05 | T71: =0.12*(1-EXP(-50*$N71))/(1-EXP(-50))+0.24*(1-(1-EXP(-50*$N71))/(1-EXP(-50))) -> 0.2397708 | U71: =(0.11852-0.05478*LN($N71))^2 -> 0.45660812 | V71: =(S$68*NORMSDIST((1-T71)^(-0.5)*NORMSINV($S71)+(T71/(1-T71))^(0.5)*NORMSINV(0.999))-$S71*S$68)*((1+($B71-2.5)*U71)/(1-1.5*U71)) -> 0.0046443329 | X71: ='[2]Moody''s Global Infra and Corp D'!$R$84 -> 0.00068322084 | Y71: =0.12*(1-EXP(-50*$X71))/(1-EXP(-50))+0.24*(1-(1-EXP(-50*$X71))/(1-EXP(-50))) -> 0.2359699 | Z71: =(0.11852-0.05478*LN($X71))^2 -> 0.26811122 | AA71: =(X$68*NORMSDIST((1-Y71)^(-0.5)*NORMSINV($X71)+(Y71/(1-Y71))^(0.5)*NORMSINV(0.999))-$X71*X$68)*((1+($B71-2.5)*Z71)/(1-1.5*Z71)) -> 0.022660723 | AC71: ='[2]Moody''s Global Infra and Corp D'!$R$85 -> 0.0039262205 | AD71: =0.12*(1-EXP(-50*$AC71))/(1-EXP(-50))+0.24*(1-(1-EXP(-50*$AC71))/(1-EXP(-50))) -> 0.21861079 | AE71: =(0.11852-0.05478*LN($AC71))^2 -> 0.17808862 | AF71: =(AC$68*NORMSDIST((1-AD71)^(-0.5)*NORMSINV($AC71)+(AD71/(1-AD71))^(0.5)*NORMSINV(0.999))-$AC71*AC$68)*((1+($B71-2.5)*AE71)/(1-1.5*AE71)) -> 0.05710242 | AH71: ='[2]Moody''s Global Infra and Corp D'!$R$86 -> 0.027167425 | AI71: =0.12*(1-EXP(-50*$AH71))/(1-EXP(-50))+0.24*(1-(1-EXP(-50*$AH71))/(1-EXP(-50))) -> 0.1508495 | AJ71: =(0.11852-0.05478*LN($AH71))^2 -> 0.099882705 | AK71: =(AH$68*NORMSDIST((1-AI71)^(-0.5)*NORMSINV($AH71)+(AI71/(1-AI71))^(0.5)*NORMSINV(0.999))-$AH71*AH$68)*((1+($B71-2.5)*AJ71)/(1-1.5*AJ71)) -> 0.11068277 | AM71: ='[2]Moody''s Global Infra and Corp D'!$R$87 -> 0.10276374 | AN71: =0.12*(1-EXP(-50*$AM71))/(1-EXP(-50))+0.24*(1-(1-EXP(-50*$AM71))/(1-EXP(-50))) -> 0.1207042 | AO71: =(0.11852-0.05478*LN($AM71))^2 -> 0.059127845 | AP71: =(AM$68*NORMSDIST((1-AN71)^(-0.5)*NORMSINV($AM71)+(AN71/(1-AN71))^(0.5)*NORMSINV(0.999))-$AM71*AM$68)*((1+($B71-2.5)*AO71)/(1-1.5*AO71)) -> 0.16938679 | AS71: ='[3]default rates'!$AT$140 -> 0.014629295 | AT71: =AT70+AS71 -> 0.056952888 | AU71: =0.12*(1-EXP(-50*$AT71))/(1-EXP(-50))+0.24*(1-(1-EXP(-50*$AT71))/(1-EXP(-50))) -> 0.12695769 | AV71: =(0.11852-0.05478*LN($AT71))^2 -> 0.075896824 | AW71: =(AT$68*NORMSDIST((1-AU71)^(-0.5)*NORMSINV($AT71)+(AU71/(1-AU71))^(0.5)*NORMSINV(0.999))-$AT71*AT$68)*((1+($B71-2.5)*AV71)/(1-1.5*AV71)) -> 0.063979966 | AY71: ='[3]default rates'!$BI$321 -> 0.011705912 | AZ71: =AZ70+AY71 -> 0.03260038 | BA71: =0.12*(1-EXP(-50*$AT71))/(1-EXP(-50))+0.24*(1-(1-EXP(-50*$AT71))/(1-EXP(-50))) -> 0.12695769 | BB71: =(0.11852-0.05478*LN($AT71))^2 -> 0.075896824 | BC71: =(AZ$68*NORMSDIST((1-BA71)^(-0.5)*NORMSINV($AZ71)+(BA71/(1-BA71))^(0.5)*NORMSINV(0.999))-$AZ71*AZ$68)*((1+($B71-2.5)*BB71)/(1-1.5*BB71)) -> 0.033369839 | BE71: ='[3]default rates'!$AT$140 -> 0.014629295 | BF71: =BF70+BE71 -> 0.056952888 | BG71: =0.12*(1-EXP(-50*$AT71))/(1-EXP(-50))+0.24*(1-(1-EXP(-50*$AT71))/(1-EXP(-50))) -> 0.12695769 | BH71: =(0.11852-0.05478*LN($AT71))^2 -> 0.075896824 | BI71: =(BF$68*NORMSDIST((1-BG71)^(-0.5)*NORMSINV($BF71)+(BG71/(1-BG71))^(0.5)*NORMSINV(0.999))-$BF71*BF$68)*((1+($B71-2.5)*BH71)/(1-1.5*BH71)) -> 0.13010992 | BK71: ='[3]default rates'!$BI$321 -> 0.011705912 | BL71: =BL70+BK71 -> 0.03260038 | BM71: =0.12*(1-EXP(-50*$AT71))/(1-EXP(-50))+0.24*(1-(1-EXP(-50*$AT71))/(1-EXP(-50))) -> 0.12695769 | BN71: =(0.11852-0.05478*LN($AT71))^2 -> 0.075896824 | BO71: =(BL$68*NORMSDIST((1-BM71)^(-0.5)*NORMSINV($BL71)+(BM71/(1-BM71))^(0.5)*NORMSINV(0.999))-$BL71*BL$68)*((1+($B71-2.5)*BN71)/(1-1.5*BN71)) -> 0.095251682
B72: =$B$12 -> 4 | D72: =Q72*100 -> 0.6370811 | E72: =V72*100 -> 0.6370811 | F72: =AA72*100 -> 2.8018127 | G72: =AF72*100 -> 7.2891744 | H72: =AK72*100 -> 13.425497 | I72: =AP72*100 -> 19.53529 | K72: =AW72*100 -> 7.2279461 | N72: ='[2]Moody''s Global Infra and Corp D'!$S$82 -> 3.8235787e-05 | O72: =0.12*(1-EXP(-50*$N72))/(1-EXP(-50))+0.24*(1-(1-EXP(-50*$N72))/(1-EXP(-50))) -> 0.2397708 | P72: =(0.11852-0.05478*LN($N72))^2 -> 0.45660812 | Q72: =(N$68*NORMSDIST((1-O72)^(-0.5)*NORMSINV($N72)+(O72/(1-O72))^(0.5)*NORMSINV(0.999))-$N72*N$68)*((1+($B72-2.5)*P72)/(1-1.5*P72)) -> 0.006370811 | S72: ='[2]Moody''s Global Infra and Corp D'!$S$83 -> 3.8235787e-05 | T72: =0.12*(1-EXP(-50*$N72))/(1-EXP(-50))+0.24*(1-(1-EXP(-50*$N72))/(1-EXP(-50))) -> 0.2397708 | U72: =(0.11852-0.05478*LN($N72))^2 -> 0.45660812 | V72: =(S$68*NORMSDIST((1-T72)^(-0.5)*NORMSINV($S72)+(T72/(1-T72))^(0.5)*NORMSINV(0.999))-$S72*S$68)*((1+($B72-2.5)*U72)/(1-1.5*U72)) -> 0.006370811 | X72: ='[2]Moody''s Global Infra and Corp D'!$S$84 -> 0.00068322084 | Y72: =0.12*(1-EXP(-50*$X72))/(1-EXP(-50))+0.24*(1-(1-EXP(-50*$X72))/(1-EXP(-50))) -> 0.2359699 | Z72: =(0.11852-0.05478*LN($X72))^2 -> 0.26811122 | AA72: =(X$68*NORMSDIST((1-Y72)^(-0.5)*NORMSINV($X72)+(Y72/(1-Y72))^(0.5)*NORMSINV(0.999))-$X72*X$68)*((1+($B72-2.5)*Z72)/(1-1.5*Z72)) -> 0.028018127 | AC72: ='[2]Moody''s Global Infra and Corp D'!$S$85 -> 0.0049077757 | AD72: =0.12*(1-EXP(-50*$AC72))/(1-EXP(-50))+0.24*(1-(1-EXP(-50*$AC72))/(1-EXP(-50))) -> 0.21388804 | AE72: =(0.11852-0.05478*LN($AC72))^2 -> 0.16792102 | AF72: =(AC$68*NORMSDIST((1-AD72)^(-0.5)*NORMSINV($AC72)+(AD72/(1-AD72))^(0.5)*NORMSINV(0.999))-$AC72*AC$68)*((1+($B72-2.5)*AE72)/(1-1.5*AE72)) -> 0.072891744 | AH72: ='[2]Moody''s Global Infra and Corp D'!$S$86 -> 0.041341734 | AI72: =0.12*(1-EXP(-50*$AH72))/(1-EXP(-50))+0.24*(1-(1-EXP(-50*$AH72))/(1-EXP(-50))) -> 0.13518647 | AJ72: =(0.11852-0.05478*LN($AH72))^2 -> 0.085874 | AK72: =(AH$68*NORMSDIST((1-AI72)^(-0.5)*NORMSINV($AH72)+(AI72/(1-AI72))^(0.5)*NORMSINV(0.999))-$AH72*AH$68)*((1+($B72-2.5)*AJ72)/(1-1.5*AJ72)) -> 0.13425497 | AM72: ='[2]Moody''s Global Infra and Corp D'!$S$87 -> 0.13583713 | AN72: =0.12*(1-EXP(-50*$AM72))/(1-EXP(-50))+0.24*(1-(1-EXP(-50*$AM72))/(1-EXP(-50))) -> 0.12013475 | AO72: =(0.11852-0.05478*LN($AM72))^2 -> 0.051928038 | AP72: =(AM$68*NORMSDIST((1-AN72)^(-0.5)*NORMSINV($AM72)+(AN72/(1-AN72))^(0.5)*NORMSINV(0.999))-$AM72*AM$68)*((1+($B72-2.5)*AO72)/(1-1.5*AO72)) -> 0.1953529 | AS72: ='[3]default rates'!$AU$140 -> 0.0099097921 | AT72: =AT71+AS72 -> 0.06686268 | AU72: =0.12*(1-EXP(-50*$AT72))/(1-EXP(-50))+0.24*(1-(1-EXP(-50*$AT72))/(1-EXP(-50))) -> 0.12423913 | AV72: =(0.11852-0.05478*LN($AT72))^2 -> 0.071132177 | AW72: =(AT$68*NORMSDIST((1-AU72)^(-0.5)*NORMSINV($AT72)+(AU72/(1-AU72))^(0.5)*NORMSINV(0.999))-$AT72*AT$68)*((1+($B72-2.5)*AV72)/(1-1.5*AV72)) -> 0.072279461 | AY72: ='[3]default rates'!$BJ$321 -> 0.010082874 | AZ72: =AZ71+AY72 -> 0.042683254 | BA72: =0.12*(1-EXP(-50*$AT72))/(1-EXP(-50))+0.24*(1-(1-EXP(-50*$AT72))/(1-EXP(-50))) -> 0.12423913 | BB72: =(0.11852-0.05478*LN($AT72))^2 -> 0.071132177 | BC72: =(AZ$68*NORMSDIST((1-BA72)^(-0.5)*NORMSINV($AZ72)+(BA72/(1-BA72))^(0.5)*NORMSINV(0.999))-$AZ72*AZ$68)*((1+($B72-2.5)*BB72)/(1-1.5*BB72)) -> 0.04049577 | BE72: ='[3]default rates'!$AU$140 -> 0.0099097921 | BF72: =BF71+BE72 -> 0.06686268 | BG72: =0.12*(1-EXP(-50*$AT72))/(1-EXP(-50))+0.24*(1-(1-EXP(-50*$AT72))/(1-EXP(-50))) -> 0.12423913 | BH72: =(0.11852-0.05478*LN($AT72))^2 -> 0.071132177 | BI72: =(BF$68*NORMSDIST((1-BG72)^(-0.5)*NORMSINV($BF72)+(BG72/(1-BG72))^(0.5)*NORMSINV(0.999))-$BF72*BF$68)*((1+($B72-2.5)*BH72)/(1-1.5*BH72)) -> 0.1469878 | BK72: ='[3]default rates'!$BJ$321 -> 0.010082874 | BL72: =BL71+BK72 -> 0.042683254 | BM72: =0.12*(1-EXP(-50*$AT72))/(1-EXP(-50))+0.24*(1-(1-EXP(-50*$AT72))/(1-EXP(-50))) -> 0.12423913 | BN72: =(0.11852-0.05478*LN($AT72))^2 -> 0.071132177 | BO72: =(BL$68*NORMSDIST((1-BM72)^(-0.5)*NORMSINV($BL72)+(BM72/(1-BM72))^(0.5)*NORMSINV(0.999))-$BL72*BL$68)*((1+($B72-2.5)*BN72)/(1-1.5*BN72)) -> 0.11559211
